Workbook
Name Slicer_Gender: #N/A
Name Slicer_Gender1: #N/A
Name Slicer_Payment_Type: #N/A
Name Slicer_Payment_Type1: #N/A
Name Slicer_Region: #N/A
Name Slicer_Region1: #N/A
Name Slicer_Years__Order_Date: #N/A
Name Slicer_Years__Order_Date1: #N/A

Sheet Customer_Dim
A1: Customer_ID | B1: Name | C1: Age | D1: Gender | E1: City | F1: State | G1: Country | H1: Loyalty_Level
A2: CUST1000 | B2: sheena bonilla | C2: 55 | D2: Male | E2: Donaldton | F2: North Carolina | G2: USA
A3: CUST1001 | B3: Eugene Nelson | C3: 26 | D3: Female | E3: Phillipsmouth | F3: North Dakota | G3: USA | H3: Platinum
A4: CUST1002 | B4: dr. Benjamin Price | C4: 29 | D4: Female | E4: Kylebury | F4: Alabama | G4: USA | H4: Platinum
A5: CUST1003 | B5: jeremy harris | C5: 59 | D5: Female | E5: Thomastown | F5: Ohio | G5: USA | H5: Bronze
A6: CUST1004 | B6: Caroline Collins | C6: 64 | D6: Female | E6: Nicholasshire | F6: California | G6: USA | H6: Silver
A7: CUST1005 | B7: Christine Vaughn | C7: 24 | D7: Male | E7: East Amandamouth | F7: Oregon | G7: USA | H7: Bronze
A8: CUST1006 | B8: Amber Jackson | C8: 29 | D8: Female | E8: Deborahborough | F8: South Dakota | G8: USA | H8: Platinum
A9: CUST1007 | B9: Daniel Boyd | C9: 29 | D9: Female | E9: West Pamelafurt | F9: West Virginia | G9: USA | H9: Bronze
A10: CUST1008 | B10: Melissa Howard | C10: 53 | D10: Female | E10: Maynardton | F10: New Hampshire | G10: USA | H10: Gold
A11: CUST1009 | B11: Ms. Maria Leach | C11: 64 | D11: Male | E11: Melissashire | F11: Pennsylvania | G11: USA | H11: Platinum
A12: CUST1010 | B12: Dominic Page | C12: 53 | D12: Male | E12: Port Michaelburgh | F12: Pennsylvania | G12: USA | H12: Bronze
A13: CUST1011 | B13: Brian Lopez | C13: 28 | D13: Female | E13: East Krista | F13: New York | G13: USA | H13: Gold
A14: CUST1012 | B14: Kenneth Lambert | C14: 55 | D14: Female | E14: North Kathryn | F14: Kansas | G14: USA | H14: Platinum
... A19: CUST1017 | B19: Adam Cruz | C19: 60 | D19: Female | E19: Brandonville | F19: Georgia | G19: USA | H19: Platinum
A20: CUST1018 | B20: Rhonda Moss | C20: 43 | D20: Male | E20: South William | F20: Kansas | G20: USA
A21: CUST1019 | B21: Michael Torres | C21: 46 | D21: Female | E21: Gonzalezfort | F21: New Jersey | G21: USA | H21: Platinum
A22: CUST1020 | B22: Bridget Allen | C22: 59 | D22: Male | E22: Lake Shaneburgh | F22: Delaware | G22: USA | H22: Silver
A23: CUST1021 | B23: Jeff Martinez | C23: 36 | D23: Female | E23: Smithburgh | F23: Oklahoma | G23: USA | H23: Gold
A24: CUST1022 | B24: paul fox | C24: 33 | D24: Female | E24: Michaelton | F24: Hawaii | G24: USA | H24: Silver
A25: CUST1023 | B25: Jonathan Steele | C25: 52 | D25: Female | E25: Molinabury | F25: Oregon | G25: USA | H25: Silver
A26: CUST1024 | B26: Heather Collins | C26: 40 | D26: Male | E26: Rogerschester | F26: Idaho | G26: USA | H26: Platinum
A27: CUST1025 | B27: Diana Taylor | C27: 59 | D27: Female | E27: Vasqueztown | F27: California | G27: USA | H27: Bronze
A28: CUST1026 | B28: Amber Carlson | C28: 18 | D28: Female | E28: East Michellemouth | F28: Missouri | G28: USA | H28: Gold
A29: CUST1027 | B29: Leslie Johnson | C29: 31 | D29: Male | E29: Mollyshire | F29: Utah | G29: USA
A30: CUST1028 | B30: Joshua Ryan | C30: 27 | D30: Female | E30: New David | F30: New Jersey | G30: USA | H30: Platinum
A31: CUST1029 | B31: David Arnold | C31: 54 | D31: Female | E31: East Jennifer | F31: California | G31: USA | H31: Silver
A32: CUST1030 | B32: Jessica Acevedo | C32: 64 | D32: Female | E32: Amybury | F32: Pennsylvania | G32: USA | H32: Bronze
A33: CUST1031 | B33: Sarah Vance | C33: 41 | D33: Male | E33: Johnsonville | F33: Oregon | G33: USA | H33: Silver
A34: CUST1032 | B34: Mike Jennings | C34: 48 | D34: Female | E34: Fostermouth | F34: Arizona | G34: USA | H34: Gold
A35: CUST1033 | B35: Robert Jones DDS | C35: 25 | D35: Male | E35: Tristanton | F35: Oklahoma | G35: USA | H35: Platinum
A36: CUST1034 | B36: Christopher Olson | C36: 27 | D36: Female | E36: West Richard | F36: Maryland | G36: USA | H36: Platinum
A37: CUST1035 | B37: Rachel Myers | C37: 52 | D37: Male | E37: Robertberg | F37: North Dakota | G37: USA | H37: Silver
A38: CUST1036 | B38: Thomas Phillips | C38: 20 | D38: Female | E38: Luisfurt | F38: Georgia | G38: USA | H38: Gold
A39: CUST1037 | B39: Christopher Carter | C39: 27 | D39: Female | E39: Brendastad | F39: South Dakota | G39: USA
A40: CUST1038 | B40: Deanna Simpson | C40: 35 | D40: Female | E40: Brownport | F40: North Dakota | G40: USA | H40: Bronze
A41: CUST1039 | B41: Tonya Reynolds | C41: 55 | D41: Female | E41: Darleneton | F41: Michigan | G41: USA | H41: Gold
A42: CUST1040 | B42: Eric Vega | C42: 50 | D42: Male | E42: Williamsonland | F42: Kansas | G42: USA | H42: Gold
A43: CUST1041 | B43: James Gibbs | C43: 21 | D43: Male | E43: Mooneyshire | F43: Alaska | G43: USA | H43: Platinum
A44: CUST1042 | B44: William Martin | C44: 19 | D44: Male | E44: Ryanburgh | F44: Connecticut | G44: USA | H44: Platinum
A45: CUST1043 | B45: Joseph Snow | C45: 45 | D45: Male | E45: South Michaelfort | F45: Vermont | G45: USA | H45: Gold
A46: CUST1044 | B46: Denise Williams | C46: 34 | D46: Male | E46: Christianstad | F46: Hawaii | G46: USA | H46: Bronze
A47: CUST1045 | B47: Jordan Jackson DDS | C47: 54 | D47: Male | E47: North Johnview | F47: Arizona | G47: USA | H47: Gold
A48: CUST1046 | B48: Michelle Garcia DDS | C48: 55 | D48: Female | E48: Perezbury | F48: Ohio | G48: USA | H48: Platinum
A49: CUST1047 | B49: Gina Knight | C49: 54 | D49: Female | E49: Lake Roberthaven | F49: Nevada | G49: USA | H49: Silver
A50: CUST1048 | B50: April Mullins | C50: 54 | D50: Male | E50: Dawsonbury | F50: North Carolina | G50: USA | H50: Platinum
A51: CUST1049 | B51: Timothy Weaver | C51: 45 | D51: Female | E51: New Amy | F51: Ohio | G51: USA | H51: Gold
... A501: C-1499 | B501: Philip Pennington | C501: 27 | D501: Female | E501: East Valerieview | F501: Oregon | G501: USA | H501: Platinum

Sheet Product_Dim
A1: Product_ID | B1: Product_Name | C1: Category | D1: Sub_Category | E1: Brand | F1: Cost | G1: Stock
A2: PROD0 | B2: Brother Laser Printer | C2: Electronics | D2: Computer | E2: Hunt Inc | F2: 112.42 | G2: 416
A3: PROD1 | B3: Men's Graphic T-Shirt | C3: Clothing | D3: Tops | E3: Terry-Moore | F3: 342.56 | G3: 181
A4: PROD2 | B4: Women's Casual Hoodie | C4: Clothing | D4: Outerwear | E4: Sims Inc | G4: 352
A5: P-3 | B5: Men's Running Jacket | C5: Clothing | D5: Outerwear | E5: Pineda Ltd | F5: 364.67 | G5: 452
A6: PROD4 | B6: Women's Yoga Pants | C6: Clothing | D6: Bottoms | E6: Gonzales-Davis | F6: 306.46 | G6: 487
A7: PROD5 | B7: Men's Leather Belt | C7: Clothing | D7: Accessories | E7: Baldwin, Garza and Gonzalez | F7: 261 | G7: 59
A8: PROD6 | B8: Herbal Face Moisturizer | C8: Beauty | D8: Skincare | E8: Davidson PLC | F8: 312.8 | G8: 350
A9: PROD7 | B9: LED Table Lamp | C9: Home | D9: Lighting | E9: Harrell LLC | F9: 218.86 | G9: 170
A10: PROD8 | B10: Wireless Bluetooth Earbuds | C10: Electronics | D10: Audio | E10: Perez-Johnston | F10: 439.07 | G10: 142
A11: PROD9 | B11: Adjustable Dumbbell Set | C11: Sports | D11: Fitness | E11: Hill PLC | F11: 495.72 | G11: 323
A12: PROD10 | B12: Ceramic Kitchen Bowl Set | C12: Home | D12: Kitchen | E12: Hamilton Group | F12: 298.86 | G12: 308
A13: PROD11 | B13: HD Smart TV Stick | C13: Electronics | D13: Accessories | E13: Gibson, Hobbs and Weaver | F13: 449.4
A14: PROD12 | B14: Hair Strengthening Shampoo | C14: Beauty | D14: Haircare | E14: Rice LLC | F14: 115.82 | G14: 460
A15: PROD13 | B15: USB-C Fast Charger | C15: Electronics | D15: Accessories | E15: Dawson-Perkins | F15: 242.23 | G15: 453
A16: PROD14 | B16: Decorative Wall Mirror | C16: Home | D16: Decor | E16: Luna, Anderson and Bowman | F16: 48.01 | G16: 439
A17: PROD15 | B17: 4K Home Projector | C17: Electronics | D17: Appliances | E17: Thomas LLC | F17: 465.34 | G17: 301
A18: P-16 | B18: Beard Grooming Kit | C18: Beauty | D18: Grooming | E18: Erickson-Green | F18: 337.42 | G18: 256
A19: PROD17 | B19: Soccer Training Cone Set | C19: Sports | D19: Accessories | E19: Ford, Murphy and Wilson | F19: 144.53 | G19: 367
A20: PROD18 | B20: Women's Denim Jeans | C20: Clothing | D20: Bottoms | E20: Guerra-Hendrix | G20: 343
A21: PROD19 | B21: Knee Support Brace | C21: Sports | D21: Equipment | E21: May-Reese | F21: 21.34 | G21: 65
A22: PROD20 | B22: Outdoor Sports Water Bottle | C22: Sports | D22: Accessories | E22: Soto-Ellis | F22: 131.51
A23: PROD21 | B23: Multi-Purpose Storage Box | C23: Home | D23: Storage | E23: Gardner-Montes | F23: 123.46 | G23: 76
A24: PROD22 | B24: Carbon Fiber Tennis Racket | C24: Sports | D24: Equipment | E24: Flores, Pineda and Rodriguez | F24: 484.62 | G24: 432
A25: PROD23 | B25: Men's Formal Shirt | C25: Clothing | D25: Tops | E25: Moon, Mora and Santos | G25: 360
A26: PROD24 | B26: Foldable Camping Chair | C26: Sports | D26: Outdoor | E26: Cook Ltd | F26: 166.06 | G26: 340
A27: PROD25 | B27: Women's Scarf Set | C27: Clothing | D27: Accessories | E27: Brown and Sons | F27: 174.02 | G27: 268
A28: PROD26 | B28: Wireless Bluetooth Speaker | C28: Electronics | D28: Audio | E28: Reed-Schmidt | F28: 322.41 | G28: 213
A29: PROD27 | B29: Decorative Floor Vase | C29: Home | D29: Decor | E29: Khan, Jones and Paul | G29: 378
A30: PROD28 | B30: Sports Stopwatch Timer | C30: Sports | D30: Accessories | E30: Burns-Hansen | F30: 38.76 | G30: 137
A31: PROD29 | B31: Fabric Sofa Throw Blanket | C31: Home | D31: Decor | E31: Hoffman Group | F31: 218.48 | G31: 276
A32: PROD30 | B32: Stainless Steel Cutlery Set | C32: Home | D32: Kitchen | E32: Stevens, Fernandez and Martin | F32: 19.52 | G32: 57
A33: PROD31 | B33: Basketball | C33: Sports | D33: Team Sports | E33: Nolan-Snow | F33: 204.39 | G33: 281
A34: PROD32 | B34: Vitamin C Face Serum | C34: Beauty | D34: Skincare | E34: Griffin Ltd | F34: 283.83 | G34: 244
A35: PROD33 | B35: Modern Wall Clock | C35: Home | D35: Decor | E35: Weiss-Watson | F35: 179.77 | G35: 305
A36: PROD34 | B36: Gaming Mechanical Keyboard | C36: Electronics | D36: Computer | E36: Lucero LLC | F36: 419.28 | G36: 86
A37: PROD35 | B37: Bedroom Table Lamp | C37: Home | D37: Lighting | E37: Jones LLC | F37: 382.22 | G37: 329
A38: PROD36 | B38: Women's Summer Dress | C38: Clothing | D38: Tops | E38: Smith-Mills | F38: 223.43 | G38: 154
A39: PROD37 | B39: Men's Casual Sneakers | C39: Clothing | D39: Footwear | E39: Hogan-Lee | F39: 353.47 | G39: 214
A40: PROD38 | B40: Sports Water Hydration Pack | C40: Sports | D40: Outdoor | E40: Sims-Smith | F40: 135.61 | G40: 394
A41: PROD39 | B41: Portable Power Bank | C41: Electronics | D41: Mobile | E41: Cummings and Sons | F41: 326.06 | G41: 301
... A48: PROD46 | B48: Men's Winter Jacket | C48: Clothing | D48: Outerwear | E48: Kelly, Smith and Perez | F48: 167.34 | G48: 296
A49: PROD47 | B49: Makeup Brush Set | C49: Beauty | D49: Makeup | E49: Cook Inc | G49: 431
A50: PROD48 | B50: Car Dashboard Phone Holder | C50: Electronics | D50: Accessories | E50: Byrd, Stewart and Valdez | F50: 177.98 | G50: 103
A51: PROD49 | B51: Men's Roll-On Perfume | C51: Beauty | D51: Fragrance | E51: Sullivan and Sons | F51: 43.29 | G51: 267
A52: PROD50 | B52: Boxing Hand Wraps | C52: Sports | D52: Fitness | E52: Smith-King | F52: 190.29 | G52: 260
A53: PROD51 | B53: HDMI Cable – 2m | C53: Electronics | D53: Accessories | E53: Bautista, Green and Hale | F53: 88.49 | G53: 246
A54: PROD52 | B54: Rugby Ball | C54: Sports | D54: Team Sports | E54: Harris Inc | F54: 212.26 | G54: 82
A55: PROD53 | B55: Men's Track Pants | C55: Clothing | D55: Bottoms | E55: Hamilton, Woods and Walker | F55: 386.56 | G55: 125
A56: PROD54 | B56: Sports Stopwatch Pro | C56: Sports | D56: Accessories | E56: Thompson-French | F56: 434.84 | G56: 185
A57: PROD55 | B57: Ceramic Plant Pot | C57: Home | D57: Decor | E57: Hatfield, Baird and Torres | F57: 81.75
A58: PROD56 | B58: Premium Blanket Throw | C58: Home | D58: Decor | E58: Hernandez, Kennedy and Porter | F58: 461.47 | G58: 190
A59: PROD57 | B59: Foam Roller | C59: Sports | D59: Fitness | E59: Atkinson, Camacho and Oliver | F59: 30.62 | G59: 138
A60: PROD58 | B60: Womens Cotton Scarf | C60: Clothing | D60: Accessories | E60: Shepherd-Gould | F60: 113.83 | G60: 485
A61: PROD59 | B61: Men's Hair Styling Gel | C61: Beauty | D61: Haircare | E61: Cline-Mccarthy | F61: 17.31 | G61: 399
A62: PROD60 | B62: Luxury Perfume Spray | C62: Beauty | D62: Fragrance | E62: Gibson, Green and Lopez | F62: 482.75 | G62: 444
A63: PROD61 | B63: Tennis Ball 3-Pack | C63: Sports | D63: Equipment | E63: Lopez LLC | F63: 103.45 | G63: 465
A64: PROD62 | B64: Laptop Cooling Pad | C64: Electronics | D64: Computer | E64: Murray, Gould and Ware | F64: 86.42 | G64: 222
A65: PROD63 | B65: Organic Sunscreen Lotion | C65: Beauty | D65: Skincare | E65: Anderson-Riley | F65: 266.86 | G65: 458
A66: PROD64 | B66: Matte Lipstick Set | C66: Beauty | D66: Makeup | E66: Zhang Inc | F66: 299.11 | G66: 118
A67: PROD65 | B67: Adjustable Dumbbells 20kg | C67: Sports | D67: Fitness | E67: Montgomery, Benton and Miller | F67: 240.63 | G67: 423
A68: PROD66 | B68: Women's Hair Dryer Brush | C68: Beauty | D68: Haircare | E68: Torres, Spencer and Potter | F68: 340.39 | G68: 177
A69: PROD67 | B69: Smart LED Light Strip | C69: Electronics | D69: Accessories | E69: Flores-Davis | F69: 349.17 | G69: 476
... A84: PROD82 | B84: Fitness Resistance Bands | C84: Sports | D84: Fitness | E84: Reese-Watson | F84: 152.92 | G84: 281
A85: PROD83 | B85: Hydrating Face Cleanser | C85: Beauty | D85: Skincare | E85: Butler Group | G85: 159
A86: PROD84 | B86: Wooden Bookshelf | C86: Home | D86: Furniture | E86: Collins-Stephenson | F86: 388.46 | G86: 208
A87: PROD85 | B87: Women's Beanie Hat | C87: Clothing | D87: Accessories | E87: Richardson-Carrillo | F87: 119.57 | G87: 210
A88: PROD86 | B88: Kitchen Cutting Board | C88: Home | D88: Kitchen | E88: Taylor, Dodson and Johnston | F88: 176.07 | G88: 82
A89: PROD87 | B89: LED Bedside Lamp | C89: Home | D89: Lighting | E89: Aguilar, Horton and Lewis | F89: 371.38 | G89: 220
A90: PROD88 | B90: Sports Wrist Sweatbands | C90: Sports | D90: Accessories | E90: Olsen-Daniels | F90: 131.24 | G90: 232
A91: PROD89 | B91: Face Foundation Kit | C91: Beauty | D91: Makeup | E91: Taylor-Elliott | F91: 183.04 | G91: 457
A92: PROD90 | B92: Gaming Mouse Pad XL | C92: Electronics | D92: Accessories | E92: Sharp, Taylor and Rodriguez | F92: 340.14 | G92: 361
A93: PROD91 | B93: Women's High Heels | C93: Clothing | D93: Footwear | E93: Smith-Charles | F93: 438.25 | G93: 496
A94: PROD92 | B94: Microwave Oven | C94: Home | D94: Appliances | E94: Green, Powell and Palmer | F94: 447.43 | G94: 191
A95: PROD93 | B95: USB-C Laptop Charger | C95: Electronics | D95: Computer | E95: Martin LLC | F95: 377.52 | G95: 485
A96: PROD94 | B96: Vitamin E Body Lotion | C96: Beauty | D96: Skincare | E96: Hoffman-Williams | F96: 358.47 | G96: 213
A97: PROD95 | B97: Sports Stopwatch Basic | C97: Sports | D97: Accessories | E97: Wilson Group | F97: 60.65 | G97: 75
... A101: PROD99 | B101: Stainless Steel Cookware Set | C101: Home | D101: Kitchen | E101: Campbell Ltd | F101: 201.41 | G101: 146

Sheet Store_Dim
A1: Store_ID | B1: Store_Name | C1: Region | D1: City | E1: Store_Type
A2: STORE0 | B2: Rivera-Warner | C2: East | D2: Washingtonfurt | E2: Flagship
A3: STORE1 | B3: Martinez, Adkins and Johnson | C3: North | D3: Danielmouth | E3: Flagship
A4: STORE2 | B4: Black-Horn | C4: South | D4: North Nancyview | E4: Outlet
A5: STORE3 | B5: Johnson-Wright | C5: North | D5: Hoodberg | E5: Outlet
A6: STORE4 | B6: Alexander Group | C6: South | D6: Port Sharon | E6: Online
A7: STORE5 | B7: Gray Ltd | C7: North | D7: New Michaelchester | E7: Outlet
A8: STORE6 | B8: Benson-Elliott | C8: East | D8: Port Josephberg | E8: Online
A9: STORE7 | B9: Martinez-Mullins | C9: South | D9: Williamsfurt | E9: Online
A10: STORE8 | B10: Bean, Jones and Park | C10: West | D10: Thompsonborough | E10: Online
A11: STORE9 | B11: Moore, Padilla and Butler | C11: South | D11: East Johnstad | E11: Flagship
A12: STORE10 | B12: Hill, Wagner and Ballard | C12: East | D12: East Davidville | E12: Online
... A21: STORE19 | B21: Mann-Austin | C21: East | D21: Vasquezborough | E21: Online

Sheet Sales_Fact
A1: Sales_ID | B1: Order_Date | C1: Customer_ID | D1: Product_ID | E1: Store_ID | F1: Quantity | G1: Unit_Price | H1: Discount | I1: Payment_Type | J1: Total_Amount
A2: SALE0 | B2: 45480 | C2: CUST1409 | D2: PROD97 | E2: STORE3 | F2: 1 | G2: 218.04 | H2: 0.09 | I2: Credit Card | J2: 198.4164
A3: SALE1 | B3: 45285 | C3: CUST1467 | D3: PROD74 | E3: STORE17 | F3: 3 | G3: 104.47 | H3: 0.27 | I3: PayPal | J3: 228.7893
A4: SALE2 | B4: 45446 | C4: CUST1056 | D4: PROD49 | E4: STORE8 | F4: 4 | G4: 914.05 | H4: 0.25 | I4: Credit Card | J4: 2742.15
A5: SALE3 | B5: 45259 | C5: CUST1346 | D5: PROD76 | E5: STORE8 | F5: 1 | G5: 921.51 | H5: 0.16 | I5: COD | J5: 774.0684
A6: SALE4 | B6: 45297 | C6: CUST1493 | D6: PROD59 | E6: STORE5 | F6: 3 | G6: 745.3 | H6: 0.18 | I6: Credit Card | J6: 1833.438
A7: SALE5 | B7: 45499 | C7: CUST1116 | D7: PROD15 | E7: STORE7 | F7: 3 | G7: 147.01 | H7: 0.19 | I7: COD | J7: 357.2343
A8: SALE6 | B8: 45850 | C8: CUST1016 | D8: PROD56 | E8: STORE4 | F8: 2 | G8: 785.31 | H8: 0.15 | I8: PayPal | J8: 1335.027
A9: SALE7 | B9: 45248 | C9: CUST1152 | D9: PROD70 | E9: STORE8 | F9: 4 | G9: 342.39 | H9: 0.23 | I9: PayPal | J9: 1054.5612
A10: SALE8 | B10: 45781 | C10: CUST1187 | D10: PROD99 | E10: STORE5 | G10: 448.25 | H10: 0.07 | I10: PayPal | J10: 1250.6175
A11: SALE9 | B11: 45869 | C11: CUST1464 | D11: PROD33 | E11: STORE0 | F11: 2 | G11: 873.17 | H11: 0.23 | I11: PayPal | J11: 1344.6818
A12: SALE10 | B12: 45335 | C12: CUST1065 | D12: PROD24 | E12: STORE14 | F12: 1 | G12: 278.63 | H12: 0.07 | I12: Credit Card | J12: 259.1259
A13: SALE11 | B13: 45801 | C13: CUST1320 | D13: PROD39 | E13: STORE1 | F13: 4 | G13: 286.92 | H13: 0.17 | I13: Credit Card | J13: 952.5744
A14: SALE12 | B14: 45528 | C14: CUST1237 | D14: PROD88 | E14: STORE4 | F14: 4 | G14: 644.58 | H14: 0.01 | I14: Credit Card | J14: 2552.5368
A15: SALE13 | B15: 45875 | C15: CUST1443 | D15: PROD34 | E15: STORE16 | F15: 2 | G15: 316.9 | H15: 0.3 | I15: PayPal | J15: 443.66
A16: SALE14 | B16: 45829 | C16: CUST1348 | D16: PROD24 | E16: STORE15 | F16: 4 | G16: 403.47 | H16: 0.29 | I16: PayPal | J16: 1145.8548
A17: SALE15 | B17: 45636 | C17: CUST1435 | D17: PROD36 | E17: STORE9 | G17: 871.34 | H17: 0.04 | I17: COD | J17: 2509.4592
A18: SALE16 | B18: 45913 | C18: CUST1276 | D18: PROD65 | E18: STORE19 | F18: 2 | G18: 451.98 | H18: 0.25 | I18: Credit Card | J18: 677.97
A19: SALE17 | B19: 45637 | C19: CUST1079 | D19: PROD27 | E19: STORE4 | F19: 2 | G19: 502.69 | H19: 0.23 | I19: Credit Card | J19: 774.1426
A20: SALE18 | B20: 45517 | C20: CUST1094 | D20: PROD39 | E20: STORE4 | F20: 2 | G20: 559.23 | H20: 0.25 | I20: COD | J20: 838.845
A21: SALE19 | B21: 45369 | C21: CUST1239 | D21: PROD60 | E21: STORE13 | F21: 4 | H21: 0.04 | I21: COD | J21: 1782.4512
A22: SALE20 | B22: 45843 | C22: CUST1144 | D22: PROD72 | E22: STORE17 | F22: 3 | G22: 986.04 | H22: 0.27 | I22: COD | J22: 2159.4276
A23: SALE21 | B23: 45447 | C23: CUST1396 | D23: PROD43 | E23: STORE18 | F23: 1 | G23: 589.56 | H23: 0.22 | I23: Credit Card | J23: 459.8568
A24: SALE22 | B24: 45394 | C24: CUST1476 | D24: PROD69 | E24: STORE10 | F24: 3 | G24: 979.42 | H24: 0.03 | I24: PayPal | J24: 2850.1122
A25: SALE23 | B25: 45466 | C25: CUST1368 | D25: PROD12 | E25: STORE8 | F25: 1 | G25: 719.28 | H25: 0.08 | I25: Credit Card | J25: 661.7376
A26: SALE24 | B26: 45908 | C26: CUST1186 | D26: PROD67 | E26: STORE6 | F26: 3 | G26: 77.6 | H26: 0.07 | I26: Credit Card | J26: 216.504
A27: SALE25 | B27: 45552 | C27: CUST1381 | D27: PROD5 | E27: STORE3 | F27: 4 | G27: 852.71 | H27: 0.14 | I27: PayPal | J27: 2933.3224
A28: SALE26 | B28: 45294 | C28: CUST1213 | D28: PROD98 | E28: STORE8 | F28: 4 | G28: 156.16 | I28: Credit Card | J28: 599.6544
A29: SALE27 | B29: 45710 | C29: CUST1200 | D29: PROD77 | E29: STORE8 | F29: 3 | G29: 815.49 | H29: 0.17 | I29: Credit Card | J29: 2030.5701
A30: SALE28 | B30: 45923 | C30: CUST1148 | D30: PROD13 | E30: STORE2 | F30: 2 | G30: 74.21 | H30: 0.11 | I30: PayPal | J30: 132.0938
A31: SALE29 | B31: 45302 | C31: CUST1348 | D31: PROD99 | E31: STORE3 | G31: 451.67 | H31: 0.15 | I31: Credit Card | J31: 1535.678
A32: SALE30 | B32: 45217 | C32: CUST1028 | D32: PROD5 | E32: STORE19 | F32: 1 | G32: 429.38 | H32: 0.13 | I32: PayPal | J32: 373.5606
A33: SALE31 | B33: 45593 | C33: CUST1412 | D33: PROD53 | E33: STORE12 | F33: 2 | G33: 148.96 | H33: 0.03 | I33: COD | J33: 288.9824
A34: SALE32 | B34: 45597 | C34: CUST1398 | D34: PROD75 | E34: STORE8 | F34: 4 | G34: 313.83 | H34: 0.08 | I34: Credit Card | J34: 1154.8944
A35: SALE33 | B35: 45620 | C35: CUST1453 | D35: PROD12 | E35: STORE6 | F35: 2 | G35: 717.31 | H35: 0.15 | I35: Credit Card | J35: 1219.427
A36: SALE34 | B36: 45215 | C36: CUST1344 | D36: PROD79 | E36: STORE1 | G36: 873.22 | H36: 0.18 | I36: Credit Card | J36: 2148.1212
A37: SALE35 | B37: 45878 | C37: CUST1218 | D37: PROD16 | E37: STORE3 | F37: 4 | G37: 109.36 | H37: 0.19 | I37: COD | J37: 354.3264
A38: SALE36 | B38: 45635 | C38: CUST1086 | D38: PROD5 | E38: STORE7 | F38: 3 | G38: 559.52 | H38: 0.16 | I38: PayPal | J38: 1409.9904
A39: SALE37 | B39: 45329 | C39: CUST1492 | D39: PROD10 | E39: STORE17 | F39: 3 | G39: 121.76 | H39: 0.27 | I39: PayPal | J39: 266.6544
A40: SALE38 | B40: 45378 | C40: CUST1189 | D40: PROD33 | E40: STORE13 | F40: 4 | G40: 735.32 | H40: 0.06 | I40: COD | J40: 2764.8032
A41: SALE39 | B41: 45264 | C41: CUST1431 | D41: PROD94 | E41: STORE3 | F41: 2 | G41: 600.73 | H41: 0.08 | I41: Credit Card | J41: 1105.3432
A42: SALE40 | B42: 45486 | C42: CUST1072 | D42: PROD26 | E42: STORE19 | F42: 2 | G42: 873.86 | H42: 0.07 | I42: COD | J42: 1625.3796
A43: SALE41 | B43: 45241 | C43: CUST1302 | D43: PROD23 | E43: STORE8 | F43: 3 | G43: 342.47 | H43: 0.08 | I43: PayPal | J43: 945.2172
A44: SALE42 | B44: 45649 | C44: CUST1335 | D44: PROD29 | E44: STORE9 | F44: 2 | G44: 915.15 | H44: 0.16 | I44: PayPal | J44: 1537.452
A45: SALE43 | B45: 45677 | C45: CUST1084 | D45: PROD33 | E45: STORE17 | G45: 863.11 | H45: 0.28 | I45: PayPal | J45: 1864.3176
A46: SALE44 | B46: 45538 | C46: CUST1203 | D46: PROD43 | E46: STORE12 | F46: 2 | G46: 209.32 | H46: 0.23 | I46: COD | J46: 322.3528
A47: SALE45 | B47: 45606 | C47: CUST1470 | D47: PROD59 | E47: STORE8 | F47: 4 | G47: 288.6 | H47: 0.09 | I47: PayPal | J47: 1050.504
A48: SALE46 | B48: 45570 | C48: CUST1070 | D48: PROD78 | E48: STORE16 | F48: 1 | G48: 418.69 | H48: 0.06 | I48: PayPal | J48: 393.5686
A49: SALE47 | B49: 45466 | C49: CUST1008 | D49: PROD30 | E49: STORE11 | F49: 1 | G49: 135.78 | H49: 0.14 | I49: PayPal | J49: 116.7708
A50: SALE48 | B50: 45218 | C50: CUST1203 | D50: PROD44 | E50: STORE17 | F50: 1 | G50: 517.13 | H50: 0.28 | I50: Credit Card | J50: 372.3336
A51: SALE49 | B51: 45607 | C51: CUST1420 | D51: PROD21 | E51: STORE16 | F51: 2 | G51: 384.66 | H51: 0.08 | I51: COD | J51: 707.7744
A52: SALE50 | B52: 45291 | C52: CUST1070 | D52: PROD52 | E52: STORE9 | F52: 3 | G52: 83.7 | H52: 0.24 | I52: PayPal | J52: 190.836
A53: SALE51 | B53: 45689 | C53: CUST1142 | D53: PROD69 | E53: STORE7 | F53: 3 | G53: 76.57 | H53: 0.26 | I53: Credit Card | J53: 169.9854
A54: SALE52 | B54: 45894 | C54: CUST1148 | D54: PROD89 | E54: STORE6 | F54: 3 | I54: Credit Card | J54: 486.0633
A55: SALE53 | B55: 45677 | C55: CUST1324 | D55: PROD20 | E55: STORE8 | F55: 1 | G55: 900.35 | H55: 0.13 | I55: COD | J55: 783.3045
A56: SALE54 | B56: 45706 | C56: CUST1095 | D56: PROD40 | E56: STORE10 | F56: 4 | G56: 428.09 | H56: 0.07 | I56: Credit Card | J56: 1592.4948
A57: SALE55 | B57: 45589 | C57: CUST1416 | D57: PROD49 | E57: STORE11 | F57: 2 | G57: 559.71 | H57: 0.3 | I57: COD | J57: 783.594
A58: SALE56 | B58: 45282 | C58: CUST1080 | D58: PROD34 | E58: STORE6 | F58: 2 | G58: 833.7 | H58: 0.06 | I58: PayPal | J58: 1567.356
A59: SALE57 | B59: 45462 | C59: CUST1467 | D59: PROD47 | E59: STORE14 | F59: 2 | G59: 680.16 | H59: 0.28 | I59: Credit Card | J59: 979.4304
A60: SALE58 | B60: 45633 | C60: CUST1404 | D60: PROD15 | E60: STORE7 | F60: 4 | G60: 733.42 | I60: PayPal | J60: 2552.3016
A61: SALE59 | B61: 45257 | C61: CUST1367 | D61: PROD89 | E61: STORE11 | F61: 1 | G61: 996.33 | H61: 0.23 | I61: PayPal | J61: 767.1741
A62: SALE60 | B62: 45854 | C62: CUST1408 | D62: PROD31 | E62: STORE10 | F62: 1 | G62: 198.83 | H62: 0.09 | I62: COD | J62: 180.9353
A63: SALE61 | B63: 45716 | C63: CUST1239 | D63: PROD19 | E63: STORE7 | F63: 1 | G63: 374.92 | H63: 0.18 | I63: PayPal | J63: 307.4344
A64: SALE62 | B64: 45515 | C64: CUST1464 | D64: PROD93 | E64: STORE16 | F64: 1 | G64: 468.94 | H64: 0.12 | I64: Credit Card | J64: 412.6672
A65: SALE63 | B65: 45927 | C65: CUST1126 | D65: PROD89 | E65: STORE12 | F65: 2 | G65: 121.37 | H65: 0.05 | I65: Credit Card | J65: 230.603
A66: SALE64 | B66: 45914 | C66: CUST1255 | D66: PROD53 | E66: STORE10 | F66: 3 | G66: 480.06 | H66: 0.01 | I66: Credit Card
A67: SALE65 | B67: 45290 | C67: CUST1162 | D67: PROD99 | E67: STORE17 | F67: 2 | G67: 856.57 | H67: 0.24 | I67: Credit Card | J67: 1301.9864
A68: SALE66 | B68: 45213 | C68: CUST1269 | D68: PROD77 | E68: STORE2 | F68: 4 | G68: 814.25 | H68: 0.18 | I68: Credit Card | J68: 2670.74
A69: SALE67 | B69: 45255 | C69: CUST1483 | D69: PROD12 | E69: STORE2 | F69: 1 | G69: 989.17 | H69: 0.2 | I69: PayPal | J69: 791.336
A70: SALE68 | B70: 45270 | C70: CUST1372 | D70: PROD72 | E70: STORE10 | F70: 4 | G70: 62.48 | H70: 0.18 | I70: Credit Card | J70: 204.9344
A71: SALE69 | B71: 45897 | C71: CUST1423 | D71: PROD13 | E71: STORE16 | F71: 4 | G71: 561.24 | H71: 0.24 | I71: Credit Card | J71: 1706.1696
A72: SALE70 | B72: 45849 | C72: CUST1058 | D72: PROD60 | E72: STORE5 | F72: 3 | G72: 92.24 | H72: 0.28 | I72: COD
A73: SALE71 | B73: 45889 | C73: CUST1168 | D73: PROD72 | E73: STORE1 | F73: 2 | G73: 668.3 | H73: 0.07 | I73: Credit Card | J73: 1243.038
A74: SALE72 | B74: 45533 | C74: CUST1409 | D74: PROD38 | E74: STORE5 | F74: 1 | G74: 553.82 | H74: 0.09 | I74: Credit Card | J74: 503.9762
A75: SALE73 | B75: 45626 | C75: CUST1037 | D75: PROD45 | E75: STORE11 | F75: 2 | G75: 556.43 | H75: 0.13 | I75: Credit Card | J75: 968.1882
A76: SALE74 | B76: 45942 | C76: CUST1273 | D76: PROD20 | E76: STORE8 | F76: 1 | G76: 184.98 | H76: 0.1 | I76: COD | J76: 166.482
A77: SALE75 | B77: 45500 | C77: CUST1035 | D77: PROD97 | E77: STORE12 | F77: 4 | G77: 700.18 | H77: 0.23 | I77: Credit Card | J77: 2156.5544
A78: SALE76 | B78: 45285 | C78: CUST1019 | D78: PROD76 | E78: STORE10 | F78: 2 | G78: 686.31 | H78: 0.25 | I78: Credit Card | J78: 1029.465
A79: SALE77 | B79: 45800 | C79: CUST1007 | D79: PROD67 | E79: STORE15 | F79: 1 | G79: 687.82 | H79: 0.27 | I79: COD | J79: 502.1086
A80: SALE78 | B80: 45609 | C80: CUST1221 | D80: PROD83 | E80: STORE8 | F80: 2 | G80: 900.55 | H80: 0.16 | I80: Credit Card | J80: 1512.924
A81: SALE79 | B81: 45268 | C81: CUST1115 | D81: PROD21 | E81: STORE2 | F81: 1 | G81: 341.17 | H81: 0.15 | I81: Credit Card | J81: 289.9945
A82: SALE80 | B82: 45885 | C82: CUST1176 | D82: PROD52 | E82: STORE8 | F82: 1 | G82: 442.27 | H82: 0.06 | I82: COD | J82: 415.7338
A83: SALE81 | B83: 45616 | C83: CUST1253 | D83: PROD71 | E83: STORE9 | F83: 1 | G83: 363.73 | H83: 0.25 | I83: PayPal | J83: 272.7975
A84: SALE82 | B84: 45518 | C84: CUST1378 | D84: PROD91 | E84: STORE17 | F84: 2 | G84: 601.33 | H84: 0.16 | I84: PayPal | J84: 1010.2344
A85: SALE83 | B85: 45427 | C85: CUST1403 | D85: PROD17 | E85: STORE18 | F85: 4 | G85: 34.39 | H85: 0.03 | I85: PayPal | J85: 133.4332
A86: SALE84 | B86: 45268 | C86: CUST1423 | D86: PROD46 | E86: STORE17 | F86: 1 | G86: 773.57 | H86: 0.05 | I86: COD
A87: SALE85 | B87: 45282 | C87: CUST1054 | D87: PROD88 | E87: STORE7 | F87: 4 | G87: 127.1 | H87: 0.24 | I87: COD | J87: 386.384
A88: SALE86 | B88: 45545 | C88: CUST1303 | D88: PROD20 | E88: STORE3 | F88: 3 | G88: 899.58 | H88: 0.28 | I88: PayPal | J88: 1943.0928
A89: SALE87 | B89: 45755 | C89: CUST1327 | D89: PROD1 | E89: STORE10 | F89: 3 | G89: 964.39 | H89: 0.04 | I89: Credit Card | J89: 2777.4432
A90: SALE88 | B90: 45588 | C90: CUST1183 | D90: PROD38 | E90: STORE0 | F90: 2 | G90: 217.83 | H90: 0.14 | I90: PayPal | J90: 374.6676
A91: SALE89 | B91: 45848 | C91: CUST1143 | D91: PROD17 | E91: STORE1 | F91: 4 | G91: 187.71 | H91: 0.06 | I91: COD | J91: 705.7896
A92: SALE90 | B92: 45577 | C92: CUST1010 | D92: PROD33 | E92: STORE18 | F92: 2 | G92: 350.12 | H92: 0.12 | I92: COD | J92: 616.2112
A93: SALE91 | B93: 45312 | C93: CUST1406 | D93: PROD16 | E93: STORE1 | F93: 4 | G93: 102.19 | H93: 0.17 | I93: PayPal | J93: 339.2708
A94: SALE92 | B94: 45350 | C94: CUST1007 | D94: PROD86 | E94: STORE4 | F94: 1 | G94: 696.53 | H94: 0.17 | I94: Credit Card | J94: 578.1199
A95: SALE93 | B95: 45657 | C95: CUST1065 | D95: PROD19 | E95: STORE4 | F95: 2 | G95: 327.52 | H95: 0.15 | I95: PayPal | J95: 556.784
A96: SALE94 | B96: 45530 | C96: CUST1298 | D96: PROD97 | E96: STORE19 | F96: 2 | G96: 569.36 | H96: 0.01 | I96: PayPal
A97: SALE95 | B97: 45556 | C97: CUST1321 | D97: PROD99 | E97: STORE6 | F97: 2 | G97: 68.29 | H97: 0.14 | I97: COD | J97: 117.4588
A98: SALE96 | B98: 45523 | C98: CUST1244 | D98: PROD50 | E98: STORE10 | F98: 1 | G98: 842.9 | H98: 0.06 | I98: COD | J98: 792.326
A99: SALE97 | B99: 45587 | C99: CUST1287 | D99: PROD3 | E99: STORE3 | F99: 3 | G99: 751.94 | H99: 0.26 | I99: PayPal | J99: 1669.3068
A100: SALE98 | B100: 45580 | C100: CUST1131 | D100: PROD56 | E100: STORE7 | F100: 4 | G100: 476.28 | H100: 0.17 | I100: Credit Card | J100: 1581.2496
...

Sheet Customer_Dim_Clean
A1: Customer_ID | B1: Name | C1: Age | D1: Gender | E1: City | F1: State | G1: Country | H1: Loyalty_Level
A2: CUST1000 | B2: =TRIM(Customer_Dim!B2) -> sheena bonilla | C2: 55 | D2: Male | E2: Donaldton | F2: North Carolina | G2: USA | H2: Unknown
A3: CUST1001 | B3: =TRIM(Customer_Dim!B3) -> Eugene Nelson | C3: 26 | D3: Female | E3: Phillipsmouth | F3: North Dakota | G3: USA | H3: Platinum
A4: CUST1002 | B4: =TRIM(Customer_Dim!B4) -> dr. Benjamin Price | C4: 29 | D4: Female | E4: Kylebury | F4: Alabama | G4: USA | H4: Platinum
A5: CUST1003 | B5: =TRIM(Customer_Dim!B5) -> jeremy harris | C5: 59 | D5: Female | E5: Thomastown | F5: Ohio | G5: USA | H5: Bronze
A6: CUST1004 | B6: =TRIM(Customer_Dim!B6) -> Caroline Collins | C6: 64 | D6: Female | E6: Nicholasshire | F6: California | G6: USA | H6: Silver
A7: CUST1005 | B7: =TRIM(Customer_Dim!B7) -> Christine Vaughn | C7: 24 | D7: Male | E7: East Amandamouth | F7: Oregon | G7: USA | H7: Bronze
A8: CUST1006 | B8: =TRIM(Customer_Dim!B8) -> Amber Jackson | C8: 29 | D8: Female | E8: Deborahborough | F8: South Dakota | G8: USA | H8: Platinum
A9: CUST1007 | B9: =TRIM(Customer_Dim!B9) -> Daniel Boyd | C9: 29 | D9: Female | E9: West Pamelafurt | F9: West Virginia | G9: USA | H9: Bronze
A10: CUST1008 | B10: =TRIM(Customer_Dim!B10) -> Melissa Howard | C10: 53 | D10: Female | E10: Maynardton | F10: New Hampshire | G10: USA | H10: Gold
A11: CUST1009 | B11: =TRIM(Customer_Dim!B11) -> Ms. Maria Leach | C11: 64 | D11: Male | E11: Melissashire | F11: Pennsylvania | G11: USA | H11: Platinum
A12: CUST1010 | B12: =TRIM(Customer_Dim!B12) -> Dominic Page | C12: 53 | D12: Male | E12: Port Michaelburgh | F12: Pennsylvania | G12: USA | H12: Bronze
A13: CUST1011 | B13: =TRIM(Customer_Dim!B13) -> Brian Lopez | C13: 28 | D13: Female | E13: East Krista | F13: New York | G13: USA | H13: Gold
... A501: CUST 1499 | B501: =TRIM(Customer_Dim!B501) -> Philip Pennington | C501: 27 | D501: Female | E501: East Valerieview | F501: Oregon | G501: USA | H501: Platinum

Sheet Product_Dim _Clean
A1: Product_ID | B1: Product_Name | C1: Category | D1: Sub_Category | E1: Brand | F1: Cost | G1: Stock | H1: crt_Stock
A2: PROD0 | B2: Brother Laser Printer | C2: Electronics | D2: Computer | E2: Hunt Inc | F2: =IF(Product_Dim!D2="",MEDIAN(Product_Dim!D1:D101),ProductTbl[[#This Row],[Cost]]) -> 112.42 | G2: 416 | H2: =IF(G2="",MEDIAN(ProductTbl[Stock]),ProductTbl[[#This Row],[Stock]]) -> 416
A3: PROD1 | B3: Men's Graphic T-Shirt | C3: Clothing | D3: Tops | E3: Terry-Moore | F3: =IF(Product_Dim!D3="",MEDIAN(Product_Dim!D2:D102),ProductTbl[[#This Row],[Cost]]) -> 342.56 | G3: 181 | H3: =IF(G3="",MEDIAN(ProductTbl[Stock]),ProductTbl[[#This Row],[Stock]]) -> 181
A4: PROD2 | B4: Women's Casual Hoodie | C4: Clothing | D4: Outerwear | E4: Sims Inc | F4: =IF(Product_Dim!D4="",MEDIAN(Product_Dim!D3:D103),ProductTbl[[#This Row],[Cost]]) -> 243.7 | G4: 352 | H4: =IF(G4="",MEDIAN(ProductTbl[Stock]),ProductTbl[[#This Row],[Stock]]) -> 352
A5: PROD3 | B5: Men's Running Jacket | C5: Clothing | D5: Outerwear | E5: Pineda Ltd | F5: =IF(Product_Dim!D5="",MEDIAN(Product_Dim!D4:D104),ProductTbl[[#This Row],[Cost]]) -> 364.67 | G5: 452 | H5: =IF(G5="",MEDIAN(ProductTbl[Stock]),ProductTbl[[#This Row],[Stock]]) -> 452
A6: PROD4 | B6: Women's Yoga Pants | C6: Clothing | D6: Bottoms | E6: Gonzales-Davis | F6: =IF(Product_Dim!D6="",MEDIAN(Product_Dim!D5:D105),ProductTbl[[#This Row],[Cost]]) -> 306.46 | G6: 487 | H6: =IF(G6="",MEDIAN(ProductTbl[Stock]),ProductTbl[[#This Row],[Stock]]) -> 487
A7: PROD5 | B7: Men's Leather Belt | C7: Clothing | D7: Accessories | E7: Baldwin, Garza and Gonzalez | F7: =IF(Product_Dim!D7="",MEDIAN(Product_Dim!D6:D106),ProductTbl[[#This Row],[Cost]]) -> 261 | G7: 59 | H7: =IF(G7="",MEDIAN(ProductTbl[Stock]),ProductTbl[[#This Row],[Stock]]) -> 59
A8: PROD6 | B8: Herbal Face Moisturizer | C8: Beauty | D8: Skincare | E8: Davidson PLC | F8: =IF(Product_Dim!D8="",MEDIAN(Product_Dim!D7:D107),ProductTbl[[#This Row],[Cost]]) -> 312.8 | G8: 350 | H8: =IF(G8="",MEDIAN(ProductTbl[Stock]),ProductTbl[[#This Row],[Stock]]) -> 350
A9: PROD7 | B9: LED Table Lamp | C9: Home | D9: Lighting | E9: Harrell LLC | F9: =IF(Product_Dim!D9="",MEDIAN(Product_Dim!D8:D108),ProductTbl[[#This Row],[Cost]]) -> 218.86 | G9: 170 | H9: =IF(G9="",MEDIAN(ProductTbl[Stock]),ProductTbl[[#This Row],[Stock]]) -> 170
A10: PROD8 | B10: Wireless Bluetooth Earbuds | C10: Electronics | D10: Audio | E10: Perez-Johnston | F10: =IF(Product_Dim!D10="",MEDIAN(Product_Dim!D9:D109),ProductTbl[[#This Row],[Cost]]) -> 439.07 | G10: 142 | H10: =IF(G10="",MEDIAN(ProductTbl[Stock]),ProductTbl[[#This Row],[Stock]]) -> 142
A11: PROD9 | B11: Adjustable Dumbbell Set | C11: Sports | D11: Fitness | E11: Hill PLC | F11: =IF(Product_Dim!D11="",MEDIAN(Product_Dim!D10:D110),ProductTbl[[#This Row],[Cost]]) -> 495.72 | G11: 323 | H11: =IF(G11="",MEDIAN(ProductTbl[Stock]),ProductTbl[[#This Row],[Stock]]) -> 323
A12: PROD10 | B12: Ceramic Kitchen Bowl Set | C12: Home | D12: Kitchen | E12: Hamilton Group | F12: =IF(Product_Dim!D12="",MEDIAN(Product_Dim!D11:D111),ProductTbl[[#This Row],[Cost]]) -> 298.86 | G12: 308 | H12: =IF(G12="",MEDIAN(ProductTbl[Stock]),ProductTbl[[#This Row],[Stock]]) -> 308
A13: PROD11 | B13: HD Smart TV Stick | C13: Electronics | D13: Accessories | E13: Gibson, Hobbs and Weaver | F13: =IF(Product_Dim!D13="",MEDIAN(Product_Dim!D12:D112),ProductTbl[[#This Row],[Cost]]) -> 449.4 | H13: =IF(G13="",MEDIAN(ProductTbl[Stock]),ProductTbl[[#This Row],[Stock]]) -> 276
A14: PROD12 | B14: Hair Strengthening Shampoo | C14: Beauty | D14: Haircare | E14: Rice LLC | F14: =IF(Product_Dim!D14="",MEDIAN(Product_Dim!D13:D113),ProductTbl[[#This Row],[Cost]]) -> 115.82 | G14: 460 | H14: =IF(G14="",MEDIAN(ProductTbl[Stock]),ProductTbl[[#This Row],[Stock]]) -> 460
A15: PROD13 | B15: USB-C Fast Charger | C15: Electronics | D15: Accessories | E15: Dawson-Perkins | F15: =IF(Product_Dim!D15="",MEDIAN(Product_Dim!D14:D114),ProductTbl[[#This Row],[Cost]]) -> 242.23 | G15: 453 | H15: =IF(G15="",MEDIAN(ProductTbl[Stock]),ProductTbl[[#This Row],[Stock]]) -> 453
A16: PROD14 | B16: Decorative Wall Mirror | C16: Home | D16: Decor | E16: Luna, Anderson and Bowman | F16: =IF(Product_Dim!D16="",MEDIAN(Product_Dim!D15:D115),ProductTbl[[#This Row],[Cost]]) -> 48.01 | G16: 439 | H16: =IF(G16="",MEDIAN(ProductTbl[Stock]),ProductTbl[[#This Row],[Stock]]) -> 439
A17: PROD15 | B17: 4K Home Projector | C17: Electronics | D17: Appliances | E17: Thomas LLC | F17: =IF(Product_Dim!D17="",MEDIAN(Product_Dim!D16:D116),ProductTbl[[#This Row],[Cost]]) -> 465.34 | G17: 301 | H17: =IF(G17="",MEDIAN(ProductTbl[Stock]),ProductTbl[[#This Row],[Stock]]) -> 301
A18: PROD16 | B18: Beard Grooming Kit | C18: Beauty | D18: Grooming | E18: Erickson-Green | F18: =IF(Product_Dim!D18="",MEDIAN(Product_Dim!D17:D117),ProductTbl[[#This Row],[Cost]]) -> 337.42 | G18: 256 | H18: =IF(G18="",MEDIAN(ProductTbl[Stock]),ProductTbl[[#This Row],[Stock]]) -> 256
A19: PROD17 | B19: Soccer Training Cone Set | C19: Sports | D19: Accessories | E19: Ford, Murphy and Wilson | F19: =IF(Product_Dim!D19="",MEDIAN(Product_Dim!D18:D118),ProductTbl[[#This Row],[Cost]]) -> 144.53 | G19: 367 | H19: =IF(G19="",MEDIAN(ProductTbl[Stock]),ProductTbl[[#This Row],[Stock]]) -> 367
A20: PROD18 | B20: Women's Denim Jeans | C20: Clothing | D20: Bottoms | E20: Guerra-Hendrix | F20: =IF(Product_Dim!D20="",MEDIAN(Product_Dim!D19:D119),ProductTbl[[#This Row],[Cost]]) -> 220.955 | G20: 343 | H20: =IF(G20="",MEDIAN(ProductTbl[Stock]),ProductTbl[[#This Row],[Stock]]) -> 343
A21: PROD19 | B21: Knee Support Brace | C21: Sports | D21: Equipment | E21: May-Reese | F21: =IF(Product_Dim!D21="",MEDIAN(Product_Dim!D20:D120),ProductTbl[[#This Row],[Cost]]) -> 21.34 | G21: 65 | H21: =IF(G21="",MEDIAN(ProductTbl[Stock]),ProductTbl[[#This Row],[Stock]]) -> 65
A22: PROD20 | B22: Outdoor Sports Water Bottle | C22: Sports | D22: Accessories | E22: Soto-Ellis | F22: =IF(Product_Dim!D22="",MEDIAN(Product_Dim!D21:D121),ProductTbl[[#This Row],[Cost]]) -> 131.51 | H22: =IF(G22="",MEDIAN(ProductTbl[Stock]),ProductTbl[[#This Row],[Stock]]) -> 276
A23: PROD21 | B23: Multi-Purpose Storage Box | C23: Home | D23: Storage | E23: Gardner-Montes | F23: =IF(Product_Dim!D23="",MEDIAN(Product_Dim!D22:D122),ProductTbl[[#This Row],[Cost]]) -> 123.46 | G23: 76 | H23: =IF(G23="",MEDIAN(ProductTbl[Stock]),ProductTbl[[#This Row],[Stock]]) -> 76
A24: PROD22 | B24: Carbon Fiber Tennis Racket | C24: Sports | D24: Equipment | E24: Flores, Pineda and Rodriguez | F24: =IF(Product_Dim!D24="",MEDIAN(Product_Dim!D23:D123),ProductTbl[[#This Row],[Cost]]) -> 484.62 | G24: 432 | H24: =IF(G24="",MEDIAN(ProductTbl[Stock]),ProductTbl[[#This Row],[Stock]]) -> 432
A25: PROD23 | B25: Men's Formal Shirt | C25: Clothing | D25: Tops | E25: Moon, Mora and Santos | F25: =IF(Product_Dim!D25="",MEDIAN(Product_Dim!D24:D124),ProductTbl[[#This Row],[Cost]]) -> 234.58 | G25: 360 | H25: =IF(G25="",MEDIAN(ProductTbl[Stock]),ProductTbl[[#This Row],[Stock]]) -> 360
A26: PROD24 | B26: Foldable Camping Chair | C26: Sports | D26: Outdoor | E26: Cook Ltd | F26: =IF(Product_Dim!D26="",MEDIAN(Product_Dim!D25:D125),ProductTbl[[#This Row],[Cost]]) -> 166.06 | G26: 340 | H26: =IF(G26="",MEDIAN(ProductTbl[Stock]),ProductTbl[[#This Row],[Stock]]) -> 340
A27: PROD25 | B27: Women's Scarf Set | C27: Clothing | D27: Accessories | E27: Brown and Sons | F27: =IF(Product_Dim!D27="",MEDIAN(Product_Dim!D26:D126),ProductTbl[[#This Row],[Cost]]) -> 174.02 | G27: 268 | H27: =IF(G27="",MEDIAN(ProductTbl[Stock]),ProductTbl[[#This Row],[Stock]]) -> 268
A28: PROD26 | B28: Wireless Bluetooth Speaker | C28: Electronics | D28: Audio | E28: Reed-Schmidt | F28: =IF(Product_Dim!D28="",MEDIAN(Product_Dim!D27:D127),ProductTbl[[#This Row],[Cost]]) -> 322.41 | G28: 213 | H28: =IF(G28="",MEDIAN(ProductTbl[Stock]),ProductTbl[[#This Row],[Stock]]) -> 213
A29: PROD27 | B29: Decorative Floor Vase | C29: Home | D29: Decor | E29: Khan, Jones and Paul | F29: =IF(Product_Dim!D29="",MEDIAN(Product_Dim!D28:D128),ProductTbl[[#This Row],[Cost]]) -> 240.63 | G29: 378 | H29: =IF(G29="",MEDIAN(ProductTbl[Stock]),ProductTbl[[#This Row],[Stock]]) -> 378
A30: PROD28 | B30: Sports Stopwatch Timer | C30: Sports | D30: Accessories | E30: Burns-Hansen | F30: =IF(Product_Dim!D30="",MEDIAN(Product_Dim!D29:D129),ProductTbl[[#This Row],[Cost]]) -> 38.76 | G30: 137 | H30: =IF(G30="",MEDIAN(ProductTbl[Stock]),ProductTbl[[#This Row],[Stock]]) -> 137
A31: PROD29 | B31: Fabric Sofa Throw Blanket | C31: Home | D31: Decor | E31: Hoffman Group | F31: =IF(Product_Dim!D31="",MEDIAN(Product_Dim!D30:D130),ProductTbl[[#This Row],[Cost]]) -> 218.48 | G31: 276 | H31: =IF(G31="",MEDIAN(ProductTbl[Stock]),ProductTbl[[#This Row],[Stock]]) -> 276
A32: PROD30 | B32: Stainless Steel Cutlery Set | C32: Home | D32: Kitchen | E32: Stevens, Fernandez and Martin | F32: =IF(Product_Dim!D32="",MEDIAN(Product_Dim!D31:D131),ProductTbl[[#This Row],[Cost]]) -> 19.52 | G32: 57 | H32: =IF(G32="",MEDIAN(ProductTbl[Stock]),ProductTbl[[#This Row],[Stock]]) -> 57
A33: PROD31 | B33: Basketball | C33: Sports | D33: Team Sports | E33: Nolan-Snow | F33: =IF(Product_Dim!D33="",MEDIAN(Product_Dim!D32:D132),ProductTbl[[#This Row],[Cost]]) -> 204.39 | G33: 281 | H33: =IF(G33="",MEDIAN(ProductTbl[Stock]),ProductTbl[[#This Row],[Stock]]) -> 281
A34: PROD32 | B34: Vitamin C Face Serum | C34: Beauty | D34: Skincare | E34: Griffin Ltd | F34: =IF(Product_Dim!D34="",MEDIAN(Product_Dim!D33:D133),ProductTbl[[#This Row],[Cost]]) -> 283.83 | G34: 244 | H34: =IF(G34="",MEDIAN(ProductTbl[Stock]),ProductTbl[[#This Row],[Stock]]) -> 244
... A56: PROD54 | B56: Sports Stopwatch Pro | C56: Sports | D56: Accessories | E56: Thompson-French | F56: =IF(Product_Dim!D56="",MEDIAN(Product_Dim!D55:D155),ProductTbl[[#This Row],[Cost]]) -> 434.84 | G56: 185 | H56: =IF(G56="",MEDIAN(ProductTbl[Stock]),ProductTbl[[#This Row],[Stock]]) -> 185
A57: PROD55 | B57: Ceramic Plant Pot | C57: Home | D57: Decor | E57: Hatfield, Baird and Torres | F57: =IF(Product_Dim!D57="",MEDIAN(Product_Dim!D56:D156),ProductTbl[[#This Row],[Cost]]) -> 81.75 | H57: =IF(G57="",MEDIAN(ProductTbl[Stock]),ProductTbl[[#This Row],[Stock]]) -> 276
A58: PROD56 | B58: Premium Blanket Throw | C58: Home | D58: Decor | E58: Hernandez, Kennedy and Porter | F58: =IF(Product_Dim!D58="",MEDIAN(Product_Dim!D57:D157),ProductTbl[[#This Row],[Cost]]) -> 461.47 | G58: 190 | H58: =IF(G58="",MEDIAN(ProductTbl[Stock]),ProductTbl[[#This Row],[Stock]]) -> 190
A59: PROD57 | B59: Foam Roller | C59: Sports | D59: Fitness | E59: Atkinson, Camacho and Oliver | F59: =IF(Product_Dim!D59="",MEDIAN(Product_Dim!D58:D158),ProductTbl[[#This Row],[Cost]]) -> 30.62 | G59: 138 | H59: =IF(G59="",MEDIAN(ProductTbl[Stock]),ProductTbl[[#This Row],[Stock]]) -> 138
A60: PROD58 | B60: Womens Cotton Scarf | C60: Clothing | D60: Accessories | E60: Shepherd-Gould | F60: =IF(Product_Dim!D60="",MEDIAN(Product_Dim!D59:D159),ProductTbl[[#This Row],[Cost]]) -> 113.83 | G60: 485 | H60: =IF(G60="",MEDIAN(ProductTbl[Stock]),ProductTbl[[#This Row],[Stock]]) -> 485
A61: PROD59 | B61: Men's Hair Styling Gel | C61: Beauty | D61: Haircare | E61: Cline-Mccarthy | F61: =IF(Product_Dim!D61="",MEDIAN(Product_Dim!D60:D160),ProductTbl[[#This Row],[Cost]]) -> 17.31 | G61: 399 | H61: =IF(G61="",MEDIAN(ProductTbl[Stock]),ProductTbl[[#This Row],[Stock]]) -> 399
A62: PROD60 | B62: Luxury Perfume Spray | C62: Beauty | D62: Fragrance | E62: Gibson, Green and Lopez | F62: =IF(Product_Dim!D62="",MEDIAN(Product_Dim!D61:D161),ProductTbl[[#This Row],[Cost]]) -> 482.75 | G62: 444 | H62: =IF(G62="",MEDIAN(ProductTbl[Stock]),ProductTbl[[#This Row],[Stock]]) -> 444
A63: PROD61 | B63: Tennis Ball 3-Pack | C63: Sports | D63: Equipment | E63: Lopez LLC | F63: =IF(Product_Dim!D63="",MEDIAN(Product_Dim!D62:D162),ProductTbl[[#This Row],[Cost]]) -> 103.45 | G63: 465 | H63: =IF(G63="",MEDIAN(ProductTbl[Stock]),ProductTbl[[#This Row],[Stock]]) -> 465
A64: PROD62 | B64: Laptop Cooling Pad | C64: Electronics | D64: Computer | E64: Murray, Gould and Ware | F64: =IF(Product_Dim!D64="",MEDIAN(Product_Dim!D63:D163),ProductTbl[[#This Row],[Cost]]) -> 86.42 | G64: 222 | H64: =IF(G64="",MEDIAN(ProductTbl[Stock]),ProductTbl[[#This Row],[Stock]]) -> 222
A65: PROD63 | B65: Organic Sunscreen Lotion | C65: Beauty | D65: Skincare | E65: Anderson-Riley | F65: =IF(Product_Dim!D65="",MEDIAN(Product_Dim!D64:D164),ProductTbl[[#This Row],[Cost]]) -> 266.86 | G65: 458 | H65: =IF(G65="",MEDIAN(ProductTbl[Stock]),ProductTbl[[#This Row],[Stock]]) -> 458
A66: PROD64 | B66: Matte Lipstick Set | C66: Beauty | D66: Makeup | E66: Zhang Inc | F66: =IF(Product_Dim!D66="",MEDIAN(Product_Dim!D65:D165),ProductTbl[[#This Row],[Cost]]) -> 299.11 | G66: 118 | H66: =IF(G66="",MEDIAN(ProductTbl[Stock]),ProductTbl[[#This Row],[Stock]]) -> 118
A67: PROD65 | B67: Adjustable Dumbbells 20kg | C67: Sports | D67: Fitness | E67: Montgomery, Benton and Miller | F67: =IF(Product_Dim!D67="",MEDIAN(Product_Dim!D66:D166),ProductTbl[[#This Row],[Cost]]) -> 240.63 | G67: 423 | H67: =IF(G67="",MEDIAN(ProductTbl[Stock]),ProductTbl[[#This Row],[Stock]]) -> 423
A68: PROD66 | B68: Women's Hair Dryer Brush | C68: Beauty | D68: Haircare | E68: Torres, Spencer and Potter | F68: =IF(Product_Dim!D68="",MEDIAN(Product_Dim!D67:D167),ProductTbl[[#This Row],[Cost]]) -> 340.39 | G68: 177 | H68: =IF(G68="",MEDIAN(ProductTbl[Stock]),ProductTbl[[#This Row],[Stock]]) -> 177
A69: PROD67 | B69: Smart LED Light Strip | C69: Electronics | D69: Accessories | E69: Flores-Davis | F69: =IF(Product_Dim!D69="",MEDIAN(Product_Dim!D68:D168),ProductTbl[[#This Row],[Cost]]) -> 349.17 | G69: 476 | H69: =IF(G69="",MEDIAN(ProductTbl[Stock]),ProductTbl[[#This Row],[Stock]]) -> 476
... A101: PROD99 | B101: Stainless Steel Cookware Set | C101: Home | D101: Kitchen | E101: Campbell Ltd | F101: =IF(Product_Dim!D101="",MEDIAN(Product_Dim!D100:D200),ProductTbl[[#This Row],[Cost]]) -> 201.41 | G101: 146 | H101: =IF(G101="",MEDIAN(ProductTbl[Stock]),ProductTbl[[#This Row],[Stock]]) -> 146

Sheet Store_Dim_Clean
A1: Store_ID | B1: Store_Name | C1: Region | D1: City | E1: Store_Type
A2: STORE0 | B2: Rivera-Warner | C2: East | D2: Washingtonfurt | E2: Flagship
A3: STORE1 | B3: Martinez, Adkins and Johnson | C3: North | D3: Danielmouth | E3: Flagship
A4: STORE2 | B4: Black-Horn | C4: South | D4: North Nancyview | E4: Outlet
A5: STORE3 | B5: Johnson-Wright | C5: North | D5: Hoodberg | E5: Outlet
A6: STORE4 | B6: Alexander Group | C6: South | D6: Port Sharon | E6: Online
A7: STORE5 | B7: Gray Ltd | C7: North | D7: New Michaelchester | E7: Outlet
A8: STORE6 | B8: Benson-Elliott | C8: East | D8: Port Josephberg | E8: Online
A9: STORE7 | B9: Martinez-Mullins | C9: South | D9: Williamsfurt | E9: Online
A10: STORE8 | B10: Bean, Jones and Park | C10: West | D10: Thompsonborough | E10: Online
A11: STORE9 | B11: Moore, Padilla and Butler | C11: South | D11: East Johnstad | E11: Flagship
A12: STORE10 | B12: Hill, Wagner and Ballard | C12: East | D12: East Davidville | E12: Online
... A21: STORE19 | B21: Mann-Austin | C21: East | D21: Vasquezborough | E21: Online

Sheet Sales_Fact_Clean
A1: Sales_ID | B1: Order_Date | C1: Customer_ID | D1: Product_ID | E1: Store_ID | F1: Quantity | G1: Unit_Price | H1: Discount | I1: Payment_Type | J1: Total_Amount | K1: crt_Total_Amount | L1: crt_Discount | M1: crt_Unit_Price | N1: Crt_Quantity
A2: SALE0 | B2: 45480 | C2: CUST1409 | D2: PROD97 | E2: STORE3 | F2: 1 | G2: 218.04 | H2: 0.09 | I2: Credit Card | J2: 198.4164 | K2: =IF(J2="",MEDIAN(SalesTbl[Total_Amount]),J2) -> 198.4164 | L2: =IF(H2="",MEDIAN(SalesTbl[Discount]),H2) -> 0.09 | M2: =IF(G2="",MEDIAN(SalesTbl[Unit_Price]),G2) -> 218.04 | N2: =IF(F2="",MEDIAN(SalesTbl[Quantity]),F2) -> 1
A3: SALE1 | B3: 45285 | C3: CUST1467 | D3: PROD74 | E3: STORE17 | F3: 3 | G3: 104.47 | H3: 0.27 | I3: PayPal | J3: 228.7893 | K3: =IF(J3="",MEDIAN(SalesTbl[Total_Amount]),J3) -> 228.7893 | L3: =IF(H3="",MEDIAN(SalesTbl[Discount]),H3) -> 0.27 | M3: =IF(G3="",MEDIAN(SalesTbl[Unit_Price]),G3) -> 104.47 | N3: =IF(F3="",MEDIAN(SalesTbl[Quantity]),F3) -> 3
A4: SALE2 | B4: 45446 | C4: CUST1056 | D4: PROD49 | E4: STORE8 | F4: 4 | G4: 914.05 | H4: 0.25 | I4: Credit Card | J4: 2742.15 | K4: =IF(J4="",MEDIAN(SalesTbl[Total_Amount]),J4) -> 2742.15 | L4: =IF(H4="",MEDIAN(SalesTbl[Discount]),H4) -> 0.25 | M4: =IF(G4="",MEDIAN(SalesTbl[Unit_Price]),G4) -> 914.05 | N4: =IF(F4="",MEDIAN(SalesTbl[Quantity]),F4) -> 4
A5: SALE3 | B5: 45259 | C5: CUST1346 | D5: PROD76 | E5: STORE8 | F5: 1 | G5: 921.51 | H5: 0.16 | I5: COD | J5: 774.0684 | K5: =IF(J5="",MEDIAN(SalesTbl[Total_Amount]),J5) -> 774.0684 | L5: =IF(H5="",MEDIAN(SalesTbl[Discount]),H5) -> 0.16 | M5: =IF(G5="",MEDIAN(SalesTbl[Unit_Price]),G5) -> 921.51 | N5: =IF(F5="",MEDIAN(SalesTbl[Quantity]),F5) -> 1
A6: SALE4 | B6: 45297 | C6: CUST1493 | D6: PROD59 | E6: STORE5 | F6: 3 | G6: 745.3 | H6: 0.18 | I6: Credit Card | J6: 1833.438 | K6: =IF(J6="",MEDIAN(SalesTbl[Total_Amount]),J6) -> 1833.438 | L6: =IF(H6="",MEDIAN(SalesTbl[Discount]),H6) -> 0.18 | M6: =IF(G6="",MEDIAN(SalesTbl[Unit_Price]),G6) -> 745.3 | N6: =IF(F6="",MEDIAN(SalesTbl[Quantity]),F6) -> 3
A7: SALE5 | B7: 45499 | C7: CUST1116 | D7: PROD15 | E7: STORE7 | F7: 3 | G7: 147.01 | H7: 0.19 | I7: COD | J7: 357.2343 | K7: =IF(J7="",MEDIAN(SalesTbl[Total_Amount]),J7) -> 357.2343 | L7: =IF(H7="",MEDIAN(SalesTbl[Discount]),H7) -> 0.19 | M7: =IF(G7="",MEDIAN(SalesTbl[Unit_Price]),G7) -> 147.01 | N7: =IF(F7="",MEDIAN(SalesTbl[Quantity]),F7) -> 3
A8: SALE6 | B8: 45850 | C8: CUST1016 | D8: PROD56 | E8: STORE4 | F8: 2 | G8: 785.31 | H8: 0.15 | I8: PayPal | J8: 1335.027 | K8: =IF(J8="",MEDIAN(SalesTbl[Total_Amount]),J8) -> 1335.027 | L8: =IF(H8="",MEDIAN(SalesTbl[Discount]),H8) -> 0.15 | M8: =IF(G8="",MEDIAN(SalesTbl[Unit_Price]),G8) -> 785.31 | N8: =IF(F8="",MEDIAN(SalesTbl[Quantity]),F8) -> 2
A9: SALE7 | B9: 45248 | C9: CUST1152 | D9: PROD70 | E9: STORE8 | F9: 4 | G9: 342.39 | H9: 0.23 | I9: PayPal | J9: 1054.5612 | K9: =IF(J9="",MEDIAN(SalesTbl[Total_Amount]),J9) -> 1054.5612 | L9: =IF(H9="",MEDIAN(SalesTbl[Discount]),H9) -> 0.23 | M9: =IF(G9="",MEDIAN(SalesTbl[Unit_Price]),G9) -> 342.39 | N9: =IF(F9="",MEDIAN(SalesTbl[Quantity]),F9) -> 4
A10: SALE8 | B10: 45781 | C10: CUST1187 | D10: PROD99 | E10: STORE5 | G10: 448.25 | H10: 0.07 | I10: PayPal | J10: 1250.6175 | K10: =IF(J10="",MEDIAN(SalesTbl[Total_Amount]),J10) -> 1250.6175 | L10: =IF(H10="",MEDIAN(SalesTbl[Discount]),H10) -> 0.07 | M10: =IF(G10="",MEDIAN(SalesTbl[Unit_Price]),G10) -> 448.25 | N10: =IF(F10="",MEDIAN(SalesTbl[Quantity]),F10) -> 2
A11: SALE9 | B11: 45869 | C11: CUST1464 | D11: PROD33 | E11: STORE0 | F11: 2 | G11: 873.17 | H11: 0.23 | I11: PayPal | J11: 1344.6818 | K11: =IF(J11="",MEDIAN(SalesTbl[Total_Amount]),J11) -> 1344.6818 | L11: =IF(H11="",MEDIAN(SalesTbl[Discount]),H11) -> 0.23 | M11: =IF(G11="",MEDIAN(SalesTbl[Unit_Price]),G11) -> 873.17 | N11: =IF(F11="",MEDIAN(SalesTbl[Quantity]),F11) -> 2
A12: SALE10 | B12: 45335 | C12: CUST1065 | D12: PROD24 | E12: STORE14 | F12: 1 | G12: 278.63 | H12: 0.07 | I12: Credit Card | J12: 259.1259 | K12: =IF(J12="",MEDIAN(SalesTbl[Total_Amount]),J12) -> 259.1259 | L12: =IF(H12="",MEDIAN(SalesTbl[Discount]),H12) -> 0.07 | M12: =IF(G12="",MEDIAN(SalesTbl[Unit_Price]),G12) -> 278.63 | N12: =IF(F12="",MEDIAN(SalesTbl[Quantity]),F12) -> 1
A13: SALE11 | B13: 45801 | C13: CUST1320 | D13: PROD39 | E13: STORE1 | F13: 4 | G13: 286.92 | H13: 0.17 | I13: Credit Card | J13: 952.5744 | K13: =IF(J13="",MEDIAN(SalesTbl[Total_Amount]),J13) -> 952.5744 | L13: =IF(H13="",MEDIAN(SalesTbl[Discount]),H13) -> 0.17 | M13: =IF(G13="",MEDIAN(SalesTbl[Unit_Price]),G13) -> 286.92 | N13: =IF(F13="",MEDIAN(SalesTbl[Quantity]),F13) -> 4
A14: SALE12 | B14: 45528 | C14: CUST1237 | D14: PROD88 | E14: STORE4 | F14: 4 | G14: 644.58 | H14: 0.01 | I14: Credit Card | J14: 2552.5368 | K14: =IF(J14="",MEDIAN(SalesTbl[Total_Amount]),J14) -> 2552.5368 | L14: =IF(H14="",MEDIAN(SalesTbl[Discount]),H14) -> 0.01 | M14: =IF(G14="",MEDIAN(SalesTbl[Unit_Price]),G14) -> 644.58 | N14: =IF(F14="",MEDIAN(SalesTbl[Quantity]),F14) -> 4
A15: SALE13 | B15: 45875 | C15: CUST1443 | D15: PROD34 | E15: STORE16 | F15: 2 | G15: 316.9 | H15: 0.3 | I15: PayPal | J15: 443.66 | K15: =IF(J15="",MEDIAN(SalesTbl[Total_Amount]),J15) -> 443.66 | L15: =IF(H15="",MEDIAN(SalesTbl[Discount]),H15) -> 0.3 | M15: =IF(G15="",MEDIAN(SalesTbl[Unit_Price]),G15) -> 316.9 | N15: =IF(F15="",MEDIAN(SalesTbl[Quantity]),F15) -> 2
A16: SALE14 | B16: 45829 | C16: CUST1348 | D16: PROD24 | E16: STORE15 | F16: 4 | G16: 403.47 | H16: 0.29 | I16: PayPal | J16: 1145.8548 | K16: =IF(J16="",MEDIAN(SalesTbl[Total_Amount]),J16) -> 1145.8548 | L16: =IF(H16="",MEDIAN(SalesTbl[Discount]),H16) -> 0.29 | M16: =IF(G16="",MEDIAN(SalesTbl[Unit_Price]),G16) -> 403.47 | N16: =IF(F16="",MEDIAN(SalesTbl[Quantity]),F16) -> 4
A17: SALE15 | B17: 45636 | C17: CUST1435 | D17: PROD36 | E17: STORE9 | G17: 871.34 | H17: 0.04 | I17: COD | J17: 2509.4592 | K17: =IF(J17="",MEDIAN(SalesTbl[Total_Amount]),J17) -> 2509.4592 | L17: =IF(H17="",MEDIAN(SalesTbl[Discount]),H17) -> 0.04 | M17: =IF(G17="",MEDIAN(SalesTbl[Unit_Price]),G17) -> 871.34 | N17: =IF(F17="",MEDIAN(SalesTbl[Quantity]),F17) -> 2
A18: SALE16 | B18: 45913 | C18: CUST1276 | D18: PROD65 | E18: STORE19 | F18: 2 | G18: 451.98 | H18: 0.25 | I18: Credit Card | J18: 677.97 | K18: =IF(J18="",MEDIAN(SalesTbl[Total_Amount]),J18) -> 677.97 | L18: =IF(H18="",MEDIAN(SalesTbl[Discount]),H18) -> 0.25 | M18: =IF(G18="",MEDIAN(SalesTbl[Unit_Price]),G18) -> 451.98 | N18: =IF(F18="",MEDIAN(SalesTbl[Quantity]),F18) -> 2
A19: SALE17 | B19: 45637 | C19: CUST1079 | D19: PROD27 | E19: STORE4 | F19: 2 | G19: 502.69 | H19: 0.23 | I19: Credit Card | J19: 774.1426 | K19: =IF(J19="",MEDIAN(SalesTbl[Total_Amount]),J19) -> 774.1426 | L19: =IF(H19="",MEDIAN(SalesTbl[Discount]),H19) -> 0.23 | M19: =IF(G19="",MEDIAN(SalesTbl[Unit_Price]),G19) -> 502.69 | N19: =IF(F19="",MEDIAN(SalesTbl[Quantity]),F19) -> 2
A20: SALE18 | B20: 45517 | C20: CUST1094 | D20: PROD39 | E20: STORE4 | F20: 2 | G20: 559.23 | H20: 0.25 | I20: COD | J20: 838.845 | K20: =IF(J20="",MEDIAN(SalesTbl[Total_Amount]),J20) -> 838.845 | L20: =IF(H20="",MEDIAN(SalesTbl[Discount]),H20) -> 0.25 | M20: =IF(G20="",MEDIAN(SalesTbl[Unit_Price]),G20) -> 559.23 | N20: =IF(F20="",MEDIAN(SalesTbl[Quantity]),F20) -> 2
A21: SALE19 | B21: 45369 | C21: CUST1239 | D21: PROD60 | E21: STORE13 | F21: 4 | H21: 0.04 | I21: COD | J21: 1782.4512 | K21: =IF(J21="",MEDIAN(SalesTbl[Total_Amount]),J21) -> 1782.4512 | L21: =IF(H21="",MEDIAN(SalesTbl[Discount]),H21) -> 0.04 | M21: =IF(G21="",MEDIAN(SalesTbl[Unit_Price]),G21) -> 527.905 | N21: =IF(F21="",MEDIAN(SalesTbl[Quantity]),F21) -> 4
A22: SALE20 | B22: 45843 | C22: CUST1144 | D22: PROD72 | E22: STORE17 | F22: 3 | G22: 986.04 | H22: 0.27 | I22: COD | J22: 2159.4276 | K22: =IF(J22="",MEDIAN(SalesTbl[Total_Amount]),J22) -> 2159.4276 | L22: =IF(H22="",MEDIAN(SalesTbl[Discount]),H22) -> 0.27 | M22: =IF(G22="",MEDIAN(SalesTbl[Unit_Price]),G22) -> 986.04 | N22: =IF(F22="",MEDIAN(SalesTbl[Quantity]),F22) -> 3
A23: SALE21 | B23: 45447 | C23: CUST1396 | D23: PROD43 | E23: STORE18 | F23: 1 | G23: 589.56 | H23: 0.22 | I23: Credit Card | J23: 459.8568 | K23: =IF(J23="",MEDIAN(SalesTbl[Total_Amount]),J23) -> 459.8568 | L23: =IF(H23="",MEDIAN(SalesTbl[Discount]),H23) -> 0.22 | M23: =IF(G23="",MEDIAN(SalesTbl[Unit_Price]),G23) -> 589.56 | N23: =IF(F23="",MEDIAN(SalesTbl[Quantity]),F23) -> 1
A24: SALE22 | B24: 45394 | C24: CUST1476 | D24: PROD69 | E24: STORE10 | F24: 3 | G24: 979.42 | H24: 0.03 | I24: PayPal | J24: 2850.1122 | K24: =IF(J24="",MEDIAN(SalesTbl[Total_Amount]),J24) -> 2850.1122 | L24: =IF(H24="",MEDIAN(SalesTbl[Discount]),H24) -> 0.03 | M24: =IF(G24="",MEDIAN(SalesTbl[Unit_Price]),G24) -> 979.42 | N24: =IF(F24="",MEDIAN(SalesTbl[Quantity]),F24) -> 3
A25: SALE23 | B25: 45466 | C25: CUST1368 | D25: PROD12 | E25: STORE8 | F25: 1 | G25: 719.28 | H25: 0.08 | I25: Credit Card | J25: 661.7376 | K25: =IF(J25="",MEDIAN(SalesTbl[Total_Amount]),J25) -> 661.7376 | L25: =IF(H25="",MEDIAN(SalesTbl[Discount]),H25) -> 0.08 | M25: =IF(G25="",MEDIAN(SalesTbl[Unit_Price]),G25) -> 719.28 | N25: =IF(F25="",MEDIAN(SalesTbl[Quantity]),F25) -> 1
A26: SALE24 | B26: 45908 | C26: CUST1186 | D26: PROD67 | E26: STORE6 | F26: 3 | G26: 77.6 | H26: 0.07 | I26: Credit Card | J26: 216.504 | K26: =IF(J26="",MEDIAN(SalesTbl[Total_Amount]),J26) -> 216.504 | L26: =IF(H26="",MEDIAN(SalesTbl[Discount]),H26) -> 0.07 | M26: =IF(G26="",MEDIAN(SalesTbl[Unit_Price]),G26) -> 77.6 | N26: =IF(F26="",MEDIAN(SalesTbl[Quantity]),F26) -> 3
A27: SALE25 | B27: 45552 | C27: CUST1381 | D27: PROD5 | E27: STORE3 | F27: 4 | G27: 852.71 | H27: 0.14 | I27: PayPal | J27: 2933.3224 | K27: =IF(J27="",MEDIAN(SalesTbl[Total_Amount]),J27) -> 2933.3224 | L27: =IF(H27="",MEDIAN(SalesTbl[Discount]),H27) -> 0.14 | M27: =IF(G27="",MEDIAN(SalesTbl[Unit_Price]),G27) -> 852.71 | N27: =IF(F27="",MEDIAN(SalesTbl[Quantity]),F27) -> 4
A28: SALE26 | B28: 45294 | C28: CUST1213 | D28: PROD98 | E28: STORE8 | F28: 4 | G28: 156.16 | I28: Credit Card | J28: 599.6544 | K28: =IF(J28="",MEDIAN(SalesTbl[Total_Amount]),J28) -> 599.6544 | L28: =IF(H28="",MEDIAN(SalesTbl[Discount]),H28) -> 0.14 | M28: =IF(G28="",MEDIAN(SalesTbl[Unit_Price]),G28) -> 156.16 | N28: =IF(F28="",MEDIAN(SalesTbl[Quantity]),F28) -> 4
A29: SALE27 | B29: 45710 | C29: CUST1200 | D29: PROD77 | E29: STORE8 | F29: 3 | G29: 815.49 | H29: 0.17 | I29: Credit Card | J29: 2030.5701 | K29: =IF(J29="",MEDIAN(SalesTbl[Total_Amount]),J29) -> 2030.5701 | L29: =IF(H29="",MEDIAN(SalesTbl[Discount]),H29) -> 0.17 | M29: =IF(G29="",MEDIAN(SalesTbl[Unit_Price]),G29) -> 815.49 | N29: =IF(F29="",MEDIAN(SalesTbl[Quantity]),F29) -> 3
A30: SALE28 | B30: 45923 | C30: CUST1148 | D30: PROD13 | E30: STORE2 | F30: 2 | G30: 74.21 | H30: 0.11 | I30: PayPal | J30: 132.0938 | K30: =IF(J30="",MEDIAN(SalesTbl[Total_Amount]),J30) -> 132.0938 | L30: =IF(H30="",MEDIAN(SalesTbl[Discount]),H30) -> 0.11 | M30: =IF(G30="",MEDIAN(SalesTbl[Unit_Price]),G30) -> 74.21 | N30: =IF(F30="",MEDIAN(SalesTbl[Quantity]),F30) -> 2
A31: SALE29 | B31: 45302 | C31: CUST1348 | D31: PROD99 | E31: STORE3 | G31: 451.67 | H31: 0.15 | I31: Credit Card | J31: 1535.678 | K31: =IF(J31="",MEDIAN(SalesTbl[Total_Amount]),J31) -> 1535.678 | L31: =IF(H31="",MEDIAN(SalesTbl[Discount]),H31) -> 0.15 | M31: =IF(G31="",MEDIAN(SalesTbl[Unit_Price]),G31) -> 451.67 | N31: =IF(F31="",MEDIAN(SalesTbl[Quantity]),F31) -> 2
A32: SALE30 | B32: 45217 | C32: CUST1028 | D32: PROD5 | E32: STORE19 | F32: 1 | G32: 429.38 | H32: 0.13 | I32: PayPal | J32: 373.5606 | K32: =IF(J32="",MEDIAN(SalesTbl[Total_Amount]),J32) -> 373.5606 | L32: =IF(H32="",MEDIAN(SalesTbl[Discount]),H32) -> 0.13 | M32: =IF(G32="",MEDIAN(SalesTbl[Unit_Price]),G32) -> 429.38 | N32: =IF(F32="",MEDIAN(SalesTbl[Quantity]),F32) -> 1
A33: SALE31 | B33: 45593 | C33: CUST1412 | D33: PROD53 | E33: STORE12 | F33: 2 | G33: 148.96 | H33: 0.03 | I33: COD | J33: 288.9824 | K33: =IF(J33="",MEDIAN(SalesTbl[Total_Amount]),J33) -> 288.9824 | L33: =IF(H33="",MEDIAN(SalesTbl[Discount]),H33) -> 0.03 | M33: =IF(G33="",MEDIAN(SalesTbl[Unit_Price]),G33) -> 148.96 | N33: =IF(F33="",MEDIAN(SalesTbl[Quantity]),F33) -> 2
A34: SALE32 | B34: 45597 | C34: CUST1398 | D34: PROD75 | E34: STORE8 | F34: 4 | G34: 313.83 | H34: 0.08 | I34: Credit Card | J34: 1154.8944 | K34: =IF(J34="",MEDIAN(SalesTbl[Total_Amount]),J34) -> 1154.8944 | L34: =IF(H34="",MEDIAN(SalesTbl[Discount]),H34) -> 0.08 | M34: =IF(G34="",MEDIAN(SalesTbl[Unit_Price]),G34) -> 313.83 | N34: =IF(F34="",MEDIAN(SalesTbl[Quantity]),F34) -> 4
A35: SALE33 | B35: 45620 | C35: CUST1453 | D35: PROD12 | E35: STORE6 | F35: 2 | G35: 717.31 | H35: 0.15 | I35: Credit Card | J35: 1219.427 | K35: =IF(J35="",MEDIAN(SalesTbl[Total_Amount]),J35) -> 1219.427 | L35: =IF(H35="",MEDIAN(SalesTbl[Discount]),H35) -> 0.15 | M35: =IF(G35="",MEDIAN(SalesTbl[Unit_Price]),G35) -> 717.31 | N35: =IF(F35="",MEDIAN(SalesTbl[Quantity]),F35) -> 2
A36: SALE34 | B36: 45215 | C36: CUST1344 | D36: PROD79 | E36: STORE1 | G36: 873.22 | H36: 0.18 | I36: Credit Card | J36: 2148.1212 | K36: =IF(J36="",MEDIAN(SalesTbl[Total_Amount]),J36) -> 2148.1212 | L36: =IF(H36="",MEDIAN(SalesTbl[Discount]),H36) -> 0.18 | M36: =IF(G36="",MEDIAN(SalesTbl[Unit_Price]),G36) -> 873.22 | N36: =IF(F36="",MEDIAN(SalesTbl[Quantity]),F36) -> 2
A37: SALE35 | B37: 45878 | C37: CUST1218 | D37: PROD16 | E37: STORE3 | F37: 4 | G37: 109.36 | H37: 0.19 | I37: COD | J37: 354.3264 | K37: =IF(J37="",MEDIAN(SalesTbl[Total_Amount]),J37) -> 354.3264 | L37: =IF(H37="",MEDIAN(SalesTbl[Discount]),H37) -> 0.19 | M37: =IF(G37="",MEDIAN(SalesTbl[Unit_Price]),G37) -> 109.36 | N37: =IF(F37="",MEDIAN(SalesTbl[Quantity]),F37) -> 4
A38: SALE36 | B38: 45635 | C38: CUST1086 | D38: PROD5 | E38: STORE7 | F38: 3 | G38: 559.52 | H38: 0.16 | I38: PayPal | J38: 1409.9904 | K38: =IF(J38="",MEDIAN(SalesTbl[Total_Amount]),J38) -> 1409.9904 | L38: =IF(H38="",MEDIAN(SalesTbl[Discount]),H38) -> 0.16 | M38: =IF(G38="",MEDIAN(SalesTbl[Unit_Price]),G38) -> 559.52 | N38: =IF(F38="",MEDIAN(SalesTbl[Quantity]),F38) -> 3
A39: SALE37 | B39: 45329 | C39: CUST1492 | D39: PROD10 | E39: STORE17 | F39: 3 | G39: 121.76 | H39: 0.27 | I39: PayPal | J39: 266.6544 | K39: =IF(J39="",MEDIAN(SalesTbl[Total_Amount]),J39) -> 266.6544 | L39: =IF(H39="",MEDIAN(SalesTbl[Discount]),H39) -> 0.27 | M39: =IF(G39="",MEDIAN(SalesTbl[Unit_Price]),G39) -> 121.76 | N39: =IF(F39="",MEDIAN(SalesTbl[Quantity]),F39) -> 3
A40: SALE38 | B40: 45378 | C40: CUST1189 | D40: PROD33 | E40: STORE13 | F40: 4 | G40: 735.32 | H40: 0.06 | I40: COD | J40: 2764.8032 | K40: =IF(J40="",MEDIAN(SalesTbl[Total_Amount]),J40) -> 2764.8032 | L40: =IF(H40="",MEDIAN(SalesTbl[Discount]),H40) -> 0.06 | M40: =IF(G40="",MEDIAN(SalesTbl[Unit_Price]),G40) -> 735.32 | N40: =IF(F40="",MEDIAN(SalesTbl[Quantity]),F40) -> 4
A41: SALE39 | B41: 45264 | C41: CUST1431 | D41: PROD94 | E41: STORE3 | F41: 2 | G41: 600.73 | H41: 0.08 | I41: Credit Card | J41: 1105.3432 | K41: =IF(J41="",MEDIAN(SalesTbl[Total_Amount]),J41) -> 1105.3432 | L41: =IF(H41="",MEDIAN(SalesTbl[Discount]),H41) -> 0.08 | M41: =IF(G41="",MEDIAN(SalesTbl[Unit_Price]),G41) -> 600.73 | N41: =IF(F41="",MEDIAN(SalesTbl[Quantity]),F41) -> 2
A42: SALE40 | B42: 45486 | C42: CUST1072 | D42: PROD26 | E42: STORE19 | F42: 2 | G42: 873.86 | H42: 0.07 | I42: COD | J42: 1625.3796 | K42: =IF(J42="",MEDIAN(SalesTbl[Total_Amount]),J42) -> 1625.3796 | L42: =IF(H42="",MEDIAN(SalesTbl[Discount]),H42) -> 0.07 | M42: =IF(G42="",MEDIAN(SalesTbl[Unit_Price]),G42) -> 873.86 | N42: =IF(F42="",MEDIAN(SalesTbl[Quantity]),F42) -> 2
A43: SALE41 | B43: 45241 | C43: CUST1302 | D43: PROD23 | E43: STORE8 | F43: 3 | G43: 342.47 | H43: 0.08 | I43: PayPal | J43: 945.2172 | K43: =IF(J43="",MEDIAN(SalesTbl[Total_Amount]),J43) -> 945.2172 | L43: =IF(H43="",MEDIAN(SalesTbl[Discount]),H43) -> 0.08 | M43: =IF(G43="",MEDIAN(SalesTbl[Unit_Price]),G43) -> 342.47 | N43: =IF(F43="",MEDIAN(SalesTbl[Quantity]),F43) -> 3
A44: SALE42 | B44: 45649 | C44: CUST1335 | D44: PROD29 | E44: STORE9 | F44: 2 | G44: 915.15 | H44: 0.16 | I44: PayPal | J44: 1537.452 | K44: =IF(J44="",MEDIAN(SalesTbl[Total_Amount]),J44) -> 1537.452 | L44: =IF(H44="",MEDIAN(SalesTbl[Discount]),H44) -> 0.16 | M44: =IF(G44="",MEDIAN(SalesTbl[Unit_Price]),G44) -> 915.15 | N44: =IF(F44="",MEDIAN(SalesTbl[Quantity]),F44) -> 2
A45: SALE43 | B45: 45677 | C45: CUST1084 | D45: PROD33 | E45: STORE17 | G45: 863.11 | H45: 0.28 | I45: PayPal | J45: 1864.3176 | K45: =IF(J45="",MEDIAN(SalesTbl[Total_Amount]),J45) -> 1864.3176 | L45: =IF(H45="",MEDIAN(SalesTbl[Discount]),H45) -> 0.28 | M45: =IF(G45="",MEDIAN(SalesTbl[Unit_Price]),G45) -> 863.11 | N45: =IF(F45="",MEDIAN(SalesTbl[Quantity]),F45) -> 2
A46: SALE44 | B46: 45538 | C46: CUST1203 | D46: PROD43 | E46: STORE12 | F46: 2 | G46: 209.32 | H46: 0.23 | I46: COD | J46: 322.3528 | K46: =IF(J46="",MEDIAN(SalesTbl[Total_Amount]),J46) -> 322.3528 | L46: =IF(H46="",MEDIAN(SalesTbl[Discount]),H46) -> 0.23 | M46: =IF(G46="",MEDIAN(SalesTbl[Unit_Price]),G46) -> 209.32 | N46: =IF(F46="",MEDIAN(SalesTbl[Quantity]),F46) -> 2
A47: SALE45 | B47: 45606 | C47: CUST1470 | D47: PROD59 | E47: STORE8 | F47: 4 | G47: 288.6 | H47: 0.09 | I47: PayPal | J47: 1050.504 | K47: =IF(J47="",MEDIAN(SalesTbl[Total_Amount]),J47) -> 1050.504 | L47: =IF(H47="",MEDIAN(SalesTbl[Discount]),H47) -> 0.09 | M47: =IF(G47="",MEDIAN(SalesTbl[Unit_Price]),G47) -> 288.6 | N47: =IF(F47="",MEDIAN(SalesTbl[Quantity]),F47) -> 4
A48: SALE46 | B48: 45570 | C48: CUST1070 | D48: PROD78 | E48: STORE16 | F48: 1 | G48: 418.69 | H48: 0.06 | I48: PayPal | J48: 393.5686 | K48: =IF(J48="",MEDIAN(SalesTbl[Total_Amount]),J48) -> 393.5686 | L48: =IF(H48="",MEDIAN(SalesTbl[Discount]),H48) -> 0.06 | M48: =IF(G48="",MEDIAN(SalesTbl[Unit_Price]),G48) -> 418.69 | N48: =IF(F48="",MEDIAN(SalesTbl[Quantity]),F48) -> 1
A49: SALE47 | B49: 45466 | C49: CUST1008 | D49: PROD30 | E49: STORE11 | F49: 1 | G49: 135.78 | H49: 0.14 | I49: PayPal | J49: 116.7708 | K49: =IF(J49="",MEDIAN(SalesTbl[Total_Amount]),J49) -> 116.7708 | L49: =IF(H49="",MEDIAN(SalesTbl[Discount]),H49) -> 0.14 | M49: =IF(G49="",MEDIAN(SalesTbl[Unit_Price]),G49) -> 135.78 | N49: =IF(F49="",MEDIAN(SalesTbl[Quantity]),F49) -> 1
A50: SALE48 | B50: 45218 | C50: CUST1203 | D50: PROD44 | E50: STORE17 | F50: 1 | G50: 517.13 | H50: 0.28 | I50: Credit Card | J50: 372.3336 | K50: =IF(J50="",MEDIAN(SalesTbl[Total_Amount]),J50) -> 372.3336 | L50: =IF(H50="",MEDIAN(SalesTbl[Discount]),H50) -> 0.28 | M50: =IF(G50="",MEDIAN(SalesTbl[Unit_Price]),G50) -> 517.13 | N50: =IF(F50="",MEDIAN(SalesTbl[Quantity]),F50) -> 1
A51: SALE49 | B51: 45607 | C51: CUST1420 | D51: PROD21 | E51: STORE16 | F51: 2 | G51: 384.66 | H51: 0.08 | I51: COD | J51: 707.7744 | K51: =IF(J51="",MEDIAN(SalesTbl[Total_Amount]),J51) -> 707.7744 | L51: =IF(H51="",MEDIAN(SalesTbl[Discount]),H51) -> 0.08 | M51: =IF(G51="",MEDIAN(SalesTbl[Unit_Price]),G51) -> 384.66 | N51: =IF(F51="",MEDIAN(SalesTbl[Quantity]),F51) -> 2
A52: SALE50 | B52: 45291 | C52: CUST1070 | D52: PROD52 | E52: STORE9 | F52: 3 | G52: 83.7 | H52: 0.24 | I52: PayPal | J52: 190.836 | K52: =IF(J52="",MEDIAN(SalesTbl[Total_Amount]),J52) -> 190.836 | L52: =IF(H52="",MEDIAN(SalesTbl[Discount]),H52) -> 0.24 | M52: =IF(G52="",MEDIAN(SalesTbl[Unit_Price]),G52) -> 83.7 | N52: =IF(F52="",MEDIAN(SalesTbl[Quantity]),F52) -> 3
A53: SALE51 | B53: 45689 | C53: CUST1142 | D53: PROD69 | E53: STORE7 | F53: 3 | G53: 76.57 | H53: 0.26 | I53: Credit Card | J53: 169.9854 | K53: =IF(J53="",MEDIAN(SalesTbl[Total_Amount]),J53) -> 169.9854 | L53: =IF(H53="",MEDIAN(SalesTbl[Discount]),H53) -> 0.26 | M53: =IF(G53="",MEDIAN(SalesTbl[Unit_Price]),G53) -> 76.57 | N53: =IF(F53="",MEDIAN(SalesTbl[Quantity]),F53) -> 3
A54: SALE52 | B54: 45894 | C54: CUST1148 | D54: PROD89 | E54: STORE6 | F54: 3 | I54: Credit Card | J54: 486.0633 | K54: =IF(J54="",MEDIAN(SalesTbl[Total_Amount]),J54) -> 486.0633 | L54: =IF(H54="",MEDIAN(SalesTbl[Discount]),H54) -> 0.14 | M54: =IF(G54="",MEDIAN(SalesTbl[Unit_Price]),G54) -> 527.905 | N54: =IF(F54="",MEDIAN(SalesTbl[Quantity]),F54) -> 3
A55: SALE53 | B55: 45677 | C55: CUST1324 | D55: PROD20 | E55: STORE8 | F55: 1 | G55: 900.35 | H55: 0.13 | I55: COD | J55: 783.3045 | K55: =IF(J55="",MEDIAN(SalesTbl[Total_Amount]),J55) -> 783.3045 | L55: =IF(H55="",MEDIAN(SalesTbl[Discount]),H55) -> 0.13 | M55: =IF(G55="",MEDIAN(SalesTbl[Unit_Price]),G55) -> 900.35 | N55: =IF(F55="",MEDIAN(SalesTbl[Quantity]),F55) -> 1
A56: SALE54 | B56: 45706 | C56: CUST1095 | D56: PROD40 | E56: STORE10 | F56: 4 | G56: 428.09 | H56: 0.07 | I56: Credit Card | J56: 1592.4948 | K56: =IF(J56="",MEDIAN(SalesTbl[Total_Amount]),J56) -> 1592.4948 | L56: =IF(H56="",MEDIAN(SalesTbl[Discount]),H56) -> 0.07 | M56: =IF(G56="",MEDIAN(SalesTbl[Unit_Price]),G56) -> 428.09 | N56: =IF(F56="",MEDIAN(SalesTbl[Quantity]),F56) -> 4
A57: SALE55 | B57: 45589 | C57: CUST1416 | D57: PROD49 | E57: STORE11 | F57: 2 | G57: 559.71 | H57: 0.3 | I57: COD | J57: 783.594 | K57: =IF(J57="",MEDIAN(SalesTbl[Total_Amount]),J57) -> 783.594 | L57: =IF(H57="",MEDIAN(SalesTbl[Discount]),H57) -> 0.3 | M57: =IF(G57="",MEDIAN(SalesTbl[Unit_Price]),G57) -> 559.71 | N57: =IF(F57="",MEDIAN(SalesTbl[Quantity]),F57) -> 2
A58: SALE56 | B58: 45282 | C58: CUST1080 | D58: PROD34 | E58: STORE6 | F58: 2 | G58: 833.7 | H58: 0.06 | I58: PayPal | J58: 1567.356 | K58: =IF(J58="",MEDIAN(SalesTbl[Total_Amount]),J58) -> 1567.356 | L58: =IF(H58="",MEDIAN(SalesTbl[Discount]),H58) -> 0.06 | M58: =IF(G58="",MEDIAN(SalesTbl[Unit_Price]),G58) -> 833.7 | N58: =IF(F58="",MEDIAN(SalesTbl[Quantity]),F58) -> 2
A59: SALE57 | B59: 45462 | C59: CUST1467 | D59: PROD47 | E59: STORE14 | F59: 2 | G59: 680.16 | H59: 0.28 | I59: Credit Card | J59: 979.4304 | K59: =IF(J59="",MEDIAN(SalesTbl[Total_Amount]),J59) -> 979.4304 | L59: =IF(H59="",MEDIAN(SalesTbl[Discount]),H59) -> 0.28 | M59: =IF(G59="",MEDIAN(SalesTbl[Unit_Price]),G59) -> 680.16 | N59: =IF(F59="",MEDIAN(SalesTbl[Quantity]),F59) -> 2
A60: SALE58 | B60: 45633 | C60: CUST1404 | D60: PROD89 | E60: STORE11 | F60: 1 | G60: 996.33 | H60: 0.23 | I60: PayPal | J60: 767.1741 | K60: =IF(J60="",MEDIAN(SalesTbl[Total_Amount]),J60) -> 767.1741 | L60: =IF(H60="",MEDIAN(SalesTbl[Discount]),H60) -> 0.23 | M60: =IF(G60="",MEDIAN(SalesTbl[Unit_Price]),G60) -> 996.33 | N60: =IF(F60="",MEDIAN(SalesTbl[Quantity]),F60) -> 1
A61: SALE59 | B61: 45257 | C61: CUST1367 | D61: PROD31 | E61: STORE10 | F61: 1 | G61: 198.83 | H61: 0.09 | I61: COD | J61: 180.9353 | K61: =IF(J61="",MEDIAN(SalesTbl[Total_Amount]),J61) -> 180.9353 | L61: =IF(H61="",MEDIAN(SalesTbl[Discount]),H61) -> 0.09 | M61: =IF(G61="",MEDIAN(SalesTbl[Unit_Price]),G61) -> 198.83 | N61: =IF(F61="",MEDIAN(SalesTbl[Quantity]),F61) -> 1
A62: SALE60 | B62: 45854 | C62: CUST1408 | D62: PROD19 | E62: STORE7 | F62: 1 | G62: 374.92 | H62: 0.18 | I62: PayPal | J62: 307.4344 | K62: =IF(J62="",MEDIAN(SalesTbl[Total_Amount]),J62) -> 307.4344 | L62: =IF(H62="",MEDIAN(SalesTbl[Discount]),H62) -> 0.18 | M62: =IF(G62="",MEDIAN(SalesTbl[Unit_Price]),G62) -> 374.92 | N62: =IF(F62="",MEDIAN(SalesTbl[Quantity]),F62) -> 1
A63: SALE61 | B63: 45716 | C63: CUST1239 | D63: PROD93 | E63: STORE16 | F63: 1 | G63: 468.94 | H63: 0.12 | I63: Credit Card | J63: 412.6672 | K63: =IF(J63="",MEDIAN(SalesTbl[Total_Amount]),J63) -> 412.6672 | L63: =IF(H63="",MEDIAN(SalesTbl[Discount]),H63) -> 0.12 | M63: =IF(G63="",MEDIAN(SalesTbl[Unit_Price]),G63) -> 468.94 | N63: =IF(F63="",MEDIAN(SalesTbl[Quantity]),F63) -> 1
A64: SALE62 | B64: 45515 | C64: CUST1464 | D64: PROD89 | E64: STORE12 | F64: 2 | G64: 121.37 | H64: 0.05 | I64: Credit Card | J64: 230.603 | K64: =IF(J64="",MEDIAN(SalesTbl[Total_Amount]),J64) -> 230.603 | L64: =IF(H64="",MEDIAN(SalesTbl[Discount]),H64) -> 0.05 | M64: =IF(G64="",MEDIAN(SalesTbl[Unit_Price]),G64) -> 121.37 | N64: =IF(F64="",MEDIAN(SalesTbl[Quantity]),F64) -> 2
A65: SALE63 | B65: 45927 | C65: CUST1126 | D65: PROD53 | E65: STORE10 | F65: 3 | G65: 480.06 | H65: 0.01 | I65: Credit Card | K65: =IF(J65="",MEDIAN(SalesTbl[Total_Amount]),J65) -> 837.2361 | L65: =IF(H65="",MEDIAN(SalesTbl[Discount]),H65) -> 0.01 | M65: =IF(G65="",MEDIAN(SalesTbl[Unit_Price]),G65) -> 480.06 | N65: =IF(F65="",MEDIAN(SalesTbl[Quantity]),F65) -> 3
A66: SALE64 | B66: 45914 | C66: CUST1255 | D66: PROD99 | E66: STORE17 | F66: 2 | G66: 856.57 | H66: 0.24 | I66: Credit Card | J66: 1301.9864 | K66: =IF(J66="",MEDIAN(SalesTbl[Total_Amount]),J66) -> 1301.9864 | L66: =IF(H66="",MEDIAN(SalesTbl[Discount]),H66) -> 0.24 | M66: =IF(G66="",MEDIAN(SalesTbl[Unit_Price]),G66) -> 856.57 | N66: =IF(F66="",MEDIAN(SalesTbl[Quantity]),F66) -> 2
A67: SALE65 | B67: 45290 | C67: CUST1162 | D67: PROD77 | E67: STORE2 | F67: 4 | G67: 814.25 | H67: 0.18 | I67: Credit Card | J67: 2670.74 | K67: =IF(J67="",MEDIAN(SalesTbl[Total_Amount]),J67) -> 2670.74 | L67: =IF(H67="",MEDIAN(SalesTbl[Discount]),H67) -> 0.18 | M67: =IF(G67="",MEDIAN(SalesTbl[Unit_Price]),G67) -> 814.25 | N67: =IF(F67="",MEDIAN(SalesTbl[Quantity]),F67) -> 4
A68: SALE66 | B68: 45213 | C68: CUST1269 | D68: PROD12 | E68: STORE2 | F68: 1 | G68: 989.17 | H68: 0.2 | I68: PayPal | J68: 791.336 | K68: =IF(J68="",MEDIAN(SalesTbl[Total_Amount]),J68) -> 791.336 | L68: =IF(H68="",MEDIAN(SalesTbl[Discount]),H68) -> 0.2 | M68: =IF(G68="",MEDIAN(SalesTbl[Unit_Price]),G68) -> 989.17 | N68: =IF(F68="",MEDIAN(SalesTbl[Quantity]),F68) -> 1
A69: SALE67 | B69: 45255 | C69: CUST1483 | D69: PROD72 | E69: STORE10 | F69: 4 | G69: 62.48 | H69: 0.18 | I69: Credit Card | J69: 204.9344 | K69: =IF(J69="",MEDIAN(SalesTbl[Total_Amount]),J69) -> 204.9344 | L69: =IF(H69="",MEDIAN(SalesTbl[Discount]),H69) -> 0.18 | M69: =IF(G69="",MEDIAN(SalesTbl[Unit_Price]),G69) -> 62.48 | N69: =IF(F69="",MEDIAN(SalesTbl[Quantity]),F69) -> 4
A70: SALE68 | B70: 45270 | C70: CUST1372 | D70: PROD13 | E70: STORE16 | F70: 4 | G70: 561.24 | H70: 0.24 | I70: Credit Card | J70: 1706.1696 | K70: =IF(J70="",MEDIAN(SalesTbl[Total_Amount]),J70) -> 1706.1696 | L70: =IF(H70="",MEDIAN(SalesTbl[Discount]),H70) -> 0.24 | M70: =IF(G70="",MEDIAN(SalesTbl[Unit_Price]),G70) -> 561.24 | N70: =IF(F70="",MEDIAN(SalesTbl[Quantity]),F70) -> 4
A71: SALE69 | B71: 45897 | C71: CUST1423 | D71: PROD60 | E71: STORE5 | F71: 3 | G71: 92.24 | H71: 0.28 | I71: COD | K71: =IF(J71="",MEDIAN(SalesTbl[Total_Amount]),J71) -> 837.2361 | L71: =IF(H71="",MEDIAN(SalesTbl[Discount]),H71) -> 0.28 | M71: =IF(G71="",MEDIAN(SalesTbl[Unit_Price]),G71) -> 92.24 | N71: =IF(F71="",MEDIAN(SalesTbl[Quantity]),F71) -> 3
A72: SALE70 | B72: 45849 | C72: CUST1058 | D72: PROD72 | E72: STORE1 | F72: 2 | G72: 668.3 | H72: 0.07 | I72: Credit Card | J72: 1243.038 | K72: =IF(J72="",MEDIAN(SalesTbl[Total_Amount]),J72) -> 1243.038 | L72: =IF(H72="",MEDIAN(SalesTbl[Discount]),H72) -> 0.07 | M72: =IF(G72="",MEDIAN(SalesTbl[Unit_Price]),G72) -> 668.3 | N72: =IF(F72="",MEDIAN(SalesTbl[Quantity]),F72) -> 2
A73: SALE71 | B73: 45889 | C73: CUST1168 | D73: PROD38 | E73: STORE5 | F73: 1 | G73: 553.82 | H73: 0.09 | I73: Credit Card | J73: 503.9762 | K73: =IF(J73="",MEDIAN(SalesTbl[Total_Amount]),J73) -> 503.9762 | L73: =IF(H73="",MEDIAN(SalesTbl[Discount]),H73) -> 0.09 | M73: =IF(G73="",MEDIAN(SalesTbl[Unit_Price]),G73) -> 553.82 | N73: =IF(F73="",MEDIAN(SalesTbl[Quantity]),F73) -> 1
A74: SALE72 | B74: 45533 | C74: CUST1409 | D74: PROD45 | E74: STORE11 | F74: 2 | G74: 556.43 | H74: 0.13 | I74: Credit Card | J74: 968.1882 | K74: =IF(J74="",MEDIAN(SalesTbl[Total_Amount]),J74) -> 968.1882 | L74: =IF(H74="",MEDIAN(SalesTbl[Discount]),H74) -> 0.13 | M74: =IF(G74="",MEDIAN(SalesTbl[Unit_Price]),G74) -> 556.43 | N74: =IF(F74="",MEDIAN(SalesTbl[Quantity]),F74) -> 2
A75: SALE73 | B75: 45626 | C75: CUST1037 | D75: PROD97 | E75: STORE12 | F75: 4 | G75: 700.18 | H75: 0.23 | I75: Credit Card | J75: 2156.5544 | K75: =IF(J75="",MEDIAN(SalesTbl[Total_Amount]),J75) -> 2156.5544 | L75: =IF(H75="",MEDIAN(SalesTbl[Discount]),H75) -> 0.23 | M75: =IF(G75="",MEDIAN(SalesTbl[Unit_Price]),G75) -> 700.18 | N75: =IF(F75="",MEDIAN(SalesTbl[Quantity]),F75) -> 4
A76: SALE74 | B76: 45942 | C76: CUST1273 | D76: PROD76 | E76: STORE10 | F76: 2 | G76: 686.31 | H76: 0.25 | I76: Credit Card | J76: 1029.465 | K76: =IF(J76="",MEDIAN(SalesTbl[Total_Amount]),J76) -> 1029.465 | L76: =IF(H76="",MEDIAN(SalesTbl[Discount]),H76) -> 0.25 | M76: =IF(G76="",MEDIAN(SalesTbl[Unit_Price]),G76) -> 686.31 | N76: =IF(F76="",MEDIAN(SalesTbl[Quantity]),F76) -> 2
A77: SALE75 | B77: 45500 | C77: CUST1035 | D77: PROD67 | E77: STORE15 | F77: 1 | G77: 687.82 | H77: 0.27 | I77: COD | J77: 502.1086 | K77: =IF(J77="",MEDIAN(SalesTbl[Total_Amount]),J77) -> 502.1086 | L77: =IF(H77="",MEDIAN(SalesTbl[Discount]),H77) -> 0.27 | M77: =IF(G77="",MEDIAN(SalesTbl[Unit_Price]),G77) -> 687.82 | N77: =IF(F77="",MEDIAN(SalesTbl[Quantity]),F77) -> 1
A78: SALE76 | B78: 45285 | C78: CUST1019 | D78: PROD83 | E78: STORE8 | F78: 2 | G78: 900.55 | H78: 0.16 | I78: Credit Card | J78: 1512.924 | K78: =IF(J78="",MEDIAN(SalesTbl[Total_Amount]),J78) -> 1512.924 | L78: =IF(H78="",MEDIAN(SalesTbl[Discount]),H78) -> 0.16 | M78: =IF(G78="",MEDIAN(SalesTbl[Unit_Price]),G78) -> 900.55 | N78: =IF(F78="",MEDIAN(SalesTbl[Quantity]),F78) -> 2
A79: SALE77 | B79: 45800 | C79: CUST1007 | D79: PROD21 | E79: STORE2 | F79: 1 | G79: 341.17 | H79: 0.15 | I79: Credit Card | J79: 289.9945 | K79: =IF(J79="",MEDIAN(SalesTbl[Total_Amount]),J79) -> 289.9945 | L79: =IF(H79="",MEDIAN(SalesTbl[Discount]),H79) -> 0.15 | M79: =IF(G79="",MEDIAN(SalesTbl[Unit_Price]),G79) -> 341.17 | N79: =IF(F79="",MEDIAN(SalesTbl[Quantity]),F79) -> 1
A80: SALE78 | B80: 45609 | C80: CUST1221 | D80: PROD52 | E80: STORE8 | F80: 1 | G80: 442.27 | H80: 0.06 | I80: COD | J80: 415.7338 | K80: =IF(J80="",MEDIAN(SalesTbl[Total_Amount]),J80) -> 415.7338 | L80: =IF(H80="",MEDIAN(SalesTbl[Discount]),H80) -> 0.06 | M80: =IF(G80="",MEDIAN(SalesTbl[Unit_Price]),G80) -> 442.27 | N80: =IF(F80="",MEDIAN(SalesTbl[Quantity]),F80) -> 1
A81: SALE79 | B81: 45268 | C81: CUST1115 | D81: PROD71 | E81: STORE9 | F81: 1 | G81: 363.73 | H81: 0.25 | I81: PayPal | J81: 272.7975 | K81: =IF(J81="",MEDIAN(SalesTbl[Total_Amount]),J81) -> 272.7975 | L81: =IF(H81="",MEDIAN(SalesTbl[Discount]),H81) -> 0.25 | M81: =IF(G81="",MEDIAN(SalesTbl[Unit_Price]),G81) -> 363.73 | N81: =IF(F81="",MEDIAN(SalesTbl[Quantity]),F81) -> 1
A82: SALE80 | B82: 45885 | C82: CUST1176 | D82: PROD91 | E82: STORE17 | F82: 2 | G82: 601.33 | H82: 0.16 | I82: PayPal | J82: 1010.2344 | K82: =IF(J82="",MEDIAN(SalesTbl[Total_Amount]),J82) -> 1010.2344 | L82: =IF(H82="",MEDIAN(SalesTbl[Discount]),H82) -> 0.16 | M82: =IF(G82="",MEDIAN(SalesTbl[Unit_Price]),G82) -> 601.33 | N82: =IF(F82="",MEDIAN(SalesTbl[Quantity]),F82) -> 2
A83: SALE81 | B83: 45616 | C83: CUST1253 | D83: PROD17 | E83: STORE18 | F83: 4 | G83: 34.39 | H83: 0.03 | I83: PayPal | J83: 133.4332 | K83: =IF(J83="",MEDIAN(SalesTbl[Total_Amount]),J83) -> 133.4332 | L83: =IF(H83="",MEDIAN(SalesTbl[Discount]),H83) -> 0.03 | M83: =IF(G83="",MEDIAN(SalesTbl[Unit_Price]),G83) -> 34.39 | N83: =IF(F83="",MEDIAN(SalesTbl[Quantity]),F83) -> 4
A84: SALE82 | B84: 45518 | C84: CUST1378 | D84: PROD46 | E84: STORE17 | F84: 1 | G84: 773.57 | H84: 0.05 | I84: COD | K84: =IF(J84="",MEDIAN(SalesTbl[Total_Amount]),J84) -> 837.2361 | L84: =IF(H84="",MEDIAN(SalesTbl[Discount]),H84) -> 0.05 | M84: =IF(G84="",MEDIAN(SalesTbl[Unit_Price]),G84) -> 773.57 | N84: =IF(F84="",MEDIAN(SalesTbl[Quantity]),F84) -> 1
A85: SALE83 | B85: 45427 | C85: CUST1403 | D85: PROD88 | E85: STORE7 | F85: 4 | G85: 127.1 | H85: 0.24 | I85: COD | J85: 386.384 | K85: =IF(J85="",MEDIAN(SalesTbl[Total_Amount]),J85) -> 386.384 | L85: =IF(H85="",MEDIAN(SalesTbl[Discount]),H85) -> 0.24 | M85: =IF(G85="",MEDIAN(SalesTbl[Unit_Price]),G85) -> 127.1 | N85: =IF(F85="",MEDIAN(SalesTbl[Quantity]),F85) -> 4
A86: SALE84 | B86: 45268 | C86: CUST1423 | D86: PROD20 | E86: STORE3 | F86: 3 | G86: 899.58 | H86: 0.28 | I86: PayPal | J86: 1943.0928 | K86: =IF(J86="",MEDIAN(SalesTbl[Total_Amount]),J86) -> 1943.0928 | L86: =IF(H86="",MEDIAN(SalesTbl[Discount]),H86) -> 0.28 | M86: =IF(G86="",MEDIAN(SalesTbl[Unit_Price]),G86) -> 899.58 | N86: =IF(F86="",MEDIAN(SalesTbl[Quantity]),F86) -> 3
A87: SALE85 | B87: 45282 | C87: CUST1054 | D87: PROD1 | E87: STORE10 | F87: 3 | G87: 964.39 | H87: 0.04 | I87: Credit Card | J87: 2777.4432 | K87: =IF(J87="",MEDIAN(SalesTbl[Total_Amount]),J87) -> 2777.4432 | L87: =IF(H87="",MEDIAN(SalesTbl[Discount]),H87) -> 0.04 | M87: =IF(G87="",MEDIAN(SalesTbl[Unit_Price]),G87) -> 964.39 | N87: =IF(F87="",MEDIAN(SalesTbl[Quantity]),F87) -> 3
A88: SALE86 | B88: 45545 | C88: CUST1303 | D88: PROD38 | E88: STORE0 | F88: 2 | G88: 217.83 | H88: 0.14 | I88: PayPal | J88: 374.6676 | K88: =IF(J88="",MEDIAN(SalesTbl[Total_Amount]),J88) -> 374.6676 | L88: =IF(H88="",MEDIAN(SalesTbl[Discount]),H88) -> 0.14 | M88: =IF(G88="",MEDIAN(SalesTbl[Unit_Price]),G88) -> 217.83 | N88: =IF(F88="",MEDIAN(SalesTbl[Quantity]),F88) -> 2
A89: SALE87 | B89: 45755 | C89: CUST1327 | D89: PROD17 | E89: STORE1 | F89: 4 | G89: 187.71 | H89: 0.06 | I89: COD | J89: 705.7896 | K89: =IF(J89="",MEDIAN(SalesTbl[Total_Amount]),J89) -> 705.7896 | L89: =IF(H89="",MEDIAN(SalesTbl[Discount]),H89) -> 0.06 | M89: =IF(G89="",MEDIAN(SalesTbl[Unit_Price]),G89) -> 187.71 | N89: =IF(F89="",MEDIAN(SalesTbl[Quantity]),F89) -> 4
A90: SALE88 | B90: 45588 | C90: CUST1183 | D90: PROD33 | E90: STORE18 | F90: 2 | G90: 350.12 | H90: 0.12 | I90: COD | J90: 616.2112 | K90: =IF(J90="",MEDIAN(SalesTbl[Total_Amount]),J90) -> 616.2112 | L90: =IF(H90="",MEDIAN(SalesTbl[Discount]),H90) -> 0.12 | M90: =IF(G90="",MEDIAN(SalesTbl[Unit_Price]),G90) -> 350.12 | N90: =IF(F90="",MEDIAN(SalesTbl[Quantity]),F90) -> 2
A91: SALE89 | B91: 45848 | C91: CUST1143 | D91: PROD16 | E91: STORE1 | F91: 4 | G91: 102.19 | H91: 0.17 | I91: PayPal | J91: 339.2708 | K91: =IF(J91="",MEDIAN(SalesTbl[Total_Amount]),J91) -> 339.2708 | L91: =IF(H91="",MEDIAN(SalesTbl[Discount]),H91) -> 0.17 | M91: =IF(G91="",MEDIAN(SalesTbl[Unit_Price]),G91) -> 102.19 | N91: =IF(F91="",MEDIAN(SalesTbl[Quantity]),F91) -> 4
A92: SALE90 | B92: 45577 | C92: CUST1010 | D92: PROD86 | E92: STORE4 | F92: 1 | G92: 696.53 | H92: 0.17 | I92: Credit Card | J92: 578.1199 | K92: =IF(J92="",MEDIAN(SalesTbl[Total_Amount]),J92) -> 578.1199 | L92: =IF(H92="",MEDIAN(SalesTbl[Discount]),H92) -> 0.17 | M92: =IF(G92="",MEDIAN(SalesTbl[Unit_Price]),G92) -> 696.53 | N92: =IF(F92="",MEDIAN(SalesTbl[Quantity]),F92) -> 1
A93: SALE91 | B93: 45312 | C93: CUST1406 | D93: PROD19 | E93: STORE4 | F93: 2 | G93: 327.52 | H93: 0.15 | I93: PayPal | J93: 556.784 | K93: =IF(J93="",MEDIAN(SalesTbl[Total_Amount]),J93) -> 556.784 | L93: =IF(H93="",MEDIAN(SalesTbl[Discount]),H93) -> 0.15 | M93: =IF(G93="",MEDIAN(SalesTbl[Unit_Price]),G93) -> 327.52 | N93: =IF(F93="",MEDIAN(SalesTbl[Quantity]),F93) -> 2
A94: SALE92 | B94: 45350 | C94: CUST1007 | D94: PROD97 | E94: STORE19 | F94: 2 | G94: 569.36 | H94: 0.01 | I94: PayPal | K94: =IF(J94="",MEDIAN(SalesTbl[Total_Amount]),J94) -> 837.2361 | L94: =IF(H94="",MEDIAN(SalesTbl[Discount]),H94) -> 0.01 | M94: =IF(G94="",MEDIAN(SalesTbl[Unit_Price]),G94) -> 569.36 | N94: =IF(F94="",MEDIAN(SalesTbl[Quantity]),F94) -> 2
A95: SALE93 | B95: 45657 | C95: CUST1065 | D95: PROD99 | E95: STORE6 | F95: 2 | G95: 68.29 | H95: 0.14 | I95: COD | J95: 117.4588 | K95: =IF(J95="",MEDIAN(SalesTbl[Total_Amount]),J95) -> 117.4588 | L95: =IF(H95="",MEDIAN(SalesTbl[Discount]),H95) -> 0.14 | M95: =IF(G95="",MEDIAN(SalesTbl[Unit_Price]),G95) -> 68.29 | N95: =IF(F95="",MEDIAN(SalesTbl[Quantity]),F95) -> 2
A96: SALE94 | B96: 45530 | C96: CUST1298 | D96: PROD50 | E96: STORE10 | F96: 1 | G96: 842.9 | H96: 0.06 | I96: COD | J96: 792.326 | K96: =IF(J96="",MEDIAN(SalesTbl[Total_Amount]),J96) -> 792.326 | L96: =IF(H96="",MEDIAN(SalesTbl[Discount]),H96) -> 0.06 | M96: =IF(G96="",MEDIAN(SalesTbl[Unit_Price]),G96) -> 842.9 | N96: =IF(F96="",MEDIAN(SalesTbl[Quantity]),F96) -> 1
A97: SALE95 | B97: 45556 | C97: CUST1321 | D97: PROD3 | E97: STORE3 | F97: 3 | G97: 751.94 | H97: 0.26 | I97: PayPal | J97: 1669.3068 | K97: =IF(J97="",MEDIAN(SalesTbl[Total_Amount]),J97) -> 1669.3068 | L97: =IF(H97="",MEDIAN(SalesTbl[Discount]),H97) -> 0.26 | M97: =IF(G97="",MEDIAN(SalesTbl[Unit_Price]),G97) -> 751.94 | N97: =IF(F97="",MEDIAN(SalesTbl[Quantity]),F97) -> 3
A98: SALE96 | B98: 45523 | C98: CUST1244 | D98: PROD56 | E98: STORE7 | F98: 4 | G98: 476.28 | H98: 0.17 | I98: Credit Card | J98: 1581.2496 | K98: =IF(J98="",MEDIAN(SalesTbl[Total_Amount]),J98) -> 1581.2496 | L98: =IF(H98="",MEDIAN(SalesTbl[Discount]),H98) -> 0.17 | M98: =IF(G98="",MEDIAN(SalesTbl[Unit_Price]),G98) -> 476.28 | N98: =IF(F98="",MEDIAN(SalesTbl[Quantity]),F98) -> 4
A99: SALE97 | B99: 45587 | C99: CUST1287 | D99: PROD54 | E99: STORE3 | F99: 3 | G99: 541.99 | H99: 0.24 | I99: COD | J99: 1235.7372 | K99: =IF(J99="",MEDIAN(SalesTbl[Total_Amount]),J99) -> 1235.7372 | L99: =IF(H99="",MEDIAN(SalesTbl[Discount]),H99) -> 0.24 | M99: =IF(G99="",MEDIAN(SalesTbl[Unit_Price]),G99) -> 541.99 | N99: =IF(F99="",MEDIAN(SalesTbl[Quantity]),F99) -> 3
A100: SALE98 | B100: 45580 | C100: CUST1131 | D100: PROD33 | E100: STORE5 | F100: 2 | G100: 401.5 | H100: 0.18 | I100: Credit Card | J100: 658.46 | K100: =IF(J100="",MEDIAN(SalesTbl[Total_Amount]),J100) -> 658.46 | L100: =IF(H100="",MEDIAN(SalesTbl[Discount]),H100) -> 0.18 | M100: =IF(G100="",MEDIAN(SalesTbl[Unit_Price]),G100) -> 401.5 | N100: =IF(F100="",MEDIAN(SalesTbl[Quantity]),F100) -> 2
...

Sheet Data_Analysis
A1: Sales_ID | B1: Order_Date | C1: Customer_ID | D1: Product_ID | E1: Product Name | F1: Cost of Product | G1: Store_ID | H1: Quantity | I1: Unit_Price | J1: Discount | K1: Payment_Type | L1: Total_Amount | M1: Gender | N1: Age | O1: Customer City | P1: Customer Level | Q1: Store City | R1: Store Region
A2: SALE0 | B2: 45480 | C2: CUST1409 | D2: PROD97 | E2: =VLOOKUP(D2,[2]Product_Dim!$A$2:$G$101,2,FALSE) -> Cricket Bat | F2: =VLOOKUP(D2,[2]Product_Dim!$A$2:$G$101,6,FALSE) -> 245.98 | G2: STORE3 | H2: 1 | I2: 218.04 | J2: 0.09 | K2: Credit Card | L2: 198.4164 | M2: =VLOOKUP(C2,'[2]Customer Detail'!$A$2:$H$501,4,FALSE) -> Male | N2: =VLOOKUP(C2,'[2]Customer Detail'!$A$2:$H$501,3,FALSE) -> 55 | O2: =VLOOKUP(C2,'[2]Customer Detail'!$A$2:$H$501,5,FALSE) -> Kathleenport | P2: =VLOOKUP(C2,'[2]Customer Detail'!$A$1:$H$501,8,FALSE) -> Gold | Q2: =VLOOKUP(G2,[2]Store_Dim!$A$1:$E$21,4,FALSE) -> Hoodberg | R2: =VLOOKUP(G2,[2]Store_Dim!$A$2:$E$21,3,FALSE) -> North
A3: SALE1 | B3: 45285 | C3: CUST1467 | D3: PROD74 | E3: =VLOOKUP(D3,[2]Product_Dim!$A$2:$G$101,2,FALSE) -> Bluetooth Car Audio System | F3: =VLOOKUP(D3,[2]Product_Dim!$A$2:$G$101,6,FALSE) -> 403.71 | G3: STORE17 | H3: 3 | I3: 104.47 | J3: 0.27 | K3: PayPal | L3: 228.7893 | M3: =VLOOKUP(C3,'[2]Customer Detail'!$A$2:$H$501,4,FALSE) -> Female | N3: =VLOOKUP(C3,'[2]Customer Detail'!$A$2:$H$501,3,FALSE) -> 63 | O3: =VLOOKUP(C3,'[2]Customer Detail'!$A$2:$H$501,5,FALSE) -> Oneillfurt | P3: =VLOOKUP(C3,'[2]Customer Detail'!$A$1:$H$501,8,FALSE) -> Gold | Q3: =VLOOKUP(G3,[2]Store_Dim!$A$1:$E$21,4,FALSE) -> Bensonhaven | R3: =VLOOKUP(G3,[2]Store_Dim!$A$2:$E$21,3,FALSE) -> North
A4: SALE2 | B4: 45357 | C4: CUST1056 | D4: PROD49 | E4: =VLOOKUP(D4,[2]Product_Dim!$A$2:$G$101,2,FALSE) -> Men's Roll-On Perfume | F4: =VLOOKUP(D4,[2]Product_Dim!$A$2:$G$101,6,FALSE) -> 43.29 | G4: STORE8 | H4: 4 | I4: 914.05 | J4: 0.25 | K4: Credit Card | L4: 2742.15 | M4: =VLOOKUP(C4,'[2]Customer Detail'!$A$2:$H$501,4,FALSE) -> Female | N4: =VLOOKUP(C4,'[2]Customer Detail'!$A$2:$H$501,3,FALSE) -> 49 | O4: =VLOOKUP(C4,'[2]Customer Detail'!$A$2:$H$501,5,FALSE) -> Deborahberg | P4: =VLOOKUP(C4,'[2]Customer Detail'!$A$1:$H$501,8,FALSE) -> Gold | Q4: =VLOOKUP(G4,[2]Store_Dim!$A$1:$E$21,4,FALSE) -> Thompsonborough | R4: =VLOOKUP(G4,[2]Store_Dim!$A$2:$E$21,3,FALSE) -> West
A5: SALE3 | B5: 45259 | C5: CUST1346 | D5: PROD76 | E5: =VLOOKUP(D5,[2]Product_Dim!$A$2:$G$101,2,FALSE) -> Wireless Mouse | F5: =VLOOKUP(D5,[2]Product_Dim!$A$2:$G$101,6,FALSE) -> 392.89 | G5: STORE8 | H5: 1 | I5: 921.51 | J5: 0.16 | K5: COD | L5: 774.0684 | M5: =VLOOKUP(C5,'[2]Customer Detail'!$A$2:$H$501,4,FALSE) -> Female | N5: =VLOOKUP(C5,'[2]Customer Detail'!$A$2:$H$501,3,FALSE) -> 58 | O5: =VLOOKUP(C5,'[2]Customer Detail'!$A$2:$H$501,5,FALSE) -> Port Crystalberg | P5: =VLOOKUP(C5,'[2]Customer Detail'!$A$1:$H$501,8,FALSE) -> Platinum | Q5: =VLOOKUP(G5,[2]Store_Dim!$A$1:$E$21,4,FALSE) -> Thompsonborough | R5: =VLOOKUP(G5,[2]Store_Dim!$A$2:$E$21,3,FALSE) -> West
A6: SALE4 | B6: 45444 | C6: CUST1493 | D6: PROD59 | E6: =VLOOKUP(D6,[2]Product_Dim!$A$2:$G$101,2,FALSE) -> Men's Hair Styling Gel | F6: =VLOOKUP(D6,[2]Product_Dim!$A$2:$G$101,6,FALSE) -> 17.31 | G6: STORE5 | H6: 3 | I6: 745.3 | J6: 0.18 | K6: Credit Card | L6: 1833.438 | M6: =VLOOKUP(C6,'[2]Customer Detail'!$A$2:$H$501,4,FALSE) -> Male | N6: =VLOOKUP(C6,'[2]Customer Detail'!$A$2:$H$501,3,FALSE) -> 28 | O6: =VLOOKUP(C6,'[2]Customer Detail'!$A$2:$H$501,5,FALSE) -> South William | P6: =VLOOKUP(C6,'[2]Customer Detail'!$A$1:$H$501,8,FALSE) -> Silver | Q6: =VLOOKUP(G6,[2]Store_Dim!$A$1:$E$21,4,FALSE) -> New Michaelchester | R6: =VLOOKUP(G6,[2]Store_Dim!$A$2:$E$21,3,FALSE) -> North
A7: SALE5 | B7: 45499 | C7: CUST1116 | D7: PROD15 | E7: =VLOOKUP(D7,[2]Product_Dim!$A$2:$G$101,2,FALSE) -> 4K Home Projector | F7: =VLOOKUP(D7,[2]Product_Dim!$A$2:$G$101,6,FALSE) -> 465.34 | G7: STORE7 | H7: 3 | I7: 147.01 | J7: 0.19 | K7: COD | L7: 357.2343 | M7: =VLOOKUP(C7,'[2]Customer Detail'!$A$2:$H$501,4,FALSE) -> Female | N7: =VLOOKUP(C7,'[2]Customer Detail'!$A$2:$H$501,3,FALSE) -> 18 | O7: =VLOOKUP(C7,'[2]Customer Detail'!$A$2:$H$501,5,FALSE) -> North Davidport | P7: =VLOOKUP(C7,'[2]Customer Detail'!$A$1:$H$501,8,FALSE) -> Platinum | Q7: =VLOOKUP(G7,[2]Store_Dim!$A$1:$E$21,4,FALSE) -> Williamsfurt | R7: =VLOOKUP(G7,[2]Store_Dim!$A$2:$E$21,3,FALSE) -> South
A8: SALE6 | B8: 45998 | C8: CUST1016 | D8: PROD56 | E8: =VLOOKUP(D8,[2]Product_Dim!$A$2:$G$101,2,FALSE) -> Premium Blanket Throw | F8: =VLOOKUP(D8,[2]Product_Dim!$A$2:$G$101,6,FALSE) -> 461.47 | G8: STORE4 | H8: 2 | I8: 785.31 | J8: 0.15 | K8: PayPal | L8: 1335.027 | M8: =VLOOKUP(C8,'[2]Customer Detail'!$A$2:$H$501,4,FALSE) -> Female | N8: =VLOOKUP(C8,'[2]Customer Detail'!$A$2:$H$501,3,FALSE) -> 24 | O8: =VLOOKUP(C8,'[2]Customer Detail'!$A$2:$H$501,5,FALSE) -> South Christopher | P8: =VLOOKUP(C8,'[2]Customer Detail'!$A$1:$H$501,8,FALSE) -> Bronze | Q8: =VLOOKUP(G8,[2]Store_Dim!$A$1:$E$21,4,FALSE) -> Port Sharon | R8: =VLOOKUP(G8,[2]Store_Dim!$A$2:$E$21,3,FALSE) -> South
A9: SALE7 | B9: 45248 | C9: CUST1152 | D9: PROD70 | E9: =VLOOKUP(D9,[2]Product_Dim!$A$2:$G$101,2,FALSE) -> Kitchen Storage Rack | F9: =VLOOKUP(D9,[2]Product_Dim!$A$2:$G$101,6,FALSE) -> 138.05 | G9: STORE8 | H9: 4 | I9: 342.39 | J9: 0.23 | K9: PayPal | L9: 1054.5612 | M9: =VLOOKUP(C9,'[2]Customer Detail'!$A$2:$H$501,4,FALSE) -> Female | N9: =VLOOKUP(C9,'[2]Customer Detail'!$A$2:$H$501,3,FALSE) -> 41 | O9: =VLOOKUP(C9,'[2]Customer Detail'!$A$2:$H$501,5,FALSE) -> Jaredville | P9: =VLOOKUP(C9,'[2]Customer Detail'!$A$1:$H$501,8,FALSE) -> Platinum | Q9: =VLOOKUP(G9,[2]Store_Dim!$A$1:$E$21,4,FALSE) -> Thompsonborough | R9: =VLOOKUP(G9,[2]Store_Dim!$A$2:$E$21,3,FALSE) -> West
A10: SALE8 | B10: 45752 | C10: CUST1187 | D10: PROD99 | E10: =VLOOKUP(D10,[2]Product_Dim!$A$2:$G$101,2,FALSE) -> Stainless Steel Cookware Set | F10: =VLOOKUP(D10,[2]Product_Dim!$A$2:$G$101,6,FALSE) -> 201.41 | G10: STORE5 | H10: 2.4802005 | I10: 448.25 | J10: 0.07 | K10: PayPal | L10: 1033.9274 | M10: =VLOOKUP(C10,'[3]Customer Detail'!$A$2:$H$501,4,FALSE) -> #N/A | N10: =VLOOKUP(C10,'[2]Customer Detail'!$A$2:$H$501,3,FALSE) -> 60 | O10: =VLOOKUP(C10,'[2]Customer Detail'!$A$2:$H$501,5,FALSE) -> Lake Blaketon | P10: =VLOOKUP(C10,'[2]Customer Detail'!$A$1:$H$501,8,FALSE) -> Platinum | Q10: =VLOOKUP(G10,[2]Store_Dim!$A$1:$E$21,4,FALSE) -> New Michaelchester | R10: =VLOOKUP(G10,[2]Store_Dim!$A$2:$E$21,3,FALSE) -> North
A11: SALE9 | B11: 45869 | C11: CUST1464 | D11: PROD33 | E11: =VLOOKUP(D11,[2]Product_Dim!$A$2:$G$101,2,FALSE) -> Modern Wall Clock | F11: =VLOOKUP(D11,[2]Product_Dim!$A$2:$G$101,6,FALSE) -> 179.77 | G11: STORE0 | H11: 2 | I11: 873.17 | J11: 0.23 | K11: PayPal | L11: 1344.6818 | M11: =VLOOKUP(C11,'[2]Customer Detail'!$A$2:$H$501,4,FALSE) -> Female | N11: =VLOOKUP(C11,'[2]Customer Detail'!$A$2:$H$501,3,FALSE) -> 45 | O11: =VLOOKUP(C11,'[2]Customer Detail'!$A$2:$H$501,5,FALSE) -> Grayland | P11: =VLOOKUP(C11,'[2]Customer Detail'!$A$1:$H$501,8,FALSE) -> Platinum | Q11: =VLOOKUP(G11,[2]Store_Dim!$A$1:$E$21,4,FALSE) -> Washingtonfurt | R11: =VLOOKUP(G11,[2]Store_Dim!$A$2:$E$21,3,FALSE) -> East
A12: SALE10 | B12: 45335 | C12: CUST1065 | D12: PROD24 | E12: =VLOOKUP(D12,[2]Product_Dim!$A$2:$G$101,2,FALSE) -> Foldable Camping Chair | F12: =VLOOKUP(D12,[2]Product_Dim!$A$2:$G$101,6,FALSE) -> 166.06 | G12: STORE14 | H12: 1 | I12: 278.63 | J12: 0.07 | K12: Credit Card | L12: 259.1259 | M12: =VLOOKUP(C12,'[2]Customer Detail'!$A$2:$H$501,4,FALSE) -> Female | N12: =VLOOKUP(C12,'[2]Customer Detail'!$A$2:$H$501,3,FALSE) -> 21 | O12: =VLOOKUP(C12,'[2]Customer Detail'!$A$2:$H$501,5,FALSE) -> Woodmouth | P12: =VLOOKUP(C12,'[2]Customer Detail'!$A$1:$H$501,8,FALSE) -> Silver | Q12: =VLOOKUP(G12,[2]Store_Dim!$A$1:$E$21,4,FALSE) -> Christopherland | R12: =VLOOKUP(G12,[2]Store_Dim!$A$2:$E$21,3,FALSE) -> South
A13: SALE11 | B13: 45801 | C13: CUST1320 | D13: PROD39 | E13: =VLOOKUP(D13,[2]Product_Dim!$A$2:$G$101,2,FALSE) -> Portable Power Bank | F13: =VLOOKUP(D13,[2]Product_Dim!$A$2:$G$101,6,FALSE) -> 326.06 | G13: STORE1 | H13: 4 | I13: 286.92 | J13: 0.17 | K13: Credit Card | L13: 952.5744 | M13: =VLOOKUP(C13,'[2]Customer Detail'!$A$2:$H$501,4,FALSE) -> Female | N13: =VLOOKUP(C13,'[2]Customer Detail'!$A$2:$H$501,3,FALSE) -> 34 | O13: =VLOOKUP(C13,'[2]Customer Detail'!$A$2:$H$501,5,FALSE) -> South Darrenland | P13: =VLOOKUP(C13,'[2]Customer Detail'!$A$1:$H$501,8,FALSE) -> Bronze | Q13: =VLOOKUP(G13,[2]Store_Dim!$A$1:$E$21,4,FALSE) -> Danielmouth | R13: =VLOOKUP(G13,[2]Store_Dim!$A$2:$E$21,3,FALSE) -> North
A14: SALE12 | B14: 45528 | C14: CUST1237 | D14: PROD88 | E14: =VLOOKUP(D14,[2]Product_Dim!$A$2:$G$101,2,FALSE) -> Sports Wrist Sweatbands | F14: =VLOOKUP(D14,[2]Product_Dim!$A$2:$G$101,6,FALSE) -> 131.24 | G14: STORE4 | H14: 4 | I14: 644.58 | J14: 0.01 | K14: Credit Card | L14: 2552.5368 | M14: =VLOOKUP(C14,'[2]Customer Detail'!$A$2:$H$501,4,FALSE) -> Female | N14: =VLOOKUP(C14,'[2]Customer Detail'!$A$2:$H$501,3,FALSE) -> 41 | O14: =VLOOKUP(C14,'[2]Customer Detail'!$A$2:$H$501,5,FALSE) -> Susanstad | P14: =VLOOKUP(C14,'[2]Customer Detail'!$A$1:$H$501,8,FALSE) -> Gold | Q14: =VLOOKUP(G14,[2]Store_Dim!$A$1:$E$21,4,FALSE) -> Port Sharon | R14: =VLOOKUP(G14,[2]Store_Dim!$A$2:$E$21,3,FALSE) -> South
A15: SALE13 | B15: 45816 | C15: CUST1443 | D15: PROD34 | E15: =VLOOKUP(D15,[2]Product_Dim!$A$2:$G$101,2,FALSE) -> Gaming Mechanical Keyboard | F15: =VLOOKUP(D15,[2]Product_Dim!$A$2:$G$101,6,FALSE) -> 419.28 | G15: STORE16 | H15: 2 | I15: 316.9 | J15: 0.3 | K15: PayPal | L15: 443.66 | M15: =VLOOKUP(C15,'[2]Customer Detail'!$A$2:$H$501,4,FALSE) -> Male | N15: =VLOOKUP(C15,'[2]Customer Detail'!$A$2:$H$501,3,FALSE) -> 51 | O15: =VLOOKUP(C15,'[2]Customer Detail'!$A$2:$H$501,5,FALSE) -> New Donnabury | P15: =VLOOKUP(C15,'[2]Customer Detail'!$A$1:$H$501,8,FALSE) -> Silver | Q15: =VLOOKUP(G15,[2]Store_Dim!$A$1:$E$21,4,FALSE) -> New Jimmymouth | R15: =VLOOKUP(G15,[2]Store_Dim!$A$2:$E$21,3,FALSE) -> West
A16: SALE14 | B16: 45829 | C16: CUST1348 | D16: PROD24 | E16: =VLOOKUP(D16,[2]Product_Dim!$A$2:$G$101,2,FALSE) -> Foldable Camping Chair | F16: =VLOOKUP(D16,[2]Product_Dim!$A$2:$G$101,6,FALSE) -> 166.06 | G16: STORE15 | H16: 4 | I16: 403.47 | J16: 0.29 | K16: PayPal | L16: 1145.8548 | M16: =VLOOKUP(C16,'[2]Customer Detail'!$A$2:$H$501,4,FALSE) -> Male | N16: =VLOOKUP(C16,'[2]Customer Detail'!$A$2:$H$501,3,FALSE) -> 55 | O16: =VLOOKUP(C16,'[2]Customer Detail'!$A$2:$H$501,5,FALSE) -> Shannonview | P16: =VLOOKUP(C16,'[2]Customer Detail'!$A$1:$H$501,8,FALSE) -> Silver | Q16: =VLOOKUP(G16,[2]Store_Dim!$A$1:$E$21,4,FALSE) -> East Jenniferstad | R16: =VLOOKUP(G16,[2]Store_Dim!$A$2:$E$21,3,FALSE) -> North
A17: SALE15 | B17: 45577 | C17: CUST1435 | D17: PROD36 | E17: =VLOOKUP(D17,[2]Product_Dim!$A$2:$G$101,2,FALSE) -> Women's Summer Dress | F17: =VLOOKUP(D17,[2]Product_Dim!$A$2:$G$101,6,FALSE) -> 223.43 | G17: STORE9 | H17: 2.4802005 | I17: 871.34 | J17: 0.04 | K17: COD | L17: 2074.654 | M17: =VLOOKUP(C17,'[2]Customer Detail'!$A$2:$H$501,4,FALSE) -> Female | N17: =VLOOKUP(C17,'[2]Customer Detail'!$A$2:$H$501,3,FALSE) -> 37 | O17: =VLOOKUP(C17,'[2]Customer Detail'!$A$2:$H$501,5,FALSE) -> Wesleyhaven | P17: =VLOOKUP(C17,'[2]Customer Detail'!$A$1:$H$501,8,FALSE) -> Silver | Q17: =VLOOKUP(G17,[2]Store_Dim!$A$1:$E$21,4,FALSE) -> East Johnstad | R17: =VLOOKUP(G17,[2]Store_Dim!$A$2:$E$21,3,FALSE) -> South
A18: SALE16 | B18: 45913 | C18: CUST1276 | D18: PROD65 | E18: =VLOOKUP(D18,[2]Product_Dim!$A$2:$G$101,2,FALSE) -> Adjustable Dumbbells 20kg | F18: =VLOOKUP(D18,[2]Product_Dim!$A$2:$G$101,6,FALSE) -> 240.63 | G18: STORE19 | H18: 2 | I18: 451.98 | J18: 0.25 | K18: Credit Card | L18: 677.97 | M18: =VLOOKUP(C18,'[2]Customer Detail'!$A$2:$H$501,4,FALSE) -> Male | N18: =VLOOKUP(C18,'[2]Customer Detail'!$A$2:$H$501,3,FALSE) -> 38 | O18: =VLOOKUP(C18,'[2]Customer Detail'!$A$2:$H$501,5,FALSE) -> Ericshire | P18: =VLOOKUP(C18,'[2]Customer Detail'!$A$1:$H$501,8,FALSE) -> Gold | Q18: =VLOOKUP(G18,[2]Store_Dim!$A$1:$E$21,4,FALSE) -> Vasquezborough | R18: =VLOOKUP(G18,[2]Store_Dim!$A$2:$E$21,3,FALSE) -> East
A19: SALE17 | B19: 45608 | C19: CUST1079 | D19: PROD27 | E19: =VLOOKUP(D19,[2]Product_Dim!$A$2:$G$101,2,FALSE) -> Decorative Floor Vase | F19: =VLOOKUP(D19,[2]Product_Dim!$A$2:$G$101,6,FALSE) -> 254.04362 | G19: STORE4 | H19: 2 | I19: 502.69 | J19: 0.23 | K19: Credit Card | L19: 774.1426 | M19: =VLOOKUP(C19,'[2]Customer Detail'!$A$2:$H$501,4,FALSE) -> Female | N19: =VLOOKUP(C19,'[2]Customer Detail'!$A$2:$H$501,3,FALSE) -> 22 | O19: =VLOOKUP(C19,'[2]Customer Detail'!$A$2:$H$501,5,FALSE) -> Nicoleborough | P19: =VLOOKUP(C19,'[2]Customer Detail'!$A$1:$H$501,8,FALSE) -> Platinum | Q19: =VLOOKUP(G19,[2]Store_Dim!$A$1:$E$21,4,FALSE) -> Port Sharon | R19: =VLOOKUP(G19,[2]Store_Dim!$A$2:$E$21,3,FALSE) -> South
A20: SALE18 | B20: 45517 | C20: CUST1094 | D20: PROD39 | E20: =VLOOKUP(D20,[2]Product_Dim!$A$2:$G$101,2,FALSE) -> Portable Power Bank | F20: =VLOOKUP(D20,[2]Product_Dim!$A$2:$G$101,6,FALSE) -> 326.06 | G20: STORE4 | H20: 2 | I20: 559.23 | J20: 0.25 | K20: COD | L20: 838.845 | M20: =VLOOKUP(C20,'[2]Customer Detail'!$A$2:$H$501,4,FALSE) -> Female | N20: =VLOOKUP(C20,'[2]Customer Detail'!$A$2:$H$501,3,FALSE) -> 43 | O20: =VLOOKUP(C20,'[2]Customer Detail'!$A$2:$H$501,5,FALSE) -> New Amyport | P20: =VLOOKUP(C20,'[2]Customer Detail'!$A$1:$H$501,8,FALSE) -> Gold | Q20: =VLOOKUP(G20,[2]Store_Dim!$A$1:$E$21,4,FALSE) -> Port Sharon | R20: =VLOOKUP(G20,[2]Store_Dim!$A$2:$E$21,3,FALSE) -> South
A21: SALE19 | B21: 45369 | C21: CUST1239 | D21: PROD60 | E21: =VLOOKUP(D21,[2]Product_Dim!$A$2:$G$101,2,FALSE) -> Luxury Perfume Spray | F21: =VLOOKUP(D21,[2]Product_Dim!$A$2:$G$101,6,FALSE) -> 482.75 | G21: STORE13 | H21: 4 | I21: 513.98477 | J21: 0.04 | K21: COD | L21: 1973.7015 | M21: =VLOOKUP(C21,'[2]Customer Detail'!$A$2:$H$501,4,FALSE) -> Female | N21: =VLOOKUP(C21,'[2]Customer Detail'!$A$2:$H$501,3,FALSE) -> 58 | O21: =VLOOKUP(C21,'[2]Customer Detail'!$A$2:$H$501,5,FALSE) -> Zamoraborough | P21: =VLOOKUP(C21,'[2]Customer Detail'!$A$1:$H$501,8,FALSE) -> Platinum | Q21: =VLOOKUP(G21,[2]Store_Dim!$A$1:$E$21,4,FALSE) -> Johnsonville | R21: =VLOOKUP(G21,[2]Store_Dim!$A$2:$E$21,3,FALSE) -> East
A22: SALE20 | B22: 45784 | C22: CUST1144 | D22: PROD72 | E22: =VLOOKUP(D22,[2]Product_Dim!$A$2:$G$101,2,FALSE) -> Professional Jump Rope | F22: =VLOOKUP(D22,[2]Product_Dim!$A$2:$G$101,6,FALSE) -> 477.61 | G22: STORE17 | H22: 3 | I22: 986.04 | J22: 0.27 | K22: COD | L22: 2159.4276 | M22: =VLOOKUP(C22,'[2]Customer Detail'!$A$2:$H$501,4,FALSE) -> Female | N22: =VLOOKUP(C22,'[2]Customer Detail'!$A$2:$H$501,3,FALSE) -> 62 | O22: =VLOOKUP(C22,'[2]Customer Detail'!$A$2:$H$501,5,FALSE) -> North Anthonychester | P22: =VLOOKUP(C22,'[2]Customer Detail'!$A$1:$H$501,8,FALSE) -> Bronze | Q22: =VLOOKUP(G22,[2]Store_Dim!$A$1:$E$21,4,FALSE) -> Bensonhaven | R22: =VLOOKUP(G22,[2]Store_Dim!$A$2:$E$21,3,FALSE) -> North
... A147: SALE145 | B147: 45522 | C147: CUST1459 | D147: PROD54 | E147: =VLOOKUP(D147,[2]Product_Dim!$A$2:$G$101,2,FALSE) -> Sports Stopwatch Pro | F147: =VLOOKUP(D147,[2]Product_Dim!$A$2:$G$101,6,FALSE) -> 434.84 | G147: STORE15 | H147: 2 | I147: 536.84 | J147: 0.09 | K147: COD | L147: 977.0488 | M147: =VLOOKUP(C147,'[2]Customer Detail'!$A$2:$H$501,4,FALSE) -> Female | N147: =VLOOKUP(C147,'[2]Customer Detail'!$A$2:$H$501,3,FALSE) -> 29 | O147: =VLOOKUP(C147,'[2]Customer Detail'!$A$2:$H$501,5,FALSE) -> Brandontown | P147: =VLOOKUP(C147,'[2]Customer Detail'!$A$1:$H$501,8,FALSE) -> Gold | Q147: =VLOOKUP(G147,[2]Store_Dim!$A$1:$E$21,4,FALSE) -> East Jenniferstad | R147: =VLOOKUP(G147,[2]Store_Dim!$A$2:$E$21,3,FALSE) -> North
A148: SALE146 | B148: 45626 | C148: CUST1443 | D148: PROD36 | E148: =VLOOKUP(D148,[2]Product_Dim!$A$2:$G$101,2,FALSE) -> Women's Summer Dress | F148: =VLOOKUP(D148,[2]Product_Dim!$A$2:$G$101,6,FALSE) -> 223.43 | G148: STORE19 | H148: 3 | I148: 584.41 | J148: No Discount | K148: COD | L148: 1753.23 | M148: =VLOOKUP(C148,'[2]Customer Detail'!$A$2:$H$501,4,FALSE) -> Male | N148: =VLOOKUP(C148,'[2]Customer Detail'!$A$2:$H$501,3,FALSE) -> 51 | O148: =VLOOKUP(C148,'[2]Customer Detail'!$A$2:$H$501,5,FALSE) -> New Donnabury | P148: =VLOOKUP(C148,'[2]Customer Detail'!$A$1:$H$501,8,FALSE) -> Silver | Q148: =VLOOKUP(G148,[2]Store_Dim!$A$1:$E$21,4,FALSE) -> Vasquezborough | R148: =VLOOKUP(G148,[2]Store_Dim!$A$2:$E$21,3,FALSE) -> East
A149: SALE147 | B149: 45617 | C149: CUST1294 | D149: PROD82 | E149: =VLOOKUP(D149,[2]Product_Dim!$A$2:$G$101,2,FALSE) -> Fitness Resistance Bands | F149: =VLOOKUP(D149,[2]Product_Dim!$A$2:$G$101,6,FALSE) -> 152.92 | G149: STORE19 | H149: 1 | I149: 653.87 | J149: 0.14 | K149: PayPal | L149: 562.3282 | M149: =VLOOKUP(C149,'[2]Customer Detail'!$A$2:$H$501,4,FALSE) -> Male | N149: =VLOOKUP(C149,'[2]Customer Detail'!$A$2:$H$501,3,FALSE) -> 29 | O149: =VLOOKUP(C149,'[2]Customer Detail'!$A$2:$H$501,5,FALSE) -> Port Richard | P149: =VLOOKUP(C149,'[2]Customer Detail'!$A$1:$H$501,8,FALSE) -> Platinum | Q149: =VLOOKUP(G149,[2]Store_Dim!$A$1:$E$21,4,FALSE) -> Vasquezborough | R149: =VLOOKUP(G149,[2]Store_Dim!$A$2:$E$21,3,FALSE) -> East
A150: SALE148 | B150: 45878 | C150: CUST1493 | D150: PROD87 | E150: =VLOOKUP(D150,[2]Product_Dim!$A$2:$G$101,2,FALSE) -> LED Bedside Lamp | F150: =VLOOKUP(D150,[2]Product_Dim!$A$2:$G$101,6,FALSE) -> 371.38 | G150: STORE0 | H150: 1 | I150: 652.03 | J150: 0.27 | K150: Credit Card | L150: 475.9819 | M150: =VLOOKUP(C150,'[2]Customer Detail'!$A$2:$H$501,4,FALSE) -> Male | N150: =VLOOKUP(C150,'[2]Customer Detail'!$A$2:$H$501,3,FALSE) -> 28 | O150: =VLOOKUP(C150,'[2]Customer Detail'!$A$2:$H$501,5,FALSE) -> South William | P150: =VLOOKUP(C150,'[2]Customer Detail'!$A$1:$H$501,8,FALSE) -> Silver | Q150: =VLOOKUP(G150,[2]Store_Dim!$A$1:$E$21,4,FALSE) -> Washingtonfurt | R150: =VLOOKUP(G150,[2]Store_Dim!$A$2:$E$21,3,FALSE) -> East
A151: SALE149 | B151: 45502 | C151: CUST1093 | D151: PROD5 | E151: =VLOOKUP(D151,[2]Product_Dim!$A$2:$G$101,2,FALSE) -> Men's Leather Belt | F151: =VLOOKUP(D151,[2]Product_Dim!$A$2:$G$101,6,FALSE) -> 261 | G151: STORE12 | H151: 3 | I151: 513.36 | J151: 0.07 | K151: COD | L151: 1432.2744 | M151: =VLOOKUP(C151,'[2]Customer Detail'!$A$2:$H$501,4,FALSE) -> Female | N151: =VLOOKUP(C151,'[2]Customer Detail'!$A$2:$H$501,3,FALSE) -> 28 | O151: =VLOOKUP(C151,'[2]Customer Detail'!$A$2:$H$501,5,FALSE) -> Port Travisstad | P151: =VLOOKUP(C151,'[2]Customer Detail'!$A$1:$H$501,8,FALSE) -> Gold | Q151: =VLOOKUP(G151,[2]Store_Dim!$A$1:$E$21,4,FALSE) -> Sabrinatown | R151: =VLOOKUP(G151,[2]Store_Dim!$A$2:$E$21,3,FALSE) -> North
A152: SALE150 | B152: 45433 | C152: CUST1068 | D152: PROD52 | E152: =VLOOKUP(D152,[2]Product_Dim!$A$2:$G$101,2,FALSE) -> Rugby Ball | F152: =VLOOKUP(D152,[2]Product_Dim!$A$2:$G$101,6,FALSE) -> 212.26 | G152: STORE5 | H152: 4 | I152: 355.64 | J152: 0.16 | K152: COD | L152: 1194.9504 | M152: =VLOOKUP(C152,'[2]Customer Detail'!$A$2:$H$501,4,FALSE) -> Female | N152: =VLOOKUP(C152,'[2]Customer Detail'!$A$2:$H$501,3,FALSE) -> 24 | O152: =VLOOKUP(C152,'[2]Customer Detail'!$A$2:$H$501,5,FALSE) -> West Johnchester | P152: =VLOOKUP(C152,'[2]Customer Detail'!$A$1:$H$501,8,FALSE) -> Silver | Q152: =VLOOKUP(G152,[2]Store_Dim!$A$1:$E$21,4,FALSE) -> New Michaelchester | R152: =VLOOKUP(G152,[2]Store_Dim!$A$2:$E$21,3,FALSE) -> North
A153: SALE151 | B153: 45594 | C153: CUST1022 | D153: PROD13 | E153: =VLOOKUP(D153,[2]Product_Dim!$A$2:$G$101,2,FALSE) -> USB-C Fast Charger | F153: =VLOOKUP(D153,[2]Product_Dim!$A$2:$G$101,6,FALSE) -> 242.23 | G153: STORE8 | H153: 4 | I153: 535.4 | J153: 0.26 | K153: PayPal | L153: 1584.784 | M153: =VLOOKUP(C153,'[2]Customer Detail'!$A$2:$H$501,4,FALSE) -> Female | N153: =VLOOKUP(C153,'[2]Customer Detail'!$A$2:$H$501,3,FALSE) -> 33 | O153: =VLOOKUP(C153,'[2]Customer Detail'!$A$2:$H$501,5,FALSE) -> Michaelton | P153: =VLOOKUP(C153,'[2]Customer Detail'!$A$1:$H$501,8,FALSE) -> Silver | Q153: =VLOOKUP(G153,[2]Store_Dim!$A$1:$E$21,4,FALSE) -> Thompsonborough | R153: =VLOOKUP(G153,[2]Store_Dim!$A$2:$E$21,3,FALSE) -> West
A154: SALE152 | B154: 45798 | C154: CUST1243 | D154: PROD69 | E154: =VLOOKUP(D154,[2]Product_Dim!$A$2:$G$101,2,FALSE) -> Men's Sports Shorts | F154: =VLOOKUP(D154,[2]Product_Dim!$A$2:$G$101,6,FALSE) -> 218.22 | G154: STORE19 | H154: 2 | I154: 108.74 | J154: 0.11 | K154: PayPal | L154: 193.5572 | M154: =VLOOKUP(C154,'[2]Customer Detail'!$A$2:$H$501,4,FALSE) -> Female | N154: =VLOOKUP(C154,'[2]Customer Detail'!$A$2:$H$501,3,FALSE) -> 56 | O154: =VLOOKUP(C154,'[2]Customer Detail'!$A$2:$H$501,5,FALSE) -> North Nicholas | P154: =VLOOKUP(C154,'[2]Customer Detail'!$A$1:$H$501,8,FALSE) -> Gold | Q154: =VLOOKUP(G154,[2]Store_Dim!$A$1:$E$21,4,FALSE) -> Vasquezborough | R154: =VLOOKUP(G154,[2]Store_Dim!$A$2:$E$21,3,FALSE) -> East
A155: SALE153 | B155: 45579 | C155: CUST1314 | D155: PROD11 | E155: =VLOOKUP(D155,[2]Product_Dim!$A$2:$G$101,2,FALSE) -> HD Smart TV Stick | F155: =VLOOKUP(D155,[2]Product_Dim!$A$2:$G$101,6,FALSE) -> 449.4 | G155: STORE19 | H155: 3 | I155: 591.98 | J155: 0.16 | K155: Credit Card | L155: 1491.7896 | M155: =VLOOKUP(C155,'[2]Customer Detail'!$A$2:$H$501,4,FALSE) -> Female | N155: =VLOOKUP(C155,'[2]Customer Detail'!$A$2:$H$501,3,FALSE) -> 53 | O155: =VLOOKUP(C155,'[2]Customer Detail'!$A$2:$H$501,5,FALSE) -> Anitaland | P155: =VLOOKUP(C155,'[2]Customer Detail'!$A$1:$H$501,8,FALSE) -> Silver | Q155: =VLOOKUP(G155,[2]Store_Dim!$A$1:$E$21,4,FALSE) -> Vasquezborough | R155: =VLOOKUP(G155,[2]Store_Dim!$A$2:$E$21,3,FALSE) -> East
A156: SALE154 | B156: 45613 | C156: CUST1405 | D156: PROD48 | E156: =VLOOKUP(D156,[2]Product_Dim!$A$2:$G$101,2,FALSE) -> Car Dashboard Phone Holder | F156: =VLOOKUP(D156,[2]Product_Dim!$A$2:$G$101,6,FALSE) -> 177.98 | G156: STORE2 | H156: 1 | I156: 345.06 | J156: 0.13 | K156: COD | L156: 300.2022 | M156: =VLOOKUP(C156,'[2]Customer Detail'!$A$2:$H$501,4,FALSE) -> Female | N156: =VLOOKUP(C156,'[2]Customer Detail'!$A$2:$H$501,3,FALSE) -> 18 | O156: =VLOOKUP(C156,'[2]Customer Detail'!$A$2:$H$501,5,FALSE) -> Garciaview | P156: =VLOOKUP(C156,'[2]Customer Detail'!$A$1:$H$501,8,FALSE) -> Gold | Q156: =VLOOKUP(G156,[2]Store_Dim!$A$1:$E$21,4,FALSE) -> North Nancyview | R156: =VLOOKUP(G156,[2]Store_Dim!$A$2:$E$21,3,FALSE) -> South
A157: SALE155 | B157: 45745 | C157: CUST1307 | D157: PROD93 | E157: =VLOOKUP(D157,[2]Product_Dim!$A$2:$G$101,2,FALSE) -> USB-C Laptop Charger | F157: =VLOOKUP(D157,[2]Product_Dim!$A$2:$G$101,6,FALSE) -> 377.52 | G157: STORE12 | H157: 4 | I157: 986.41 | J157: 0.22 | K157: Credit Card | L157: 3077.5992 | M157: =VLOOKUP(C157,'[2]Customer Detail'!$A$2:$H$501,4,FALSE) -> Female | N157: =VLOOKUP(C157,'[2]Customer Detail'!$A$2:$H$501,3,FALSE) -> 56 | O157: =VLOOKUP(C157,'[2]Customer Detail'!$A$2:$H$501,5,FALSE) -> West Patriciaview | P157: =VLOOKUP(C157,'[2]Customer Detail'!$A$1:$H$501,8,FALSE) -> Bronze | Q157: =VLOOKUP(G157,[2]Store_Dim!$A$1:$E$21,4,FALSE) -> Sabrinatown | R157: =VLOOKUP(G157,[2]Store_Dim!$A$2:$E$21,3,FALSE) -> North
A158: SALE156 | B158: 45494 | C158: CUST1319 | D158: PROD49 | E158: =VLOOKUP(D158,[2]Product_Dim!$A$2:$G$101,2,FALSE) -> Men's Roll-On Perfume | F158: =VLOOKUP(D158,[2]Product_Dim!$A$2:$G$101,6,FALSE) -> 43.29 | G158: STORE0 | H158: 2 | I158: 921.52 | J158: No Discount | K158: PayPal | L158: 1843.04 | M158: =VLOOKUP(C158,'[2]Customer Detail'!$A$2:$H$501,4,FALSE) -> Male | N158: =VLOOKUP(C158,'[2]Customer Detail'!$A$2:$H$501,3,FALSE) -> 54 | O158: =VLOOKUP(C158,'[2]Customer Detail'!$A$2:$H$501,5,FALSE) -> West Mathewside | P158: =VLOOKUP(C158,'[2]Customer Detail'!$A$1:$H$501,8,FALSE) -> Platinum | Q158: =VLOOKUP(G158,[2]Store_Dim!$A$1:$E$21,4,FALSE) -> Washingtonfurt | R158: =VLOOKUP(G158,[2]Store_Dim!$A$2:$E$21,3,FALSE) -> East
A159: SALE157 | B159: 45883 | C159: CUST1097 | D159: PROD55 | E159: =VLOOKUP(D159,[2]Product_Dim!$A$2:$G$101,2,FALSE) -> Ceramic Plant Pot | F159: =VLOOKUP(D159,[2]Product_Dim!$A$2:$G$101,6,FALSE) -> 81.75 | G159: STORE5 | H159: 1 | I159: 83.1 | J159: 0.04 | K159: PayPal | L159: 79.776 | M159: =VLOOKUP(C159,'[2]Customer Detail'!$A$2:$H$501,4,FALSE) -> Male | N159: =VLOOKUP(C159,'[2]Customer Detail'!$A$2:$H$501,3,FALSE) -> 36 | O159: =VLOOKUP(C159,'[2]Customer Detail'!$A$2:$H$501,5,FALSE) -> Lake Thomas | P159: =VLOOKUP(C159,'[2]Customer Detail'!$A$1:$H$501,8,FALSE) -> Silver | Q159: =VLOOKUP(G159,[2]Store_Dim!$A$1:$E$21,4,FALSE) -> New Michaelchester | R159: =VLOOKUP(G159,[2]Store_Dim!$A$2:$E$21,3,FALSE) -> North
A160: SALE158 | B160: 45601 | C160: CUST1369 | D160: PROD28 | E160: =VLOOKUP(D160,[2]Product_Dim!$A$2:$G$101,2,FALSE) -> Sports Stopwatch Timer | F160: =VLOOKUP(D160,[2]Product_Dim!$A$2:$G$101,6,FALSE) -> 38.76 | G160: STORE11 | H160: 2 | I160: 60.98 | J160: 0.23 | K160: PayPal | L160: 93.9092 | M160: =VLOOKUP(C160,'[2]Customer Detail'!$A$2:$H$501,4,FALSE) -> Female | N160: =VLOOKUP(C160,'[2]Customer Detail'!$A$2:$H$501,3,FALSE) -> 20 | O160: =VLOOKUP(C160,'[2]Customer Detail'!$A$2:$H$501,5,FALSE) -> West Bruce | P160: =VLOOKUP(C160,'[2]Customer Detail'!$A$1:$H$501,8,FALSE) -> Platinum | Q160: =VLOOKUP(G160,[2]Store_Dim!$A$1:$E$21,4,FALSE) -> Lake Michael | R160: =VLOOKUP(G160,[2]Store_Dim!$A$2:$E$21,3,FALSE) -> South
A161: SALE159 | B161: 45454 | C161: CUST1394 | D161: PROD89 | E161: =VLOOKUP(D161,[2]Product_Dim!$A$2:$G$101,2,FALSE) -> Face Foundation Kit | F161: =VLOOKUP(D161,[2]Product_Dim!$A$2:$G$101,6,FALSE) -> 183.04 | G161: STORE16 | H161: 2 | I161: 122.23 | J161: 0.21 | K161: COD | L161: 193.1234 | M161: =VLOOKUP(C161,'[2]Customer Detail'!$A$2:$H$501,4,FALSE) -> Female | N161: =VLOOKUP(C161,'[2]Customer Detail'!$A$2:$H$501,3,FALSE) -> 43 | O161: =VLOOKUP(C161,'[2]Customer Detail'!$A$2:$H$501,5,FALSE) -> Cannonberg | P161: =VLOOKUP(C161,'[2]Customer Detail'!$A$1:$H$501,8,FALSE) -> Bronze | Q161: =VLOOKUP(G161,[2]Store_Dim!$A$1:$E$21,4,FALSE) -> New Jimmymouth | R161: =VLOOKUP(G161,[2]Store_Dim!$A$2:$E$21,3,FALSE) -> West
A162: SALE160 | B162: 45918 | C162: CUST1020 | D162: PROD70 | E162: =VLOOKUP(D162,[2]Product_Dim!$A$2:$G$101,2,FALSE) -> Kitchen Storage Rack | F162: =VLOOKUP(D162,[2]Product_Dim!$A$2:$G$101,6,FALSE) -> 138.05 | G162: STORE18 | H162: 2 | I162: 623.38 | J162: 0.13 | K162: Credit Card | L162: 1084.6812 | M162: =VLOOKUP(C162,'[2]Customer Detail'!$A$2:$H$501,4,FALSE) -> Male | N162: =VLOOKUP(C162,'[2]Customer Detail'!$A$2:$H$501,3,FALSE) -> 59 | O162: =VLOOKUP(C162,'[2]Customer Detail'!$A$2:$H$501,5,FALSE) -> Lake Shaneburgh | P162: =VLOOKUP(C162,'[2]Customer Detail'!$A$1:$H$501,8,FALSE) -> Silver | Q162: =VLOOKUP(G162,[2]Store_Dim!$A$1:$E$21,4,FALSE) -> East Stevechester | R162: =VLOOKUP(G162,[2]Store_Dim!$A$2:$E$21,3,FALSE) -> East
A163: SALE161 | B163: 45729 | C163: CUST1058 | D163: PROD70 | E163: =VLOOKUP(D163,[2]Product_Dim!$A$2:$G$101,2,FALSE) -> Kitchen Storage Rack | F163: =VLOOKUP(D163,[2]Product_Dim!$A$2:$G$101,6,FALSE) -> 138.05 | G163: STORE0 | H163: 1 | I163: 479.58 | J163: 0.05 | K163: PayPal | L163: 455.601 | M163: =VLOOKUP(C163,'[2]Customer Detail'!$A$2:$H$501,4,FALSE) -> Male | N163: =VLOOKUP(C163,'[2]Customer Detail'!$A$2:$H$501,3,FALSE) -> 51 | O163: =VLOOKUP(C163,'[2]Customer Detail'!$A$2:$H$501,5,FALSE) -> Snowmouth | P163: =VLOOKUP(C163,'[2]Customer Detail'!$A$1:$H$501,8,FALSE) -> Platinum | Q163: =VLOOKUP(G163,[2]Store_Dim!$A$1:$E$21,4,FALSE) -> Washingtonfurt | R163: =VLOOKUP(G163,[2]Store_Dim!$A$2:$E$21,3,FALSE) -> East
A164: SALE162 | B164: 45276 | C164: CUST1298 | D164: PROD73 | E164: =VLOOKUP(D164,[2]Product_Dim!$A$2:$G$101,2,FALSE) -> Shin Guards – Adult | F164: =VLOOKUP(D164,[2]Product_Dim!$A$2:$G$101,6,FALSE) -> 107.06 | G164: STORE6 | H164: 3 | I164: 369.32 | J164: 0.14 | K164: PayPal | L164: 952.8456 | M164: =VLOOKUP(C164,'[2]Customer Detail'!$A$2:$H$501,4,FALSE) -> Male | N164: =VLOOKUP(C164,'[2]Customer Detail'!$A$2:$H$501,3,FALSE) -> 64 | O164: =VLOOKUP(C164,'[2]Customer Detail'!$A$2:$H$501,5,FALSE) -> New Joshuatown | P164: =VLOOKUP(C164,'[2]Customer Detail'!$A$1:$H$501,8,FALSE) -> Platinum | Q164: =VLOOKUP(G164,[2]Store_Dim!$A$1:$E$21,4,FALSE) -> Port Josephberg | R164: =VLOOKUP(G164,[2]Store_Dim!$A$2:$E$21,3,FALSE) -> East
A165: SALE163 | B165: 45851 | C165: CUST1076 | D165: PROD32 | E165: =VLOOKUP(D165,[2]Product_Dim!$A$2:$G$101,2,FALSE) -> Vitamin C Face Serum | F165: =VLOOKUP(D165,[2]Product_Dim!$A$2:$G$101,6,FALSE) -> 283.83 | G165: STORE1 | H165: 1 | I165: 488.31 | J165: 0.03 | K165: PayPal | L165: 473.6607 | M165: =VLOOKUP(C165,'[2]Customer Detail'!$A$2:$H$501,4,FALSE) -> Male | N165: =VLOOKUP(C165,'[2]Customer Detail'!$A$2:$H$501,3,FALSE) -> 37 | O165: =VLOOKUP(C165,'[2]Customer Detail'!$A$2:$H$501,5,FALSE) -> Rodrigueztown | P165: =VLOOKUP(C165,'[2]Customer Detail'!$A$1:$H$501,8,FALSE) -> Gold | Q165: =VLOOKUP(G165,[2]Store_Dim!$A$1:$E$21,4,FALSE) -> Danielmouth | R165: =VLOOKUP(G165,[2]Store_Dim!$A$2:$E$21,3,FALSE) -> North
A166: SALE164 | B166: 45418 | C166: CUST1276 | D166: PROD54 | E166: =VLOOKUP(D166,[2]Product_Dim!$A$2:$G$101,2,FALSE) -> Sports Stopwatch Pro | F166: =VLOOKUP(D166,[2]Product_Dim!$A$2:$G$101,6,FALSE) -> 434.84 | G166: STORE12 | H166: 4 | I166: 164.04 | J166: 0.26 | K166: Credit Card | L166: 485.5584 | M166: =VLOOKUP(C166,'[2]Customer Detail'!$A$2:$H$501,4,FALSE) -> Male | N166: =VLOOKUP(C166,'[2]Customer Detail'!$A$2:$H$501,3,FALSE) -> 38 | O166: =VLOOKUP(C166,'[2]Customer Detail'!$A$2:$H$501,5,FALSE) -> Ericshire | P166: =VLOOKUP(C166,'[2]Customer Detail'!$A$1:$H$501,8,FALSE) -> Gold | Q166: =VLOOKUP(G166,[2]Store_Dim!$A$1:$E$21,4,FALSE) -> Sabrinatown | R166: =VLOOKUP(G166,[2]Store_Dim!$A$2:$E$21,3,FALSE) -> North
A167: SALE165 | B167: 45508 | C167: CUST1073 | D167: PROD10 | E167: =VLOOKUP(D167,[2]Product_Dim!$A$2:$G$101,2,FALSE) -> Ceramic Kitchen Bowl Set | F167: =VLOOKUP(D167,[2]Product_Dim!$A$2:$G$101,6,FALSE) -> 298.86 | G167: STORE17 | H167: 3 | I167: 707.95 | J167: 0.18 | K167: PayPal | L167: 1741.557 | M167: =VLOOKUP(C167,'[2]Customer Detail'!$A$2:$H$501,4,FALSE) -> Female | N167: =VLOOKUP(C167,'[2]Customer Detail'!$A$2:$H$501,3,FALSE) -> 56 | O167: =VLOOKUP(C167,'[2]Customer Detail'!$A$2:$H$501,5,FALSE) -> Sandrastad | P167: =VLOOKUP(C167,'[2]Customer Detail'!$A$1:$H$501,8,FALSE) -> Silver | Q167: =VLOOKUP(G167,[2]Store_Dim!$A$1:$E$21,4,FALSE) -> Bensonhaven | R167: =VLOOKUP(G167,[2]Store_Dim!$A$2:$E$21,3,FALSE) -> North
A168: SALE166 | B168: 45269 | C168: CUST1295 | D168: PROD69 | E168: =VLOOKUP(D168,[2]Product_Dim!$A$2:$G$101,2,FALSE) -> Men's Sports Shorts | F168: =VLOOKUP(D168,[2]Product_Dim!$A$2:$G$101,6,FALSE) -> 218.22 | G168: STORE8 | H168: 4 | I168: 714.47 | J168: 0.18 | K168: COD | L168: 2343.4616 | M168: =VLOOKUP(C168,'[2]Customer Detail'!$A$2:$H$501,4,FALSE) -> Female | N168: =VLOOKUP(C168,'[2]Customer Detail'!$A$2:$H$501,3,FALSE) -> 19 | O168: =VLOOKUP(C168,'[2]Customer Detail'!$A$2:$H$501,5,FALSE) -> North Michelleport | P168: =VLOOKUP(C168,'[2]Customer Detail'!$A$1:$H$501,8,FALSE) -> Bronze | Q168: =VLOOKUP(G168,[2]Store_Dim!$A$1:$E$21,4,FALSE) -> Thompsonborough | R168: =VLOOKUP(G168,[2]Store_Dim!$A$2:$E$21,3,FALSE) -> West
A169: SALE167 | B169: 45866 | C169: CUST1415 | D169: PROD79 | E169: =VLOOKUP(D169,[2]Product_Dim!$A$2:$G$101,2,FALSE) -> Decorative Lamp Shade | F169: =VLOOKUP(D169,[2]Product_Dim!$A$2:$G$101,6,FALSE) -> 228.53 | G169: STORE7 | H169: 4 | I169: 422.09 | J169: 0.04 | K169: Credit Card | L169: 1620.8256 | M169: =VLOOKUP(C169,'[2]Customer Detail'!$A$2:$H$501,4,FALSE) -> Female | N169: =VLOOKUP(C169,'[2]Customer Detail'!$A$2:$H$501,3,FALSE) -> 26 | O169: =VLOOKUP(C169,'[2]Customer Detail'!$A$2:$H$501,5,FALSE) -> Kramerview | P169: =VLOOKUP(C169,'[2]Customer Detail'!$A$1:$H$501,8,FALSE) -> Silver | Q169: =VLOOKUP(G169,[2]Store_Dim!$A$1:$E$21,4,FALSE) -> Williamsfurt | R169: =VLOOKUP(G169,[2]Store_Dim!$A$2:$E$21,3,FALSE) -> South
A170: SALE168 | B170: 45462 | C170: CUST1108 | D170: PROD30 | E170: =VLOOKUP(D170,[2]Product_Dim!$A$2:$G$101,2,FALSE) -> Stainless Steel Cutlery Set | F170: =VLOOKUP(D170,[2]Product_Dim!$A$2:$G$101,6,FALSE) -> 19.52 | G170: STORE9 | H170: 1 | I170: 998.19 | J170: 0.2 | K170: Credit Card | L170: 798.552 | M170: =VLOOKUP(C170,'[2]Customer Detail'!$A$2:$H$501,4,FALSE) -> Male | N170: =VLOOKUP(C170,'[2]Customer Detail'!$A$2:$H$501,3,FALSE) -> 38 | O170: =VLOOKUP(C170,'[2]Customer Detail'!$A$2:$H$501,5,FALSE) -> Webstermouth | P170: =VLOOKUP(C170,'[2]Customer Detail'!$A$1:$H$501,8,FALSE) -> Bronze | Q170: =VLOOKUP(G170,[2]Store_Dim!$A$1:$E$21,4,FALSE) -> East Johnstad | R170: =VLOOKUP(G170,[2]Store_Dim!$A$2:$E$21,3,FALSE) -> South
... A179: SALE177 | B179: 45670 | C179: CUST1499 | D179: PROD55 | E179: =VLOOKUP(D179,[2]Product_Dim!$A$2:$G$101,2,FALSE) -> Ceramic Plant Pot | F179: =VLOOKUP(D179,[2]Product_Dim!$A$2:$G$101,6,FALSE) -> 81.75 | G179: STORE8 | H179: 1 | I179: 79 | J179: 0.04 | K179: PayPal | L179: 75.84 | M179: =VLOOKUP(C179,'[2]Customer Detail'!$A$2:$H$501,4,FALSE) -> Female | N179: =VLOOKUP(C179,'[2]Customer Detail'!$A$2:$H$501,3,FALSE) -> 27 | O179: =VLOOKUP(C179,'[2]Customer Detail'!$A$2:$H$501,5,FALSE) -> East Valerieview | P179: =VLOOKUP(C179,'[2]Customer Detail'!$A$1:$H$501,8,FALSE) -> Platinum | Q179: =VLOOKUP(G179,[2]Store_Dim!$A$1:$E$21,4,FALSE) -> Thompsonborough | R179: =VLOOKUP(G179,[2]Store_Dim!$A$2:$E$21,3,FALSE) -> West
A180: SALE178 | B180: 45885 | C180: CUST1066 | D180: PROD94 | E180: =VLOOKUP(D180,[2]Product_Dim!$A$2:$G$101,2,FALSE) -> Vitamin E Body Lotion | F180: =VLOOKUP(D180,[2]Product_Dim!$A$2:$G$101,6,FALSE) -> 358.47 | G180: STORE5 | H180: 4 | I180: 638.91 | J180: No Discount | K180: COD | L180: 2555.64 | M180: =VLOOKUP(C180,'[2]Customer Detail'!$A$2:$H$501,4,FALSE) -> Female | N180: =VLOOKUP(C180,'[2]Customer Detail'!$A$2:$H$501,3,FALSE) -> 27 | O180: =VLOOKUP(C180,'[2]Customer Detail'!$A$2:$H$501,5,FALSE) -> South Aaronside | P180: =VLOOKUP(C180,'[2]Customer Detail'!$A$1:$H$501,8,FALSE) -> Silver | Q180: =VLOOKUP(G180,[2]Store_Dim!$A$1:$E$21,4,FALSE) -> New Michaelchester | R180: =VLOOKUP(G180,[2]Store_Dim!$A$2:$E$21,3,FALSE) -> North
A181: SALE179 | B181: 45812 | C181: CUST1081 | D181: PROD45 | E181: =VLOOKUP(D181,[2]Product_Dim!$A$2:$G$101,2,FALSE) -> High-Grip Football | F181: =VLOOKUP(D181,[2]Product_Dim!$A$2:$G$101,6,FALSE) -> 318.91 | G181: STORE0 | H181: 2 | I181: 522.17 | J181: 0.27 | K181: Credit Card | L181: 762.3682 | M181: =VLOOKUP(C181,'[2]Customer Detail'!$A$2:$H$501,4,FALSE) -> Female | N181: =VLOOKUP(C181,'[2]Customer Detail'!$A$2:$H$501,3,FALSE) -> 34 | O181: =VLOOKUP(C181,'[2]Customer Detail'!$A$2:$H$501,5,FALSE) -> South David | P181: =VLOOKUP(C181,'[2]Customer Detail'!$A$1:$H$501,8,FALSE) -> Platinum | Q181: =VLOOKUP(G181,[2]Store_Dim!$A$1:$E$21,4,FALSE) -> Washingtonfurt | R181: =VLOOKUP(G181,[2]Store_Dim!$A$2:$E$21,3,FALSE) -> East
A182: SALE180 | B182: 45235 | C182: CUST1478 | D182: PROD39 | E182: =VLOOKUP(D182,[2]Product_Dim!$A$2:$G$101,2,FALSE) -> Portable Power Bank | F182: =VLOOKUP(D182,[2]Product_Dim!$A$2:$G$101,6,FALSE) -> 326.06 | G182: STORE12 | H182: 3 | I182: 954.29 | J182: 0.27 | K182: Credit Card | L182: 2089.8951 | M182: =VLOOKUP(C182,'[2]Customer Detail'!$A$2:$H$501,4,FALSE) -> Male | N182: =VLOOKUP(C182,'[2]Customer Detail'!$A$2:$H$501,3,FALSE) -> 59 | O182: =VLOOKUP(C182,'[2]Customer Detail'!$A$2:$H$501,5,FALSE) -> West Sarah | P182: =VLOOKUP(C182,'[2]Customer Detail'!$A$1:$H$501,8,FALSE) -> Gold | Q182: =VLOOKUP(G182,[2]Store_Dim!$A$1:$E$21,4,FALSE) -> Sabrinatown | R182: =VLOOKUP(G182,[2]Store_Dim!$A$2:$E$21,3,FALSE) -> North
A183: SALE181 | B183: 45710 | C183: CUST1462 | D183: PROD33 | E183: =VLOOKUP(D183,[2]Product_Dim!$A$2:$G$101,2,FALSE) -> Modern Wall Clock | F183: =VLOOKUP(D183,[2]Product_Dim!$A$2:$G$101,6,FALSE) -> 179.77 | G183: STORE13 | H183: 3 | I183: 53.92 | J183: 0.15 | K183: PayPal | L183: 137.496 | M183: =VLOOKUP(C183,'[2]Customer Detail'!$A$2:$H$501,4,FALSE) -> Female | N183: =VLOOKUP(C183,'[2]Customer Detail'!$A$2:$H$501,3,FALSE) -> 34 | O183: =VLOOKUP(C183,'[2]Customer Detail'!$A$2:$H$501,5,FALSE) -> Burkefurt | P183: =VLOOKUP(C183,'[2]Customer Detail'!$A$1:$H$501,8,FALSE) -> Silver | Q183: =VLOOKUP(G183,[2]Store_Dim!$A$1:$E$21,4,FALSE) -> Johnsonville | R183: =VLOOKUP(G183,[2]Store_Dim!$A$2:$E$21,3,FALSE) -> East
A184: SALE182 | B184: 45753 | C184: CUST1396 | D184: PROD34 | E184: =VLOOKUP(D184,[2]Product_Dim!$A$2:$G$101,2,FALSE) -> Gaming Mechanical Keyboard | F184: =VLOOKUP(D184,[2]Product_Dim!$A$2:$G$101,6,FALSE) -> 419.28 | G184: STORE0 | H184: 4 | I184: 741.88 | J184: 0.02 | K184: COD | L184: 2908.1696 | M184: =VLOOKUP(C184,'[2]Customer Detail'!$A$2:$H$501,4,FALSE) -> Female | N184: =VLOOKUP(C184,'[2]Customer Detail'!$A$2:$H$501,3,FALSE) -> 25 | O184: =VLOOKUP(C184,'[2]Customer Detail'!$A$2:$H$501,5,FALSE) -> Parkerview | P184: =VLOOKUP(C184,'[2]Customer Detail'!$A$1:$H$501,8,FALSE) -> Silver | Q184: =VLOOKUP(G184,[2]Store_Dim!$A$1:$E$21,4,FALSE) -> Washingtonfurt | R184: =VLOOKUP(G184,[2]Store_Dim!$A$2:$E$21,3,FALSE) -> East
A185: SALE183 | B185: 45594 | C185: CUST1033 | D185: PROD46 | E185: =VLOOKUP(D185,[2]Product_Dim!$A$2:$G$101,2,FALSE) -> Men's Winter Jacket | F185: =VLOOKUP(D185,[2]Product_Dim!$A$2:$G$101,6,FALSE) -> 167.34 | G185: STORE3 | H185: 1 | I185: 547.09 | J185: 0.01 | K185: PayPal | L185: 541.6191 | M185: =VLOOKUP(C185,'[2]Customer Detail'!$A$2:$H$501,4,FALSE) -> Male | N185: =VLOOKUP(C185,'[2]Customer Detail'!$A$2:$H$501,3,FALSE) -> 25 | O185: =VLOOKUP(C185,'[2]Customer Detail'!$A$2:$H$501,5,FALSE) -> Tristanton | P185: =VLOOKUP(C185,'[2]Customer Detail'!$A$1:$H$501,8,FALSE) -> Platinum | Q185: =VLOOKUP(G185,[2]Store_Dim!$A$1:$E$21,4,FALSE) -> Hoodberg | R185: =VLOOKUP(G185,[2]Store_Dim!$A$2:$E$21,3,FALSE) -> North
A186: SALE184 | B186: 45686 | C186: CUST1489 | D186: PROD89 | E186: =VLOOKUP(D186,[2]Product_Dim!$A$2:$G$101,2,FALSE) -> Face Foundation Kit | F186: =VLOOKUP(D186,[2]Product_Dim!$A$2:$G$101,6,FALSE) -> 183.04 | G186: STORE3 | H186: 1 | I186: 789.35 | J186: 0.14 | K186: PayPal | L186: 678.841 | M186: =VLOOKUP(C186,'[2]Customer Detail'!$A$2:$H$501,4,FALSE) -> Female | N186: =VLOOKUP(C186,'[2]Customer Detail'!$A$2:$H$501,3,FALSE) -> 42 | O186: =VLOOKUP(C186,'[2]Customer Detail'!$A$2:$H$501,5,FALSE) -> Lake Elizabethside | P186: =VLOOKUP(C186,'[2]Customer Detail'!$A$1:$H$501,8,FALSE) -> Silver | Q186: =VLOOKUP(G186,[2]Store_Dim!$A$1:$E$21,4,FALSE) -> Hoodberg | R186: =VLOOKUP(G186,[2]Store_Dim!$A$2:$E$21,3,FALSE) -> North
A187: SALE185 | B187: 45354 | C187: CUST1428 | D187: PROD63 | E187: =VLOOKUP(D187,[2]Product_Dim!$A$2:$G$101,2,FALSE) -> Organic Sunscreen Lotion | F187: =VLOOKUP(D187,[2]Product_Dim!$A$2:$G$101,6,FALSE) -> 266.86 | G187: STORE3 | H187: 3 | I187: 476.78 | J187: 0.09 | K187: COD | L187: 1301.6094 | M187: =VLOOKUP(C187,'[2]Customer Detail'!$A$2:$H$501,4,FALSE) -> Female | N187: =VLOOKUP(C187,'[2]Customer Detail'!$A$2:$H$501,3,FALSE) -> 27 | O187: =VLOOKUP(C187,'[2]Customer Detail'!$A$2:$H$501,5,FALSE) -> Hartmouth | P187: =VLOOKUP(C187,'[2]Customer Detail'!$A$1:$H$501,8,FALSE) -> Bronze | Q187: =VLOOKUP(G187,[2]Store_Dim!$A$1:$E$21,4,FALSE) -> Hoodberg | R187: =VLOOKUP(G187,[2]Store_Dim!$A$2:$E$21,3,FALSE) -> North
A188: SALE186 | B188: 45600 | C188: CUST1453 | D188: PROD79 | E188: =VLOOKUP(D188,[2]Product_Dim!$A$2:$G$101,2,FALSE) -> Decorative Lamp Shade | F188: =VLOOKUP(D188,[2]Product_Dim!$A$2:$G$101,6,FALSE) -> 228.53 | G188: STORE18 | H188: 2 | I188: 504.26 | J188: 0.04 | K188: PayPal | L188: 968.1792 | M188: =VLOOKUP(C188,'[2]Customer Detail'!$A$2:$H$501,4,FALSE) -> Female | N188: =VLOOKUP(C188,'[2]Customer Detail'!$A$2:$H$501,3,FALSE) -> 62 | O188: =VLOOKUP(C188,'[2]Customer Detail'!$A$2:$H$501,5,FALSE) -> Lake Carolyn | P188: =VLOOKUP(C188,'[2]Customer Detail'!$A$1:$H$501,8,FALSE) -> Platinum | Q188: =VLOOKUP(G188,[2]Store_Dim!$A$1:$E$21,4,FALSE) -> East Stevechester | R188: =VLOOKUP(G188,[2]Store_Dim!$A$2:$E$21,3,FALSE) -> East
A189: SALE187 | B189: 45538 | C189: CUST1272 | D189: PROD81 | E189: =VLOOKUP(D189,[2]Product_Dim!$A$2:$G$101,2,FALSE) -> Badminton Racket Set | F189: =VLOOKUP(D189,[2]Product_Dim!$A$2:$G$101,6,FALSE) -> 285.54 | G189: STORE6 | H189: 2 | I189: 549.33 | J189: 0.01 | K189: COD | L189: 1087.6734 | M189: =VLOOKUP(C189,'[2]Customer Detail'!$A$2:$H$501,4,FALSE) -> Female | N189: =VLOOKUP(C189,'[2]Customer Detail'!$A$2:$H$501,3,FALSE) -> 48 | O189: =VLOOKUP(C189,'[2]Customer Detail'!$A$2:$H$501,5,FALSE) -> Welchview | P189: =VLOOKUP(C189,'[2]Customer Detail'!$A$1:$H$501,8,FALSE) -> Gold | Q189: =VLOOKUP(G189,[2]Store_Dim!$A$1:$E$21,4,FALSE) -> Port Josephberg | R189: =VLOOKUP(G189,[2]Store_Dim!$A$2:$E$21,3,FALSE) -> East
A190: SALE188 | B190: 45411 | C190: CUST1382 | D190: PROD4 | E190: =VLOOKUP(D190,[2]Product_Dim!$A$2:$G$101,2,FALSE) -> Women's Yoga Pants | F190: =VLOOKUP(D190,[2]Product_Dim!$A$2:$G$101,6,FALSE) -> 306.46 | G190: STORE3 | H190: 3 | I190: 620.22 | J190: 0.04 | K190: Credit Card | L190: 1786.2336 | M190: =VLOOKUP(C190,'[2]Customer Detail'!$A$2:$H$501,4,FALSE) -> Female | N190: =VLOOKUP(C190,'[2]Customer Detail'!$A$2:$H$501,3,FALSE) -> 20 | O190: =VLOOKUP(C190,'[2]Customer Detail'!$A$2:$H$501,5,FALSE) -> Novakstad | P190: =VLOOKUP(C190,'[2]Customer Detail'!$A$1:$H$501,8,FALSE) -> Gold | Q190: =VLOOKUP(G190,[2]Store_Dim!$A$1:$E$21,4,FALSE) -> Hoodberg | R190: =VLOOKUP(G190,[2]Store_Dim!$A$2:$E$21,3,FALSE) -> North
A191: SALE189 | B191: 45411 | C191: CUST1091 | D191: PROD46 | E191: =VLOOKUP(D191,[2]Product_Dim!$A$2:$G$101,2,FALSE) -> Men's Winter Jacket | F191: =VLOOKUP(D191,[2]Product_Dim!$A$2:$G$101,6,FALSE) -> 167.34 | G191: STORE3 | H191: 1 | I191: 580.76 | J191: 0.1 | K191: COD | L191: 522.684 | M191: =VLOOKUP(C191,'[2]Customer Detail'!$A$2:$H$501,4,FALSE) -> Female | N191: =VLOOKUP(C191,'[2]Customer Detail'!$A$2:$H$501,3,FALSE) -> 29 | O191: =VLOOKUP(C191,'[2]Customer Detail'!$A$2:$H$501,5,FALSE) -> South Amandahaven | P191: =VLOOKUP(C191,'[2]Customer Detail'!$A$1:$H$501,8,FALSE) -> Silver | Q191: =VLOOKUP(G191,[2]Store_Dim!$A$1:$E$21,4,FALSE) -> Hoodberg | R191: =VLOOKUP(G191,[2]Store_Dim!$A$2:$E$21,3,FALSE) -> North
A192: SALE190 | B192: 45775 | C192: CUST1334 | D192: PROD71 | E192: =VLOOKUP(D192,[2]Product_Dim!$A$2:$G$101,2,FALSE) -> Hair Repair Oil Treatment | F192: =VLOOKUP(D192,[2]Product_Dim!$A$2:$G$101,6,FALSE) -> 214.32 | G192: STORE9 | H192: 3 | I192: 444.55 | J192: 0.14 | K192: PayPal | L192: 1146.939 | M192: =VLOOKUP(C192,'[2]Customer Detail'!$A$2:$H$501,4,FALSE) -> Female | N192: =VLOOKUP(C192,'[2]Customer Detail'!$A$2:$H$501,3,FALSE) -> 50 | O192: =VLOOKUP(C192,'[2]Customer Detail'!$A$2:$H$501,5,FALSE) -> Donaldsontown | P192: =VLOOKUP(C192,'[2]Customer Detail'!$A$1:$H$501,8,FALSE) -> Silver | Q192: =VLOOKUP(G192,[2]Store_Dim!$A$1:$E$21,4,FALSE) -> East Johnstad | R192: =VLOOKUP(G192,[2]Store_Dim!$A$2:$E$21,3,FALSE) -> South
... A426: SALE424 | B426: 45220 | C426: CUST1037 | D426: PROD79 | E426: =VLOOKUP(D426,[2]Product_Dim!$A$2:$G$101,2,FALSE) -> Decorative Lamp Shade | F426: =VLOOKUP(D426,[2]Product_Dim!$A$2:$G$101,6,FALSE) -> 228.53 | G426: STORE13 | H426: 1 | I426: 823.61 | J426: 0.28 | K426: COD | L426: 592.9992 | M426: =VLOOKUP(C426,'[2]Customer Detail'!$A$2:$H$501,4,FALSE) -> Female | N426: =VLOOKUP(C426,'[2]Customer Detail'!$A$2:$H$501,3,FALSE) -> 27 | O426: =VLOOKUP(C426,'[2]Customer Detail'!$A$2:$H$501,5,FALSE) -> Brendastad | P426: =VLOOKUP(C426,'[2]Customer Detail'!$A$1:$H$501,8,FALSE) -> Platinum | Q426: =VLOOKUP(G426,[2]Store_Dim!$A$1:$E$21,4,FALSE) -> Johnsonville | R426: =VLOOKUP(G426,[2]Store_Dim!$A$2:$E$21,3,FALSE) -> East
A427: SALE425 | B427: 45807 | C427: CUST1478 | D427: PROD87 | E427: =VLOOKUP(D427,[2]Product_Dim!$A$2:$G$101,2,FALSE) -> LED Bedside Lamp | F427: =VLOOKUP(D427,[2]Product_Dim!$A$2:$G$101,6,FALSE) -> 371.38 | G427: STORE9 | H427: 2 | I427: 209.96 | J427: No Discount | K427: Credit Card | L427: 419.92 | M427: =VLOOKUP(C427,'[2]Customer Detail'!$A$2:$H$501,4,FALSE) -> Male | N427: =VLOOKUP(C427,'[2]Customer Detail'!$A$2:$H$501,3,FALSE) -> 59 | O427: =VLOOKUP(C427,'[2]Customer Detail'!$A$2:$H$501,5,FALSE) -> West Sarah | P427: =VLOOKUP(C427,'[2]Customer Detail'!$A$1:$H$501,8,FALSE) -> Gold | Q427: =VLOOKUP(G427,[2]Store_Dim!$A$1:$E$21,4,FALSE) -> East Johnstad | R427: =VLOOKUP(G427,[2]Store_Dim!$A$2:$E$21,3,FALSE) -> South
A428: SALE426 | B428: 45462 | C428: CUST1175 | D428: PROD0 | E428: =VLOOKUP(D428,[2]Product_Dim!$A$2:$G$101,2,FALSE) -> Brother Laser Printer | F428: =VLOOKUP(D428,[2]Product_Dim!$A$2:$G$101,6,FALSE) -> 112.42 | G428: STORE16 | H428: 4 | I428: 897.93 | J428: 0.05 | K428: COD | L428: 3412.134 | M428: =VLOOKUP(C428,'[2]Customer Detail'!$A$2:$H$501,4,FALSE) -> Male | N428: =VLOOKUP(C428,'[2]Customer Detail'!$A$2:$H$501,3,FALSE) -> 56 | O428: =VLOOKUP(C428,'[2]Customer Detail'!$A$2:$H$501,5,FALSE) -> East Jessicaborough | P428: =VLOOKUP(C428,'[2]Customer Detail'!$A$1:$H$501,8,FALSE) -> Platinum | Q428: =VLOOKUP(G428,[2]Store_Dim!$A$1:$E$21,4,FALSE) -> New Jimmymouth | R428: =VLOOKUP(G428,[2]Store_Dim!$A$2:$E$21,3,FALSE) -> West
A429: SALE427 | B429: 45646 | C429: CUST1181 | D429: PROD63 | E429: =VLOOKUP(D429,[2]Product_Dim!$A$2:$G$101,2,FALSE) -> Organic Sunscreen Lotion | F429: =VLOOKUP(D429,[2]Product_Dim!$A$2:$G$101,6,FALSE) -> 266.86 | G429: STORE0 | H429: 4 | I429: 925.95 | J429: 0.16 | K429: COD | L429: 3111.192 | M429: =VLOOKUP(C429,'[2]Customer Detail'!$A$2:$H$501,4,FALSE) -> Male | N429: =VLOOKUP(C429,'[2]Customer Detail'!$A$2:$H$501,3,FALSE) -> 60 | O429: =VLOOKUP(C429,'[2]Customer Detail'!$A$2:$H$501,5,FALSE) -> New Brianchester | P429: =VLOOKUP(C429,'[2]Customer Detail'!$A$1:$H$501,8,FALSE) -> Bronze | Q429: =VLOOKUP(G429,[2]Store_Dim!$A$1:$E$21,4,FALSE) -> Washingtonfurt | R429: =VLOOKUP(G429,[2]Store_Dim!$A$2:$E$21,3,FALSE) -> East
A430: SALE428 | B430: 45520 | C430: CUST1084 | D430: PROD51 | E430: =VLOOKUP(D430,[2]Product_Dim!$A$2:$G$101,2,FALSE) -> HDMI Cable – 2m | F430: =VLOOKUP(D430,[2]Product_Dim!$A$2:$G$101,6,FALSE) -> 88.49 | G430: STORE6 | H430: 2 | I430: 573.09 | J430: 0.03 | K430: COD | L430: 1111.7946 | M430: =VLOOKUP(C430,'[2]Customer Detail'!$A$2:$H$501,4,FALSE) -> Female | N430: =VLOOKUP(C430,'[2]Customer Detail'!$A$2:$H$501,3,FALSE) -> 26 | O430: =VLOOKUP(C430,'[2]Customer Detail'!$A$2:$H$501,5,FALSE) -> Garyberg | P430: =VLOOKUP(C430,'[2]Customer Detail'!$A$1:$H$501,8,FALSE) -> Platinum | Q430: =VLOOKUP(G430,[2]Store_Dim!$A$1:$E$21,4,FALSE) -> Port Josephberg | R430: =VLOOKUP(G430,[2]Store_Dim!$A$2:$E$21,3,FALSE) -> East
A431: SALE429 | B431: 45731 | C431: CUST1183 | D431: PROD7 | E431: =VLOOKUP(D431,[2]Product_Dim!$A$2:$G$101,2,FALSE) -> LED Table Lamp | F431: =VLOOKUP(D431,[2]Product_Dim!$A$2:$G$101,6,FALSE) -> 218.86 | G431: STORE4 | H431: 4 | I431: 149.83 | J431: 0.02 | K431: Credit Card | L431: 587.3336 | M431: =VLOOKUP(C431,'[2]Customer Detail'!$A$2:$H$501,4,FALSE) -> Male | N431: =VLOOKUP(C431,'[2]Customer Detail'!$A$2:$H$501,3,FALSE) -> 18 | O431: =VLOOKUP(C431,'[2]Customer Detail'!$A$2:$H$501,5,FALSE) -> Port James | P431: =VLOOKUP(C431,'[2]Customer Detail'!$A$1:$H$501,8,FALSE) -> Platinum | Q431: =VLOOKUP(G431,[2]Store_Dim!$A$1:$E$21,4,FALSE) -> Port Sharon | R431: =VLOOKUP(G431,[2]Store_Dim!$A$2:$E$21,3,FALSE) -> South
A432: SALE430 | B432: 45445 | C432: CUST1001 | D432: PROD51 | E432: =VLOOKUP(D432,[2]Product_Dim!$A$2:$G$101,2,FALSE) -> HDMI Cable – 2m | F432: =VLOOKUP(D432,[2]Product_Dim!$A$2:$G$101,6,FALSE) -> 88.49 | G432: STORE14 | H432: 3 | I432: 287.71 | J432: 0.03 | K432: COD | L432: 837.2361 | M432: =VLOOKUP(C432,'[2]Customer Detail'!$A$2:$H$501,4,FALSE) -> Female | N432: =VLOOKUP(C432,'[2]Customer Detail'!$A$2:$H$501,3,FALSE) -> 26 | O432: =VLOOKUP(C432,'[2]Customer Detail'!$A$2:$H$501,5,FALSE) -> Phillipsmouth | P432: =VLOOKUP(C432,'[2]Customer Detail'!$A$1:$H$501,8,FALSE) -> Platinum | Q432: =VLOOKUP(G432,[2]Store_Dim!$A$1:$E$21,4,FALSE) -> Christopherland | R432: =VLOOKUP(G432,[2]Store_Dim!$A$2:$E$21,3,FALSE) -> South
A433: SALE431 | B433: 45860 | C433: CUST1094 | D433: PROD67 | E433: =VLOOKUP(D433,[2]Product_Dim!$A$2:$G$101,2,FALSE) -> Smart LED Light Strip | F433: =VLOOKUP(D433,[2]Product_Dim!$A$2:$G$101,6,FALSE) -> 349.17 | G433: STORE6 | H433: 2 | I433: 849.8 | J433: 0.06 | K433: COD | L433: 1597.624 | M433: =VLOOKUP(C433,'[2]Customer Detail'!$A$2:$H$501,4,FALSE) -> Female | N433: =VLOOKUP(C433,'[2]Customer Detail'!$A$2:$H$501,3,FALSE) -> 43 | O433: =VLOOKUP(C433,'[2]Customer Detail'!$A$2:$H$501,5,FALSE) -> New Amyport | P433: =VLOOKUP(C433,'[2]Customer Detail'!$A$1:$H$501,8,FALSE) -> Gold | Q433: =VLOOKUP(G433,[2]Store_Dim!$A$1:$E$21,4,FALSE) -> Port Josephberg | R433: =VLOOKUP(G433,[2]Store_Dim!$A$2:$E$21,3,FALSE) -> East
A434: SALE432 | B434: 45725 | C434: CUST1016 | D434: PROD41 | E434: =VLOOKUP(D434,[2]Product_Dim!$A$2:$G$101,2,FALSE) -> Yoga Exercise Mat | F434: =VLOOKUP(D434,[2]Product_Dim!$A$2:$G$101,6,FALSE) -> 313.26 | G434: STORE3 | H434: 3 | I434: 482.58 | J434: 0.28 | K434: PayPal | L434: 1042.3728 | M434: =VLOOKUP(C434,'[2]Customer Detail'!$A$2:$H$501,4,FALSE) -> Female | N434: =VLOOKUP(C434,'[2]Customer Detail'!$A$2:$H$501,3,FALSE) -> 24 | O434: =VLOOKUP(C434,'[2]Customer Detail'!$A$2:$H$501,5,FALSE) -> South Christopher | P434: =VLOOKUP(C434,'[2]Customer Detail'!$A$1:$H$501,8,FALSE) -> Bronze | Q434: =VLOOKUP(G434,[2]Store_Dim!$A$1:$E$21,4,FALSE) -> Hoodberg | R434: =VLOOKUP(G434,[2]Store_Dim!$A$2:$E$21,3,FALSE) -> North
A435: SALE433 | B435: 45699 | C435: CUST1114 | D435: PROD59 | E435: =VLOOKUP(D435,[2]Product_Dim!$A$2:$G$101,2,FALSE) -> Men's Hair Styling Gel | F435: =VLOOKUP(D435,[2]Product_Dim!$A$2:$G$101,6,FALSE) -> 17.31 | G435: STORE2 | H435: 2 | I435: 64.7 | J435: No Discount | K435: Credit Card | L435: 129.4 | M435: =VLOOKUP(C435,'[2]Customer Detail'!$A$2:$H$501,4,FALSE) -> Male | N435: =VLOOKUP(C435,'[2]Customer Detail'!$A$2:$H$501,3,FALSE) -> 30 | O435: =VLOOKUP(C435,'[2]Customer Detail'!$A$2:$H$501,5,FALSE) -> East Donna | P435: =VLOOKUP(C435,'[2]Customer Detail'!$A$1:$H$501,8,FALSE) -> Bronze | Q435: =VLOOKUP(G435,[2]Store_Dim!$A$1:$E$21,4,FALSE) -> North Nancyview | R435: =VLOOKUP(G435,[2]Store_Dim!$A$2:$E$21,3,FALSE) -> South
A436: SALE434 | B436: 45266 | C436: CUST1148 | D436: PROD5 | E436: =VLOOKUP(D436,[2]Product_Dim!$A$2:$G$101,2,FALSE) -> Men's Leather Belt | F436: =VLOOKUP(D436,[2]Product_Dim!$A$2:$G$101,6,FALSE) -> 261 | G436: STORE5 | H436: 3 | I436: 589.83 | J436: 0.26 | K436: Credit Card | L436: 1309.4226 | M436: =VLOOKUP(C436,'[2]Customer Detail'!$A$2:$H$501,4,FALSE) -> Female | N436: =VLOOKUP(C436,'[2]Customer Detail'!$A$2:$H$501,3,FALSE) -> 42 | O436: =VLOOKUP(C436,'[2]Customer Detail'!$A$2:$H$501,5,FALSE) -> New Brian | P436: =VLOOKUP(C436,'[2]Customer Detail'!$A$1:$H$501,8,FALSE) -> Bronze | Q436: =VLOOKUP(G436,[2]Store_Dim!$A$1:$E$21,4,FALSE) -> New Michaelchester | R436: =VLOOKUP(G436,[2]Store_Dim!$A$2:$E$21,3,FALSE) -> North
A437: SALE435 | B437: 45889 | C437: CUST1288 | D437: PROD3 | E437: =VLOOKUP(D437,[2]Product_Dim!$A$2:$G$101,2,FALSE) -> Men's Running Jacket | F437: =VLOOKUP(D437,[2]Product_Dim!$A$2:$G$101,6,FALSE) -> 364.67 | G437: STORE9 | H437: 4 | I437: 758.49 | J437: 0.16 | K437: COD | L437: 2548.5264 | M437: =VLOOKUP(C437,'[2]Customer Detail'!$A$2:$H$501,4,FALSE) -> Male | N437: =VLOOKUP(C437,'[2]Customer Detail'!$A$2:$H$501,3,FALSE) -> 58 | O437: =VLOOKUP(C437,'[2]Customer Detail'!$A$2:$H$501,5,FALSE) -> North Joseside | P437: =VLOOKUP(C437,'[2]Customer Detail'!$A$1:$H$501,8,FALSE) -> Gold | Q437: =VLOOKUP(G437,[2]Store_Dim!$A$1:$E$21,4,FALSE) -> East Johnstad | R437: =VLOOKUP(G437,[2]Store_Dim!$A$2:$E$21,3,FALSE) -> South
A438: SALE436 | B438: 45555 | C438: CUST1053 | D438: PROD37 | E438: =VLOOKUP(D438,[2]Product_Dim!$A$2:$G$101,2,FALSE) -> Men's Casual Sneakers | F438: =VLOOKUP(D438,[2]Product_Dim!$A$2:$G$101,6,FALSE) -> 353.47 | G438: STORE12 | H438: 4 | I438: 747.56 | J438: 0.09 | K438: COD | L438: 2721.1184 | M438: =VLOOKUP(C438,'[2]Customer Detail'!$A$2:$H$501,4,FALSE) -> Female | N438: =VLOOKUP(C438,'[2]Customer Detail'!$A$2:$H$501,3,FALSE) -> 37 | O438: =VLOOKUP(C438,'[2]Customer Detail'!$A$2:$H$501,5,FALSE) -> East Andrea | P438: =VLOOKUP(C438,'[2]Customer Detail'!$A$1:$H$501,8,FALSE) -> Gold | Q438: =VLOOKUP(G438,[2]Store_Dim!$A$1:$E$21,4,FALSE) -> Sabrinatown | R438: =VLOOKUP(G438,[2]Store_Dim!$A$2:$E$21,3,FALSE) -> North
A439: SALE437 | B439: 45813 | C439: CUST1253 | D439: PROD40 | E439: =VLOOKUP(D439,[2]Product_Dim!$A$2:$G$101,2,FALSE) -> Noise-Canceling Headphones | F439: =VLOOKUP(D439,[2]Product_Dim!$A$2:$G$101,6,FALSE) -> 38.52 | G439: STORE17 | H439: 3 | I439: 551.22 | J439: 0.12 | K439: PayPal | L439: 1455.2208 | M439: =VLOOKUP(C439,'[2]Customer Detail'!$A$2:$H$501,4,FALSE) -> Male | N439: =VLOOKUP(C439,'[2]Customer Detail'!$A$2:$H$501,3,FALSE) -> 32 | O439: =VLOOKUP(C439,'[2]Customer Detail'!$A$2:$H$501,5,FALSE) -> New Maria | P439: =VLOOKUP(C439,'[2]Customer Detail'!$A$1:$H$501,8,FALSE) -> Bronze | Q439: =VLOOKUP(G439,[2]Store_Dim!$A$1:$E$21,4,FALSE) -> Bensonhaven | R439: =VLOOKUP(G439,[2]Store_Dim!$A$2:$E$21,3,FALSE) -> North
A440: SALE438 | B440: 45811 | C440: CUST1159 | D440: PROD69 | E440: =VLOOKUP(D440,[2]Product_Dim!$A$2:$G$101,2,FALSE) -> Men's Sports Shorts | F440: =VLOOKUP(D440,[2]Product_Dim!$A$2:$G$101,6,FALSE) -> 218.22 | G440: STORE14 | H440: 2 | I440: 527.06 | J440: 0.17 | K440: PayPal | L440: 874.9196 | M440: =VLOOKUP(C440,'[2]Customer Detail'!$A$2:$H$501,4,FALSE) -> Female | N440: =VLOOKUP(C440,'[2]Customer Detail'!$A$2:$H$501,3,FALSE) -> 46 | O440: =VLOOKUP(C440,'[2]Customer Detail'!$A$2:$H$501,5,FALSE) -> Floydton | P440: =VLOOKUP(C440,'[2]Customer Detail'!$A$1:$H$501,8,FALSE) -> Gold | Q440: =VLOOKUP(G440,[2]Store_Dim!$A$1:$E$21,4,FALSE) -> Christopherland | R440: =VLOOKUP(G440,[2]Store_Dim!$A$2:$E$21,3,FALSE) -> South
A441: SALE439 | B441: 45670 | C441: CUST1098 | D441: PROD62 | E441: =VLOOKUP(D441,[2]Product_Dim!$A$2:$G$101,2,FALSE) -> Laptop Cooling Pad | F441: =VLOOKUP(D441,[2]Product_Dim!$A$2:$G$101,6,FALSE) -> 86.42 | G441: STORE5 | H441: 4 | I441: 875.41 | J441: 0.27 | K441: Credit Card | L441: 2556.1972 | M441: =VLOOKUP(C441,'[2]Customer Detail'!$A$2:$H$501,4,FALSE) -> Male | N441: =VLOOKUP(C441,'[2]Customer Detail'!$A$2:$H$501,3,FALSE) -> 24 | O441: =VLOOKUP(C441,'[2]Customer Detail'!$A$2:$H$501,5,FALSE) -> Lake Kaylahaven | P441: =VLOOKUP(C441,'[2]Customer Detail'!$A$1:$H$501,8,FALSE) -> Gold | Q441: =VLOOKUP(G441,[2]Store_Dim!$A$1:$E$21,4,FALSE) -> New Michaelchester | R441: =VLOOKUP(G441,[2]Store_Dim!$A$2:$E$21,3,FALSE) -> North
A442: SALE440 | B442: 45736 | C442: CUST1007 | D442: PROD85 | E442: =VLOOKUP(D442,[2]Product_Dim!$A$2:$G$101,2,FALSE) -> Women's Beanie Hat | F442: =VLOOKUP(D442,[2]Product_Dim!$A$2:$G$101,6,FALSE) -> 119.57 | G442: STORE0 | H442: 2 | I442: 226.43 | J442: 0.03 | K442: Credit Card | L442: 439.2742 | M442: =VLOOKUP(C442,'[2]Customer Detail'!$A$2:$H$501,4,FALSE) -> Female | N442: =VLOOKUP(C442,'[2]Customer Detail'!$A$2:$H$501,3,FALSE) -> 29 | O442: =VLOOKUP(C442,'[2]Customer Detail'!$A$2:$H$501,5,FALSE) -> West Pamelafurt | P442: =VLOOKUP(C442,'[2]Customer Detail'!$A$1:$H$501,8,FALSE) -> Bronze | Q442: =VLOOKUP(G442,[2]Store_Dim!$A$1:$E$21,4,FALSE) -> Washingtonfurt | R442: =VLOOKUP(G442,[2]Store_Dim!$A$2:$E$21,3,FALSE) -> East
A443: SALE441 | B443: 45480 | C443: CUST1035 | D443: PROD79 | E443: =VLOOKUP(D443,[2]Product_Dim!$A$2:$G$101,2,FALSE) -> Decorative Lamp Shade | F443: =VLOOKUP(D443,[2]Product_Dim!$A$2:$G$101,6,FALSE) -> 228.53 | G443: STORE5 | H443: 2 | I443: 285.39 | J443: 0.1 | K443: Credit Card | L443: 513.702 | M443: =VLOOKUP(C443,'[2]Customer Detail'!$A$2:$H$501,4,FALSE) -> Male | N443: =VLOOKUP(C443,'[2]Customer Detail'!$A$2:$H$501,3,FALSE) -> 52 | O443: =VLOOKUP(C443,'[2]Customer Detail'!$A$2:$H$501,5,FALSE) -> Robertberg | P443: =VLOOKUP(C443,'[2]Customer Detail'!$A$1:$H$501,8,FALSE) -> Silver | Q443: =VLOOKUP(G443,[2]Store_Dim!$A$1:$E$21,4,FALSE) -> New Michaelchester | R443: =VLOOKUP(G443,[2]Store_Dim!$A$2:$E$21,3,FALSE) -> North
A444: SALE442 | B444: 45929 | C444: CUST1334 | D444: PROD11 | E444: =VLOOKUP(D444,[2]Product_Dim!$A$2:$G$101,2,FALSE) -> HD Smart TV Stick | F444: =VLOOKUP(D444,[2]Product_Dim!$A$2:$G$101,6,FALSE) -> 449.4 | G444: STORE15 | H444: 2 | I444: 298.01 | J444: 0.05 | K444: Credit Card | L444: 566.219 | M444: =VLOOKUP(C444,'[2]Customer Detail'!$A$2:$H$501,4,FALSE) -> Female | N444: =VLOOKUP(C444,'[2]Customer Detail'!$A$2:$H$501,3,FALSE) -> 50 | O444: =VLOOKUP(C444,'[2]Customer Detail'!$A$2:$H$501,5,FALSE) -> Donaldsontown | P444: =VLOOKUP(C444,'[2]Customer Detail'!$A$1:$H$501,8,FALSE) -> Silver | Q444: =VLOOKUP(G444,[2]Store_Dim!$A$1:$E$21,4,FALSE) -> East Jenniferstad | R444: =VLOOKUP(G444,[2]Store_Dim!$A$2:$E$21,3,FALSE) -> North
A445: SALE443 | B445: 45626 | C445: CUST1159 | D445: PROD40 | E445: =VLOOKUP(D445,[2]Product_Dim!$A$2:$G$101,2,FALSE) -> Noise-Canceling Headphones | F445: =VLOOKUP(D445,[2]Product_Dim!$A$2:$G$101,6,FALSE) -> 38.52 | G445: STORE4 | H445: 4 | I445: 753.49 | J445: 0.26 | K445: COD | L445: 2230.3304 | M445: =VLOOKUP(C445,'[2]Customer Detail'!$A$2:$H$501,4,FALSE) -> Female | N445: =VLOOKUP(C445,'[2]Customer Detail'!$A$2:$H$501,3,FALSE) -> 46 | O445: =VLOOKUP(C445,'[2]Customer Detail'!$A$2:$H$501,5,FALSE) -> Floydton | P445: =VLOOKUP(C445,'[2]Customer Detail'!$A$1:$H$501,8,FALSE) -> Gold | Q445: =VLOOKUP(G445,[2]Store_Dim!$A$1:$E$21,4,FALSE) -> Port Sharon | R445: =VLOOKUP(G445,[2]Store_Dim!$A$2:$E$21,3,FALSE) -> South
A446: SALE444 | B446: 45460 | C446: CUST1488 | D446: PROD78 | E446: =VLOOKUP(D446,[2]Product_Dim!$A$2:$G$101,2,FALSE) -> Essential Oil Diffuser | F446: =VLOOKUP(D446,[2]Product_Dim!$A$2:$G$101,6,FALSE) -> 325.26 | G446: STORE12 | H446: 2 | I446: 130.39 | J446: 0.17 | K446: PayPal | L446: 216.4474 | M446: =VLOOKUP(C446,'[2]Customer Detail'!$A$2:$H$501,4,FALSE) -> Female | N446: =VLOOKUP(C446,'[2]Customer Detail'!$A$2:$H$501,3,FALSE) -> 23 | O446: =VLOOKUP(C446,'[2]Customer Detail'!$A$2:$H$501,5,FALSE) -> South Davidport | P446: =VLOOKUP(C446,'[2]Customer Detail'!$A$1:$H$501,8,FALSE) -> Platinum | Q446: =VLOOKUP(G446,[2]Store_Dim!$A$1:$E$21,4,FALSE) -> Sabrinatown | R446: =VLOOKUP(G446,[2]Store_Dim!$A$2:$E$21,3,FALSE) -> North
A447: SALE445 | B447: 45709 | C447: CUST1345 | D447: PROD22 | E447: =VLOOKUP(D447,[2]Product_Dim!$A$2:$G$101,2,FALSE) -> Carbon Fiber Tennis Racket | F447: =VLOOKUP(D447,[2]Product_Dim!$A$2:$G$101,6,FALSE) -> 484.62 | G447: STORE9 | H447: 4 | I447: 164.02 | J447: 0.01 | K447: PayPal | L447: 649.5192 | M447: =VLOOKUP(C447,'[2]Customer Detail'!$A$2:$H$501,4,FALSE) -> Male | N447: =VLOOKUP(C447,'[2]Customer Detail'!$A$2:$H$501,3,FALSE) -> 33 | O447: =VLOOKUP(C447,'[2]Customer Detail'!$A$2:$H$501,5,FALSE) -> North Jonathan | P447: =VLOOKUP(C447,'[2]Customer Detail'!$A$1:$H$501,8,FALSE) -> Bronze | Q447: =VLOOKUP(G447,[2]Store_Dim!$A$1:$E$21,4,FALSE) -> East Johnstad | R447: =VLOOKUP(G447,[2]Store_Dim!$A$2:$E$21,3,FALSE) -> South
... A547: SALE545 | B547: 45255 | C547: CUST1103 | D547: PROD26 | E547: =VLOOKUP(D547,[2]Product_Dim!$A$2:$G$101,2,FALSE) -> Wireless Bluetooth Speaker | F547: =VLOOKUP(D547,[2]Product_Dim!$A$2:$G$101,6,FALSE) -> 322.41 | G547: STORE1 | H547: 4 | I547: 90.32 | J547: 0.08 | K547: PayPal | L547: 332.3776 | M547: =VLOOKUP(C547,'[2]Customer Detail'!$A$2:$H$501,4,FALSE) -> Male | N547: =VLOOKUP(C547,'[2]Customer Detail'!$A$2:$H$501,3,FALSE) -> 21 | O547: =VLOOKUP(C547,'[2]Customer Detail'!$A$2:$H$501,5,FALSE) -> West Lauren | P547: =VLOOKUP(C547,'[2]Customer Detail'!$A$1:$H$501,8,FALSE) -> Bronze | Q547: =VLOOKUP(G547,[2]Store_Dim!$A$1:$E$21,4,FALSE) -> Danielmouth | R547: =VLOOKUP(G547,[2]Store_Dim!$A$2:$E$21,3,FALSE) -> North
A548: SALE546 | B548: 45695 | C548: CUST1378 | D548: PROD10 | E548: =VLOOKUP(D548,[2]Product_Dim!$A$2:$G$101,2,FALSE) -> Ceramic Kitchen Bowl Set | F548: =VLOOKUP(D548,[2]Product_Dim!$A$2:$G$101,6,FALSE) -> 298.86 | G548: STORE6 | H548: 3 | I548: 370.93 | J548: No Discount | K548: Credit Card | L548: 1112.79 | M548: =VLOOKUP(C548,'[2]Customer Detail'!$A$2:$H$501,4,FALSE) -> Female | N548: =VLOOKUP(C548,'[2]Customer Detail'!$A$2:$H$501,3,FALSE) -> 44 | O548: =VLOOKUP(C548,'[2]Customer Detail'!$A$2:$H$501,5,FALSE) -> Fischerborough | P548: =VLOOKUP(C548,'[2]Customer Detail'!$A$1:$H$501,8,FALSE) -> Bronze | Q548: =VLOOKUP(G548,[2]Store_Dim!$A$1:$E$21,4,FALSE) -> Port Josephberg | R548: =VLOOKUP(G548,[2]Store_Dim!$A$2:$E$21,3,FALSE) -> East
A549: SALE547 | B549: 45281 | C549: CUST1046 | D549: PROD23 | E549: =VLOOKUP(D549,[2]Product_Dim!$A$2:$G$101,2,FALSE) -> Men's Formal Shirt | F549: =VLOOKUP(D549,[2]Product_Dim!$A$2:$G$101,6,FALSE) -> 254.04362 | G549: STORE15 | H549: 1 | I549: 352.43 | J549: 0.14 | K549: PayPal | L549: 303.0898 | M549: =VLOOKUP(C549,'[2]Customer Detail'!$A$2:$H$501,4,FALSE) -> Female | N549: =VLOOKUP(C549,'[2]Customer Detail'!$A$2:$H$501,3,FALSE) -> 55 | O549: =VLOOKUP(C549,'[2]Customer Detail'!$A$2:$H$501,5,FALSE) -> Perezbury | P549: =VLOOKUP(C549,'[2]Customer Detail'!$A$1:$H$501,8,FALSE) -> Platinum | Q549: =VLOOKUP(G549,[2]Store_Dim!$A$1:$E$21,4,FALSE) -> East Jenniferstad | R549: =VLOOKUP(G549,[2]Store_Dim!$A$2:$E$21,3,FALSE) -> North
A550: SALE548 | B550: 45295 | C550: CUST1123 | D550: PROD12 | E550: =VLOOKUP(D550,[2]Product_Dim!$A$2:$G$101,2,FALSE) -> Hair Strengthening Shampoo | F550: =VLOOKUP(D550,[2]Product_Dim!$A$2:$G$101,6,FALSE) -> 115.82 | G550: STORE15 | H550: 2 | I550: 562.97 | J550: 0.2 | K550: Credit Card | L550: 900.752 | M550: =VLOOKUP(C550,'[2]Customer Detail'!$A$2:$H$501,4,FALSE) -> Male | N550: =VLOOKUP(C550,'[2]Customer Detail'!$A$2:$H$501,3,FALSE) -> 40 | O550: =VLOOKUP(C550,'[2]Customer Detail'!$A$2:$H$501,5,FALSE) -> North Sabrina | P550: =VLOOKUP(C550,'[2]Customer Detail'!$A$1:$H$501,8,FALSE) -> Silver | Q550: =VLOOKUP(G550,[2]Store_Dim!$A$1:$E$21,4,FALSE) -> East Jenniferstad | R550: =VLOOKUP(G550,[2]Store_Dim!$A$2:$E$21,3,FALSE) -> North
A551: SALE549 | B551: 45260 | C551: CUST1157 | D551: PROD55 | E551: =VLOOKUP(D551,[2]Product_Dim!$A$2:$G$101,2,FALSE) -> Ceramic Plant Pot | F551: =VLOOKUP(D551,[2]Product_Dim!$A$2:$G$101,6,FALSE) -> 81.75 | G551: STORE7 | H551: 1 | I551: 522.85 | J551: 0.12 | K551: PayPal | L551: 460.108 | M551: =VLOOKUP(C551,'[2]Customer Detail'!$A$2:$H$501,4,FALSE) -> Male | N551: =VLOOKUP(C551,'[2]Customer Detail'!$A$2:$H$501,3,FALSE) -> 59 | O551: =VLOOKUP(C551,'[2]Customer Detail'!$A$2:$H$501,5,FALSE) -> North Larryfurt | P551: =VLOOKUP(C551,'[2]Customer Detail'!$A$1:$H$501,8,FALSE) -> Platinum | Q551: =VLOOKUP(G551,[2]Store_Dim!$A$1:$E$21,4,FALSE) -> Williamsfurt | R551: =VLOOKUP(G551,[2]Store_Dim!$A$2:$E$21,3,FALSE) -> South
A552: SALE550 | B552: 45851 | C552: CUST1349 | D552: PROD21 | E552: =VLOOKUP(D552,[2]Product_Dim!$A$2:$G$101,2,FALSE) -> Multi-Purpose Storage Box | F552: =VLOOKUP(D552,[2]Product_Dim!$A$2:$G$101,6,FALSE) -> 123.46 | G552: STORE16 | H552: 4 | I552: 714.89 | J552: 0.15 | K552: Credit Card | L552: 2430.626 | M552: =VLOOKUP(C552,'[2]Customer Detail'!$A$2:$H$501,4,FALSE) -> Male | N552: =VLOOKUP(C552,'[2]Customer Detail'!$A$2:$H$501,3,FALSE) -> 31 | O552: =VLOOKUP(C552,'[2]Customer Detail'!$A$2:$H$501,5,FALSE) -> New Angiefurt | P552: =VLOOKUP(C552,'[2]Customer Detail'!$A$1:$H$501,8,FALSE) -> Bronze | Q552: =VLOOKUP(G552,[2]Store_Dim!$A$1:$E$21,4,FALSE) -> New Jimmymouth | R552: =VLOOKUP(G552,[2]Store_Dim!$A$2:$E$21,3,FALSE) -> West
A553: SALE551 | B553: 45222 | C553: CUST1187 | D553: PROD43 | E553: =VLOOKUP(D553,[2]Product_Dim!$A$2:$G$101,2,FALSE) -> USB External Hard Drive | F553: =VLOOKUP(D553,[2]Product_Dim!$A$2:$G$101,6,FALSE) -> 253.33 | G553: STORE2 | H553: 3 | I553: 137.77 | J553: 0.26 | K553: PayPal | L553: 305.8494 | M553: =VLOOKUP(C553,'[2]Customer Detail'!$A$2:$H$501,4,FALSE) -> Female | N553: =VLOOKUP(C553,'[2]Customer Detail'!$A$2:$H$501,3,FALSE) -> 60 | O553: =VLOOKUP(C553,'[2]Customer Detail'!$A$2:$H$501,5,FALSE) -> Lake Blaketon | P553: =VLOOKUP(C553,'[2]Customer Detail'!$A$1:$H$501,8,FALSE) -> Platinum | Q553: =VLOOKUP(G553,[2]Store_Dim!$A$1:$E$21,4,FALSE) -> North Nancyview | R553: =VLOOKUP(G553,[2]Store_Dim!$A$2:$E$21,3,FALSE) -> South
A554: SALE552 | B554: 45940 | C554: CUST1027 | D554: PROD92 | E554: =VLOOKUP(D554,[2]Product_Dim!$A$2:$G$101,2,FALSE) -> Microwave Oven | F554: =VLOOKUP(D554,[2]Product_Dim!$A$2:$G$101,6,FALSE) -> 447.43 | G554: STORE11 | H554: 3 | I554: 862.18 | J554: 0.22 | K554: PayPal | L554: 2017.5012 | M554: =VLOOKUP(C554,'[2]Customer Detail'!$A$2:$H$501,4,FALSE) -> Male | N554: =VLOOKUP(C554,'[2]Customer Detail'!$A$2:$H$501,3,FALSE) -> 31 | O554: =VLOOKUP(C554,'[2]Customer Detail'!$A$2:$H$501,5,FALSE) -> Mollyshire | P554: =VLOOKUP(C554,'[2]Customer Detail'!$A$1:$H$501,8,FALSE) -> Platinum | Q554: =VLOOKUP(G554,[2]Store_Dim!$A$1:$E$21,4,FALSE) -> Lake Michael | R554: =VLOOKUP(G554,[2]Store_Dim!$A$2:$E$21,3,FALSE) -> South
A555: SALE553 | B555: 45822 | C555: CUST1057 | D555: PROD38 | E555: =VLOOKUP(D555,[2]Product_Dim!$A$2:$G$101,2,FALSE) -> Sports Water Hydration Pack | F555: =VLOOKUP(D555,[2]Product_Dim!$A$2:$G$101,6,FALSE) -> 135.61 | G555: STORE14 | H555: 2 | I555: 833.64 | J555: 0.24 | K555: PayPal | L555: 1267.1328 | M555: =VLOOKUP(C555,'[2]Customer Detail'!$A$2:$H$501,4,FALSE) -> Female | N555: =VLOOKUP(C555,'[2]Customer Detail'!$A$2:$H$501,3,FALSE) -> 43 | O555: =VLOOKUP(C555,'[2]Customer Detail'!$A$2:$H$501,5,FALSE) -> Morrisbury | P555: =VLOOKUP(C555,'[2]Customer Detail'!$A$1:$H$501,8,FALSE) -> Platinum | Q555: =VLOOKUP(G555,[2]Store_Dim!$A$1:$E$21,4,FALSE) -> Christopherland | R555: =VLOOKUP(G555,[2]Store_Dim!$A$2:$E$21,3,FALSE) -> South
A556: SALE554 | B556: 45752 | C556: CUST1270 | D556: PROD19 | E556: =VLOOKUP(D556,[2]Product_Dim!$A$2:$G$101,2,FALSE) -> Knee Support Brace | F556: =VLOOKUP(D556,[2]Product_Dim!$A$2:$G$101,6,FALSE) -> 21.34 | G556: STORE15 | H556: 3 | I556: 543.22 | J556: 0.05 | K556: COD | L556: 1548.177 | M556: =VLOOKUP(C556,'[2]Customer Detail'!$A$2:$H$501,4,FALSE) -> Female | N556: =VLOOKUP(C556,'[2]Customer Detail'!$A$2:$H$501,3,FALSE) -> 31 | O556: =VLOOKUP(C556,'[2]Customer Detail'!$A$2:$H$501,5,FALSE) -> Ramosmouth | P556: =VLOOKUP(C556,'[2]Customer Detail'!$A$1:$H$501,8,FALSE) -> Gold | Q556: =VLOOKUP(G556,[2]Store_Dim!$A$1:$E$21,4,FALSE) -> East Jenniferstad | R556: =VLOOKUP(G556,[2]Store_Dim!$A$2:$E$21,3,FALSE) -> North
A557: SALE555 | B557: 45677 | C557: CUST1278 | D557: PROD88 | E557: =VLOOKUP(D557,[2]Product_Dim!$A$2:$G$101,2,FALSE) -> Sports Wrist Sweatbands | F557: =VLOOKUP(D557,[2]Product_Dim!$A$2:$G$101,6,FALSE) -> 131.24 | G557: STORE2 | H557: 3 | I557: 691.02 | J557: 0.12 | K557: COD | L557: 1824.2928 | M557: =VLOOKUP(C557,'[2]Customer Detail'!$A$2:$H$501,4,FALSE) -> Female | N557: =VLOOKUP(C557,'[2]Customer Detail'!$A$2:$H$501,3,FALSE) -> 42 | O557: =VLOOKUP(C557,'[2]Customer Detail'!$A$2:$H$501,5,FALSE) -> Port Mariastad | P557: =VLOOKUP(C557,'[2]Customer Detail'!$A$1:$H$501,8,FALSE) -> Platinum | Q557: =VLOOKUP(G557,[2]Store_Dim!$A$1:$E$21,4,FALSE) -> North Nancyview | R557: =VLOOKUP(G557,[2]Store_Dim!$A$2:$E$21,3,FALSE) -> South
A558: SALE556 | B558: 45253 | C558: CUST1087 | D558: PROD86 | E558: =VLOOKUP(D558,[2]Product_Dim!$A$2:$G$101,2,FALSE) -> Kitchen Cutting Board | F558: =VLOOKUP(D558,[2]Product_Dim!$A$2:$G$101,6,FALSE) -> 176.07 | G558: STORE17 | H558: 4 | I558: 338.73 | J558: 0.18 | K558: Credit Card | L558: 1111.0344 | M558: =VLOOKUP(C558,'[2]Customer Detail'!$A$2:$H$501,4,FALSE) -> Female | N558: =VLOOKUP(C558,'[2]Customer Detail'!$A$2:$H$501,3,FALSE) -> 58 | O558: =VLOOKUP(C558,'[2]Customer Detail'!$A$2:$H$501,5,FALSE) -> East Jenna | P558: =VLOOKUP(C558,'[2]Customer Detail'!$A$1:$H$501,8,FALSE) -> Bronze | Q558: =VLOOKUP(G558,[2]Store_Dim!$A$1:$E$21,4,FALSE) -> Bensonhaven | R558: =VLOOKUP(G558,[2]Store_Dim!$A$2:$E$21,3,FALSE) -> North
A559: SALE557 | B559: 45389 | C559: CUST1062 | D559: PROD84 | E559: =VLOOKUP(D559,[2]Product_Dim!$A$2:$G$101,2,FALSE) -> Wooden Bookshelf | F559: =VLOOKUP(D559,[2]Product_Dim!$A$2:$G$101,6,FALSE) -> 388.46 | G559: STORE16 | H559: 3 | I559: 366.08 | J559: 0.05 | K559: Credit Card | L559: 1043.328 | M559: =VLOOKUP(C559,'[2]Customer Detail'!$A$2:$H$501,4,FALSE) -> Male | N559: =VLOOKUP(C559,'[2]Customer Detail'!$A$2:$H$501,3,FALSE) -> 50 | O559: =VLOOKUP(C559,'[2]Customer Detail'!$A$2:$H$501,5,FALSE) -> Stevensonton | P559: =VLOOKUP(C559,'[2]Customer Detail'!$A$1:$H$501,8,FALSE) -> Bronze | Q559: =VLOOKUP(G559,[2]Store_Dim!$A$1:$E$21,4,FALSE) -> New Jimmymouth | R559: =VLOOKUP(G559,[2]Store_Dim!$A$2:$E$21,3,FALSE) -> West
A560: SALE558 | B560: 45840 | C560: CUST1105 | D560: PROD13 | E560: =VLOOKUP(D560,[2]Product_Dim!$A$2:$G$101,2,FALSE) -> USB-C Fast Charger | F560: =VLOOKUP(D560,[2]Product_Dim!$A$2:$G$101,6,FALSE) -> 242.23 | G560: STORE13 | H560: 4 | I560: 539.48 | J560: 0.28 | K560: COD | L560: 1553.7024 | M560: =VLOOKUP(C560,'[2]Customer Detail'!$A$2:$H$501,4,FALSE) -> Female | N560: =VLOOKUP(C560,'[2]Customer Detail'!$A$2:$H$501,3,FALSE) -> 50 | O560: =VLOOKUP(C560,'[2]Customer Detail'!$A$2:$H$501,5,FALSE) -> Port Victoria | P560: =VLOOKUP(C560,'[2]Customer Detail'!$A$1:$H$501,8,FALSE) -> Gold | Q560: =VLOOKUP(G560,[2]Store_Dim!$A$1:$E$21,4,FALSE) -> Johnsonville | R560: =VLOOKUP(G560,[2]Store_Dim!$A$2:$E$21,3,FALSE) -> East
... A565: SALE563 | B565: 45223 | C565: CUST1011 | D565: PROD3 | E565: =VLOOKUP(D565,[2]Product_Dim!$A$2:$G$101,2,FALSE) -> Men's Running Jacket | F565: =VLOOKUP(D565,[2]Product_Dim!$A$2:$G$101,6,FALSE) -> 364.67 | G565: STORE3 | H565: 3 | I565: 728.32 | J565: 0.01 | K565: Credit Card | L565: 2163.1104 | M565: =VLOOKUP(C565,'[2]Customer Detail'!$A$2:$H$501,4,FALSE) -> Female | N565: =VLOOKUP(C565,'[2]Customer Detail'!$A$2:$H$501,3,FALSE) -> 28 | O565: =VLOOKUP(C565,'[2]Customer Detail'!$A$2:$H$501,5,FALSE) -> East Krista | P565: =VLOOKUP(C565,'[2]Customer Detail'!$A$1:$H$501,8,FALSE) -> Gold | Q565: =VLOOKUP(G565,[2]Store_Dim!$A$1:$E$21,4,FALSE) -> Hoodberg | R565: =VLOOKUP(G565,[2]Store_Dim!$A$2:$E$21,3,FALSE) -> North
A566: SALE564 | B566: 45507 | C566: CUST1452 | D566: PROD59 | E566: =VLOOKUP(D566,[2]Product_Dim!$A$2:$G$101,2,FALSE) -> Men's Hair Styling Gel | F566: =VLOOKUP(D566,[2]Product_Dim!$A$2:$G$101,6,FALSE) -> 17.31 | G566: STORE7 | H566: 3 | I566: 836.4 | J566: No Discount | K566: Credit Card | L566: 2509.2 | M566: =VLOOKUP(C566,'[2]Customer Detail'!$A$2:$H$501,4,FALSE) -> Female | N566: =VLOOKUP(C566,'[2]Customer Detail'!$A$2:$H$501,3,FALSE) -> 60 | O566: =VLOOKUP(C566,'[2]Customer Detail'!$A$2:$H$501,5,FALSE) -> New Laura | P566: =VLOOKUP(C566,'[2]Customer Detail'!$A$1:$H$501,8,FALSE) -> Bronze | Q566: =VLOOKUP(G566,[2]Store_Dim!$A$1:$E$21,4,FALSE) -> Williamsfurt | R566: =VLOOKUP(G566,[2]Store_Dim!$A$2:$E$21,3,FALSE) -> South
A567: SALE565 | B567: 45843 | C567: CUST1149 | D567: PROD90 | E567: =VLOOKUP(D567,[2]Product_Dim!$A$2:$G$101,2,FALSE) -> Gaming Mouse Pad XL | F567: =VLOOKUP(D567,[2]Product_Dim!$A$2:$G$101,6,FALSE) -> 340.14 | G567: STORE12 | H567: 1 | I567: 780.16 | J567: 0.02 | K567: COD | L567: 764.5568 | M567: =VLOOKUP(C567,'[2]Customer Detail'!$A$2:$H$501,4,FALSE) -> Male | N567: =VLOOKUP(C567,'[2]Customer Detail'!$A$2:$H$501,3,FALSE) -> 33 | O567: =VLOOKUP(C567,'[2]Customer Detail'!$A$2:$H$501,5,FALSE) -> West Markhaven | P567: =VLOOKUP(C567,'[2]Customer Detail'!$A$1:$H$501,8,FALSE) -> Platinum | Q567: =VLOOKUP(G567,[2]Store_Dim!$A$1:$E$21,4,FALSE) -> Sabrinatown | R567: =VLOOKUP(G567,[2]Store_Dim!$A$2:$E$21,3,FALSE) -> North
A568: SALE566 | B568: 45804 | C568: CUST1470 | D568: PROD46 | E568: =VLOOKUP(D568,[2]Product_Dim!$A$2:$G$101,2,FALSE) -> Men's Winter Jacket | F568: =VLOOKUP(D568,[2]Product_Dim!$A$2:$G$101,6,FALSE) -> 167.34 | G568: STORE13 | H568: 4 | I568: 354.12 | J568: 0.06 | K568: PayPal | L568: 1331.4912 | M568: =VLOOKUP(C568,'[2]Customer Detail'!$A$2:$H$501,4,FALSE) -> Female | N568: =VLOOKUP(C568,'[2]Customer Detail'!$A$2:$H$501,3,FALSE) -> 21 | O568: =VLOOKUP(C568,'[2]Customer Detail'!$A$2:$H$501,5,FALSE) -> Kanebury | P568: =VLOOKUP(C568,'[2]Customer Detail'!$A$1:$H$501,8,FALSE) -> Gold | Q568: =VLOOKUP(G568,[2]Store_Dim!$A$1:$E$21,4,FALSE) -> Johnsonville | R568: =VLOOKUP(G568,[2]Store_Dim!$A$2:$E$21,3,FALSE) -> East
...

Sheet Statistic_Summary
B3: Summary
B4: Total No of Sales | C4: =COUNT(Data_Analysis!L2:L2001) -> 2000
B5: Male Sales Count | C5: =COUNTIF(Table64[Gender],"Male") -> 904
B6: Female Sales Count | C6: =COUNTIF(Table64[Gender],"Female") -> 1095
B7: Total Sales Amount | C7: =SUM(Table64[[#All],[Total_Amount]]) -> 2174512.5
B8: Min_Sales Amount | C8: =MIN(Table64[[#All],[Total_Amount]]) -> 18.459
B9: Max_Sales Amount | C9: =MAX(Table64[[#All],[Total_Amount]]) -> 3908.2428

Sheet Charts and Tables
A1: Name | B1: Order_Date | C1: Total_Amount | D1: Payment_Type | E1: Age | F1: Gender | G1: Category | H1: Region | L1: Order_Date | M1: Total_Amount | R1: Payment_Type | S1: Total_Amount | W1: Gender | X1: Category | Y1: Total_Amount | AF1: Total_Amount | AG1: Region
A2: Sarah Smith | B2: 45480 | C2: 198.4164 | D2: Credit Card | E2: 48 | F2: Female | G2: Sports | H2: North | L2: 45480 | M2: 198.4164 | O2: Row Labels | P2: Sum of Total_Amount | R2: Credit Card | S2: 198.4164 | W2: Female | X2: Sports | Y2: 198.4164 | AF2: 198.4164 | AG2: North
A3: Michael Foley | B3: 45285 | C3: 228.7893 | D3: PayPal | E3: 45 | F3: Male | G3: Electronics | H3: North | L3: 45285 | M3: 228.7893 | O3: 2025 | P3: 857221.8 | R3: PayPal | S3: 228.7893 | T3: Row Labels | U3: Sum of Total_Amount | W3: Male | X3: Electronics | Y3: 228.7893 | Z3: Sum of Total_Amount | AA3: Column Labels | AF3: 228.7893 | AG3: North
A4: Christopher Sutton | B4: 45446 | C4: 2742.15 | D4: Credit Card | E4: 43 | F4: Female | G4: Beauty | H4: West | L4: 45446 | M4: 2742.15 | O4: Grand Total | P4: 857221.8 | R4: Credit Card | S4: 2742.15 | T4: COD | U4: 703703.34 | W4: Female | X4: Beauty | Y4: 2742.15 | Z4: Row Labels | AA4: Female | AB4: Male | AC4: Grand Total | AF4: 2742.15 | AG4: West | AH4: Row Labels | AI4: Sum of Total_Amount
A5: John Jordan | B5: 45259 | C5: 774.0684 | D5: COD | E5: 39 | F5: Female | G5: Electronics | H5: West | L5: 45259 | M5: 774.0684 | R5: COD | S5: 774.0684 | T5: Credit Card | U5: 714843.57 | W5: Female | X5: Electronics | Y5: 774.0684 | Z5: Beauty | AA5: 180344.28 | AB5: 175735.69 | AC5: 356079.97 | AF5: 774.0684 | AG5: West | AH5: East | AI5: 199672.35
A6: Amanda Powell | B6: 45297 | C6: 1833.438 | D6: Credit Card | E6: 21 | F6: Male | G6: Beauty | H6: North | L6: 45297 | M6: 1833.438 | R6: Credit Card | S6: 1833.438 | T6: PayPal | U6: 756718.1 | W6: Male | X6: Beauty | Y6: 1833.438 | Z6: Clothing | AA6: 155935.59 | AB6: 166848.67 | AC6: 322784.26 | AF6: 1833.438 | AG6: North | AH6: North | AI6: 1380704.5
A7: Anthony Phillips | B7: 45499 | C7: 357.2343 | D7: COD | E7: 21 | F7: Female | G7: Electronics | H7: South | L7: 45499 | M7: 357.2343 | R7: COD | S7: 357.2343 | T7: Grand Total | U7: 2175265 | W7: Female | X7: Electronics | Y7: 357.2343 | Z7: Electronics | AA7: 281133.04 | AB7: 222031.8 | AC7: 503164.84 | AF7: 357.2343 | AG7: South | AH7: South | AI7: 435916.67
A8: John Scott | B8: 45850 | C8: 1335.027 | D8: PayPal | E8: 60 | F8: Female | G8: Home | H8: South | L8: 45850 | M8: 1335.027 | R8: PayPal | S8: 1335.027 | W8: Female | X8: Home | Y8: 1335.027 | Z8: Home | AA8: 217025.26 | AB8: 231524.56 | AC8: 448549.82 | AF8: 1335.027 | AG8: South | AH8: West | AI8: 158971.46
A9: Patrick Roberts | B9: 45248 | C9: 1054.5612 | D9: PayPal | E9: 31 | F9: Male | G9: Home | H9: West | L9: 45248 | M9: 1054.5612 | R9: PayPal | S9: 1054.5612 | W9: Male | X9: Home | Y9: 1054.5612 | Z9: Sports | AA9: 276719.29 | AB9: 267966.82 | AC9: 544686.11 | AF9: 1054.5612 | AG9: West | AH9: Grand Total | AI9: 2175265
A10: Dr. Suzanne Bullock | B10: 45781 | C10: 1250.6175 | D10: PayPal | E10: 42 | F10: Male | G10: Home | H10: North | L10: 45781 | M10: 1250.6175 | R10: PayPal | S10: 1250.6175 | W10: Male | X10: Home | Y10: 1250.6175 | Z10: Grand Total | AA10: 1111157.5 | AB10: 1064107.5 | AC10: 2175265 | AF10: 1250.6175 | AG10: North
A11: David Pierce | B11: 45869 | C11: 1344.6818 | D11: PayPal | E11: 28 | F11: Female | G11: Home | H11: East | L11: 45869 | M11: 1344.6818 | R11: PayPal | S11: 1344.6818 | W11: Female | X11: Home | Y11: 1344.6818 | AF11: 1344.6818 | AG11: East
A12: Michael Thomas | B12: 45335 | C12: 259.1259 | D12: Credit Card | E12: 27 | F12: Female | G12: Sports | H12: North | L12: 45335 | M12: 259.1259 | R12: Credit Card | S12: 259.1259 | W12: Female | X12: Sports | Y12: 259.1259 | AF12: 259.1259 | AG12: North
A13: Jessica Gonzalez | B13: 45801 | C13: 952.5744 | D13: Credit Card | E13: 21 | F13: Female | G13: Electronics | H13: North | L13: 45801 | M13: 952.5744 | R13: Credit Card | S13: 952.5744 | W13: Female | X13: Electronics | Y13: 952.5744 | AF13: 952.5744 | AG13: North
A14: Wesley Short | B14: 45528 | C14: 2552.5368 | D14: Credit Card | E14: 40 | F14: Male | G14: Sports | H14: South | L14: 45528 | M14: 2552.5368 | R14: Credit Card | S14: 2552.5368 | W14: Male | X14: Sports | Y14: 2552.5368 | AF14: 2552.5368 | AG14: South
A15: Adam Castro | B15: 45875 | C15: 443.66 | D15: PayPal | E15: 19 | F15: Male | G15: Electronics | H15: North | L15: 45875 | M15: 443.66 | R15: PayPal | S15: 443.66 | W15: Male | X15: Electronics | Y15: 443.66 | AF15: 443.66 | AG15: North
A16: Sherry Cabrera | B16: 45829 | C16: 1145.8548 | D16: PayPal | E16: 31 | F16: Male | G16: Sports | H16: North | L16: 45829 | M16: 1145.8548 | R16: PayPal | S16: 1145.8548 | W16: Male | X16: Sports | Y16: 1145.8548 | AF16: 1145.8548 | AG16: North
A17: Lindsay Beasley | B17: 45636 | C17: 2509.4592 | D17: COD | E17: 61 | F17: Male | G17: Clothing | H17: South | L17: 45636 | M17: 2509.4592 | R17: COD | S17: 2509.4592 | W17: Male | X17: Clothing | Y17: 2509.4592 | AF17: 2509.4592 | AG17: South
A18: Arthur Warren | B18: 45913 | C18: 677.97 | D18: Credit Card | E18: 22 | F18: Female | G18: Sports | H18: North | L18: 45913 | M18: 677.97 | R18: Credit Card | S18: 677.97 | W18: Female | X18: Sports | Y18: 677.97 | AF18: 677.97 | AG18: North
A19: Molly Gardner | B19: 45637 | C19: 774.1426 | D19: Credit Card | E19: 61 | F19: Female | G19: Home | H19: South | L19: 45637 | M19: 774.1426 | R19: Credit Card | S19: 774.1426 | W19: Female | X19: Home | Y19: 774.1426 | AF19: 774.1426 | AG19: South
A20: David Patterson | B20: 45517 | C20: 838.845 | D20: COD | E20: 62 | F20: Female | G20: Electronics | H20: South | L20: 45517 | M20: 838.845 | R20: COD | S20: 838.845 | W20: Female | X20: Electronics | Y20: 838.845 | AF20: 838.845 | AG20: South
A21: Maria Hill | B21: 45369 | C21: 1782.4512 | D21: COD | E21: 59 | F21: Female | G21: Beauty | H21: North | L21: 45369 | M21: 1782.4512 | R21: COD | S21: 1782.4512 | W21: Female | X21: Beauty | Y21: 1782.4512 | AF21: 1782.4512 | AG21: North
A22: Justin Cross | B22: 45843 | C22: 2159.4276 | D22: COD | E22: 46 | F22: Male | G22: Sports | H22: North | L22: 45843 | M22: 2159.4276 | R22: COD | S22: 2159.4276 | W22: Male | X22: Sports | Y22: 2159.4276 | AF22: 2159.4276 | AG22: North
... A2001: Jonathan Steele | B2001: 45267 | C2001: 170.4405 | D2001: PayPal | E2001: 40 | F2001: Male | G2001: Electronics | H2001: North | L2001: 45267 | M2001: 170.4405 | R2001: PayPal | S2001: 170.4405 | W2001: Male | X2001: Electronics | Y2001: 170.4405 | AF2001: 170.4405 | AG2001: North

Sheet Dashboard
